Workbook

Sheet overview
A1: The analysis of the `delegated_tasks` data reveals insights into task performance across different categories.
A3: Here are the key takeaways: * **Overall Task Performance by Category:**
A4: * The `computer_programmers` category has the highest pass rate at approximately 94.12%, with 16 out of 17 tasks passed.
A5: * The `hr` category also shows a strong performance, with a pass rate of 90.00% (18 out of 20 tasks passed).
A6: * `marketing` and `operations` categories have moderate pass rates of 82.35% and 78.57% respectively.

Sheet delegated_tasks
B1: Task ID | C1: Member IDs | D1: Agent IDs | E1: Created At | F1: Updated At | G1: deepflow_task_id | H1: category | I1: Passed
A2: 0 | B2: 295 | C2: 30 | D2: 11 | E2: 2025-07-27T18:28:54.700Z | F2: 2025-07-27T18:28:54.700Z | G2: =VLOOKUP(B2,tasks!B2:C74,2,FALSE) -> computer_programmers_0 | H2: =LEFT(G2,FIND("_"&RIGHT(G2,LEN(G2)-FIND("@",SUBSTITUTE(G2,"_","@",LEN(G2)-LEN(SUBSTITUTE(G2,"_",""))))),G2)-1) -> computer_programmers | I2: TRUE
A3: 1 | B3: 296 | C3: 30 | D3: 11 | E3: 2025-07-27T18:29:00.737Z | F3: 2025-07-27T18:29:00.737Z | G3: =VLOOKUP(B3,tasks!B3:C75,2,FALSE) -> computer_programmers_1 | H3: =LEFT(G3,FIND("_"&RIGHT(G3,LEN(G3)-FIND("@",SUBSTITUTE(G3,"_","@",LEN(G3)-LEN(SUBSTITUTE(G3,"_",""))))),G3)-1) -> computer_programmers | I3: TRUE
A4: 2 | B4: 297 | C4: 30 | D4: 11 | E4: 2025-07-27T18:29:07.144Z | F4: 2025-07-27T18:29:07.144Z | G4: =VLOOKUP(B4,tasks!B4:C76,2,FALSE) -> computer_programmers_2 | H4: =LEFT(G4,FIND("_"&RIGHT(G4,LEN(G4)-FIND("@",SUBSTITUTE(G4,"_","@",LEN(G4)-LEN(SUBSTITUTE(G4,"_",""))))),G4)-1) -> computer_programmers | I4: TRUE
A5: 3 | B5: 298 | C5: 30 | D5: 11 | E5: 2025-07-27T18:29:18.458Z | F5: 2025-07-27T18:29:18.458Z | G5: =VLOOKUP(B5,tasks!B5:C77,2,FALSE) -> computer_programmers_3 | H5: =LEFT(G5,FIND("_"&RIGHT(G5,LEN(G5)-FIND("@",SUBSTITUTE(G5,"_","@",LEN(G5)-LEN(SUBSTITUTE(G5,"_",""))))),G5)-1) -> computer_programmers | I5: TRUE
A6: 4 | B6: 299 | C6: 30 | D6: 11 | E6: 2025-07-27T18:29:26.971Z | F6: 2025-07-27T18:29:26.971Z | G6: =VLOOKUP(B6,tasks!B6:C78,2,FALSE) -> computer_programmers_4 | H6: =LEFT(G6,FIND("_"&RIGHT(G6,LEN(G6)-FIND("@",SUBSTITUTE(G6,"_","@",LEN(G6)-LEN(SUBSTITUTE(G6,"_",""))))),G6)-1) -> computer_programmers | I6: TRUE
A7: 5 | B7: 300 | C7: 30,26 | D7: 11 | E7: 2025-07-27T18:29:34.938Z | F7: 2025-07-27T18:29:34.938Z | G7: =VLOOKUP(B7,tasks!B7:C79,2,FALSE) -> computer_programmers_5 | H7: =LEFT(G7,FIND("_"&RIGHT(G7,LEN(G7)-FIND("@",SUBSTITUTE(G7,"_","@",LEN(G7)-LEN(SUBSTITUTE(G7,"_",""))))),G7)-1) -> computer_programmers | I7: TRUE
A8: 6 | B8: 301 | C8: 30 | D8: 11 | E8: 2025-07-27T18:29:41.885Z | F8: 2025-07-27T18:29:41.885Z | G8: =VLOOKUP(B8,tasks!B8:C80,2,FALSE) -> computer_programmers_6 | H8: =LEFT(G8,FIND("_"&RIGHT(G8,LEN(G8)-FIND("@",SUBSTITUTE(G8,"_","@",LEN(G8)-LEN(SUBSTITUTE(G8,"_",""))))),G8)-1) -> computer_programmers | I8: TRUE
A9: 7 | B9: 302 | C9: 30 | D9: 11 | E9: 2025-07-27T18:29:49.900Z | F9: 2025-07-27T18:29:49.900Z | G9: =VLOOKUP(B9,tasks!B9:C81,2,FALSE) -> computer_programmers_7 | H9: =LEFT(G9,FIND("_"&RIGHT(G9,LEN(G9)-FIND("@",SUBSTITUTE(G9,"_","@",LEN(G9)-LEN(SUBSTITUTE(G9,"_",""))))),G9)-1) -> computer_programmers | I9: TRUE | J9: 30 | K9: 11
A10: 8 | B10: 303 | C10: 30 | D10: 11 | E10: 2025-07-27T18:29:56.575Z | F10: 2025-07-27T18:29:56.575Z | G10: =VLOOKUP(B10,tasks!B10:C82,2,FALSE) -> computer_programmers_8 | H10: =LEFT(G10,FIND("_"&RIGHT(G10,LEN(G10)-FIND("@",SUBSTITUTE(G10,"_","@",LEN(G10)-LEN(SUBSTITUTE(G10,"_",""))))),G10)-1) -> computer_programmers | I10: TRUE
A11: 9 | B11: 304 | C11: 30 | D11: 11 | E11: 2025-07-27T18:30:03.689Z | F11: 2025-07-27T18:30:03.689Z | G11: =VLOOKUP(B11,tasks!B11:C83,2,FALSE) -> computer_programmers_9 | H11: =LEFT(G11,FIND("_"&RIGHT(G11,LEN(G11)-FIND("@",SUBSTITUTE(G11,"_","@",LEN(G11)-LEN(SUBSTITUTE(G11,"_",""))))),G11)-1) -> computer_programmers | I11: TRUE
A12: 10 | B12: 305 | C12: 27 | D12: 9,8 | E12: 2025-07-27T18:30:20.976Z | F12: 2025-07-27T18:30:20.976Z | G12: =VLOOKUP(B12,tasks!B12:C84,2,FALSE) -> computer_programmers_10 | H12: =LEFT(G12,FIND("_"&RIGHT(G12,LEN(G12)-FIND("@",SUBSTITUTE(G12,"_","@",LEN(G12)-LEN(SUBSTITUTE(G12,"_",""))))),G12)-1) -> computer_programmers | I12: FALSE
A13: 11 | B13: 306 | C13: 30 | D13: 11,10 | E13: 2025-07-27T18:30:28.386Z | F13: 2025-07-27T18:30:28.386Z | G13: =VLOOKUP(B13,tasks!B13:C85,2,FALSE) -> computer_programmers_11 | H13: =LEFT(G13,FIND("_"&RIGHT(G13,LEN(G13)-FIND("@",SUBSTITUTE(G13,"_","@",LEN(G13)-LEN(SUBSTITUTE(G13,"_",""))))),G13)-1) -> computer_programmers | I13: TRUE
A14: 12 | B14: 307 | C14: 30,26 | D14: 11 | E14: 2025-07-27T18:30:38.678Z | F14: 2025-07-27T18:30:38.678Z | G14: =VLOOKUP(B14,tasks!B14:C86,2,FALSE) -> computer_programmers_12 | H14: =LEFT(G14,FIND("_"&RIGHT(G14,LEN(G14)-FIND("@",SUBSTITUTE(G14,"_","@",LEN(G14)-LEN(SUBSTITUTE(G14,"_",""))))),G14)-1) -> computer_programmers | I14: TRUE
A15: 13 | B15: 308 | C15: 30 | D15: 11 | E15: 2025-07-27T18:30:45.873Z | F15: 2025-07-27T18:30:45.873Z | G15: =VLOOKUP(B15,tasks!B15:C87,2,FALSE) -> computer_programmers_13 | H15: =LEFT(G15,FIND("_"&RIGHT(G15,LEN(G15)-FIND("@",SUBSTITUTE(G15,"_","@",LEN(G15)-LEN(SUBSTITUTE(G15,"_",""))))),G15)-1) -> computer_programmers | I15: TRUE
A16: 14 | B16: 309 | C16: 30,27 | D16: 11 | E16: 2025-07-27T18:30:57.492Z | F16: 2025-07-27T18:30:57.492Z | G16: =VLOOKUP(B16,tasks!B16:C88,2,FALSE) -> computer_programmers_14 | H16: =LEFT(G16,FIND("_"&RIGHT(G16,LEN(G16)-FIND("@",SUBSTITUTE(G16,"_","@",LEN(G16)-LEN(SUBSTITUTE(G16,"_",""))))),G16)-1) -> computer_programmers | I16: TRUE
A17: 15 | B17: 310 | C17: 30 | D17: 11 | E17: 2025-07-27T18:31:03.746Z | F17: 2025-07-27T18:31:03.746Z | G17: =VLOOKUP(B17,tasks!B17:C89,2,FALSE) -> computer_programmers_15 | H17: =LEFT(G17,FIND("_"&RIGHT(G17,LEN(G17)-FIND("@",SUBSTITUTE(G17,"_","@",LEN(G17)-LEN(SUBSTITUTE(G17,"_",""))))),G17)-1) -> computer_programmers | I17: TRUE
A18: 16 | B18: 311 | C18: 30,26 | D18: 11 | E18: 2025-07-27T18:31:11.147Z | F18: 2025-07-27T18:31:11.147Z | G18: =VLOOKUP(B18,tasks!B18:C90,2,FALSE) -> computer_programmers_16 | H18: =LEFT(G18,FIND("_"&RIGHT(G18,LEN(G18)-FIND("@",SUBSTITUTE(G18,"_","@",LEN(G18)-LEN(SUBSTITUTE(G18,"_",""))))),G18)-1) -> computer_programmers | I18: TRUE
A19: 36 | B19: 332 | C19: 26,29 | D19: 10,7 | E19: 2025-07-27T18:34:08.570Z | F19: 2025-07-27T18:34:08.570Z | G19: =VLOOKUP(B19,tasks!B19:C110,2,FALSE) -> operations_1 | H19: =LEFT(G19,FIND("_"&RIGHT(G19,LEN(G19)-FIND("@",SUBSTITUTE(G19,"_","@",LEN(G19)-LEN(SUBSTITUTE(G19,"_",""))))),G19)-1) -> operations | I19: TRUE
A20: 37 | B20: 333 | C20: 26 | D20: 10 | E20: 2025-07-27T18:34:16.205Z | F20: 2025-07-27T18:34:16.205Z | G20: =VLOOKUP(B20,tasks!B20:C111,2,FALSE) -> operations_2 | H20: =LEFT(G20,FIND("_"&RIGHT(G20,LEN(G20)-FIND("@",SUBSTITUTE(G20,"_","@",LEN(G20)-LEN(SUBSTITUTE(G20,"_",""))))),G20)-1) -> operations | I20: TRUE
A21: 38 | B21: 334 | C21: 29 | D21: 8 | E21: 2025-07-27T18:34:24.821Z | F21: 2025-07-27T18:34:24.821Z | G21: =VLOOKUP(B21,tasks!B21:C112,2,FALSE) -> operations_3 | H21: =LEFT(G21,FIND("_"&RIGHT(G21,LEN(G21)-FIND("@",SUBSTITUTE(G21,"_","@",LEN(G21)-LEN(SUBSTITUTE(G21,"_",""))))),G21)-1) -> operations | I21: FALSE
A22: 39 | B22: 335 | C22: 26 | D22: 7 | E22: 2025-07-27T18:34:30.443Z | F22: 2025-07-27T18:34:30.443Z | G22: =VLOOKUP(B22,tasks!B22:C113,2,FALSE) -> operations_4 | H22: =LEFT(G22,FIND("_"&RIGHT(G22,LEN(G22)-FIND("@",SUBSTITUTE(G22,"_","@",LEN(G22)-LEN(SUBSTITUTE(G22,"_",""))))),G22)-1) -> operations | I22: TRUE
A23: 40 | B23: 336 | C23: 27,26 | D23: 9 | E23: 2025-07-27T18:34:37.796Z | F23: 2025-07-27T18:34:37.796Z | G23: =VLOOKUP(B23,tasks!B23:C114,2,FALSE) -> operations_5 | H23: =LEFT(G23,FIND("_"&RIGHT(G23,LEN(G23)-FIND("@",SUBSTITUTE(G23,"_","@",LEN(G23)-LEN(SUBSTITUTE(G23,"_",""))))),G23)-1) -> operations | I23: TRUE
A24: 41 | B24: 337 | C24: 29 | D24: 8 | E24: 2025-07-27T18:34:45.381Z | F24: 2025-07-27T18:34:45.381Z | G24: =VLOOKUP(B24,tasks!B24:C115,2,FALSE) -> operations_6 | H24: =LEFT(G24,FIND("_"&RIGHT(G24,LEN(G24)-FIND("@",SUBSTITUTE(G24,"_","@",LEN(G24)-LEN(SUBSTITUTE(G24,"_",""))))),G24)-1) -> operations | I24: FALSE
A25: 42 | B25: 338 | C25: 29,26 | D25: 10 | E25: 2025-07-27T18:34:53.405Z | F25: 2025-07-27T18:34:53.405Z | G25: =VLOOKUP(B25,tasks!B25:C116,2,FALSE) -> operations_7 | H25: =LEFT(G25,FIND("_"&RIGHT(G25,LEN(G25)-FIND("@",SUBSTITUTE(G25,"_","@",LEN(G25)-LEN(SUBSTITUTE(G25,"_",""))))),G25)-1) -> operations | I25: TRUE
A26: 43 | B26: 339 | C26: 26 | D26: 10 | E26: 2025-07-27T18:35:04.471Z | F26: 2025-07-27T18:35:04.471Z | G26: =VLOOKUP(B26,tasks!B26:C117,2,FALSE) -> operations_8 | H26: =LEFT(G26,FIND("_"&RIGHT(G26,LEN(G26)-FIND("@",SUBSTITUTE(G26,"_","@",LEN(G26)-LEN(SUBSTITUTE(G26,"_",""))))),G26)-1) -> operations | I26: TRUE | J26: 10 | K26: 26
A27: 44 | B27: 340 | C27: 26,27 | D27: 10 | E27: 2025-07-27T18:35:13.413Z | F27: 2025-07-27T18:35:13.413Z | G27: =VLOOKUP(B27,tasks!B27:C118,2,FALSE) -> operations_9 | H27: =LEFT(G27,FIND("_"&RIGHT(G27,LEN(G27)-FIND("@",SUBSTITUTE(G27,"_","@",LEN(G27)-LEN(SUBSTITUTE(G27,"_",""))))),G27)-1) -> operations | I27: TRUE
A28: 45 | B28: 341 | C28: 26 | D28: 7 | E28: 2025-07-27T18:35:20.202Z | F28: 2025-07-27T18:35:20.202Z | G28: =VLOOKUP(B28,tasks!B28:C119,2,FALSE) -> operations_10 | H28: =LEFT(G28,FIND("_"&RIGHT(G28,LEN(G28)-FIND("@",SUBSTITUTE(G28,"_","@",LEN(G28)-LEN(SUBSTITUTE(G28,"_",""))))),G28)-1) -> operations | I28: TRUE
A29: 46 | B29: 342 | C29: 27 | D29: 10 | E29: 2025-07-27T18:35:27.212Z | F29: 2025-07-27T18:35:27.212Z | G29: =VLOOKUP(B29,tasks!B29:C120,2,FALSE) -> operations_11 | H29: =LEFT(G29,FIND("_"&RIGHT(G29,LEN(G29)-FIND("@",SUBSTITUTE(G29,"_","@",LEN(G29)-LEN(SUBSTITUTE(G29,"_",""))))),G29)-1) -> operations | I29: TRUE
A30: 47 | B30: 343 | C30: 27 | D30: 9 | E30: 2025-07-27T18:35:36.062Z | F30: 2025-07-27T18:35:36.062Z | G30: =VLOOKUP(B30,tasks!B30:C121,2,FALSE) -> operations_12 | H30: =LEFT(G30,FIND("_"&RIGHT(G30,LEN(G30)-FIND("@",SUBSTITUTE(G30,"_","@",LEN(G30)-LEN(SUBSTITUTE(G30,"_",""))))),G30)-1) -> operations | I30: FALSE
A31: 48 | B31: 344 | C31: 27 | D31: 10 | E31: 2025-07-27T18:35:48.828Z | F31: 2025-07-27T18:35:48.828Z | G31: =VLOOKUP(B31,tasks!B31:C122,2,FALSE) -> operations_15 | H31: =LEFT(G31,FIND("_"&RIGHT(G31,LEN(G31)-FIND("@",SUBSTITUTE(G31,"_","@",LEN(G31)-LEN(SUBSTITUTE(G31,"_",""))))),G31)-1) -> operations | I31: TRUE
A32: 49 | B32: 345 | C32: 26 | D32: 10,7 | E32: 2025-07-27T18:36:01.112Z | F32: 2025-07-27T18:36:01.112Z | G32: =VLOOKUP(B32,tasks!B32:C123,2,FALSE) -> operations_16 | H32: =LEFT(G32,FIND("_"&RIGHT(G32,LEN(G32)-FIND("@",SUBSTITUTE(G32,"_","@",LEN(G32)-LEN(SUBSTITUTE(G32,"_",""))))),G32)-1) -> operations | I32: TRUE
A33: 50 | B33: 346 | C33: 27 | D33: 9 | E33: 2025-07-27T18:36:10.070Z | F33: 2025-07-27T18:36:10.070Z | G33: =VLOOKUP(B33,tasks!B33:C124,2,FALSE) -> marketing_0 | H33: =LEFT(G33,FIND("_"&RIGHT(G33,LEN(G33)-FIND("@",SUBSTITUTE(G33,"_","@",LEN(G33)-LEN(SUBSTITUTE(G33,"_",""))))),G33)-1) -> marketing | I33: TRUE
A34: 51 | B34: 347 | C34: 26 | D34: 7 | E34: 2025-07-27T18:36:23.460Z | F34: 2025-07-27T18:36:23.460Z | G34: =VLOOKUP(B34,tasks!B34:C125,2,FALSE) -> marketing_2 | H34: =LEFT(G34,FIND("_"&RIGHT(G34,LEN(G34)-FIND("@",SUBSTITUTE(G34,"_","@",LEN(G34)-LEN(SUBSTITUTE(G34,"_",""))))),G34)-1) -> marketing | I34: FALSE | M34: 1. TASK : have subtask, its from same domain person
A35: 52 | B35: 348 | C35: 27,26 | D35: 9 | E35: 2025-07-27T18:36:31.760Z | F35: 2025-07-27T18:36:31.760Z | G35: =VLOOKUP(B35,tasks!B35:C126,2,FALSE) -> marketing_3 | H35: =LEFT(G35,FIND("_"&RIGHT(G35,LEN(G35)-FIND("@",SUBSTITUTE(G35,"_","@",LEN(G35)-LEN(SUBSTITUTE(G35,"_",""))))),G35)-1) -> marketing | I35: TRUE
A36: 53 | B36: 349 | C36: 27 | D36: 9 | E36: 2025-07-27T18:36:41.297Z | F36: 2025-07-27T18:36:41.297Z | G36: =VLOOKUP(B36,tasks!B36:C127,2,FALSE) -> marketing_4 | H36: =LEFT(G36,FIND("_"&RIGHT(G36,LEN(G36)-FIND("@",SUBSTITUTE(G36,"_","@",LEN(G36)-LEN(SUBSTITUTE(G36,"_",""))))),G36)-1) -> marketing | I36: TRUE
A37: 54 | B37: 350 | C37: 29,27 | D37: 9 | E37: 2025-07-27T18:36:49.883Z | F37: 2025-07-27T18:36:49.883Z | G37: =VLOOKUP(B37,tasks!B37:C128,2,FALSE) -> marketing_5 | H37: =LEFT(G37,FIND("_"&RIGHT(G37,LEN(G37)-FIND("@",SUBSTITUTE(G37,"_","@",LEN(G37)-LEN(SUBSTITUTE(G37,"_",""))))),G37)-1) -> marketing | I37: TRUE
A38: 55 | B38: 351 | C38: 27 | D38: 9 | E38: 2025-07-27T18:36:59.382Z | F38: 2025-07-27T18:36:59.382Z | G38: =VLOOKUP(B38,tasks!B38:C129,2,FALSE) -> marketing_6 | H38: =LEFT(G38,FIND("_"&RIGHT(G38,LEN(G38)-FIND("@",SUBSTITUTE(G38,"_","@",LEN(G38)-LEN(SUBSTITUTE(G38,"_",""))))),G38)-1) -> marketing | I38: TRUE | J38: 27 | K38: 9
A39: 56 | B39: 352 | C39: 27 | D39: 9,7 | E39: 2025-07-27T18:37:05.840Z | F39: 2025-07-27T18:37:05.840Z | G39: =VLOOKUP(B39,tasks!B39:C130,2,FALSE) -> marketing_7 | H39: =LEFT(G39,FIND("_"&RIGHT(G39,LEN(G39)-FIND("@",SUBSTITUTE(G39,"_","@",LEN(G39)-LEN(SUBSTITUTE(G39,"_",""))))),G39)-1) -> marketing | I39: TRUE
A40: 57 | B40: 353 | C40: 26 | D40: 10 | E40: 2025-07-27T18:37:11.888Z | F40: 2025-07-27T18:37:11.888Z | G40: =VLOOKUP(B40,tasks!B40:C131,2,FALSE) -> marketing_8 | H40: =LEFT(G40,FIND("_"&RIGHT(G40,LEN(G40)-FIND("@",SUBSTITUTE(G40,"_","@",LEN(G40)-LEN(SUBSTITUTE(G40,"_",""))))),G40)-1) -> marketing | I40: FALSE
A41: 58 | B41: 354 | C41: 27,26 | D41: 9 | E41: 2025-07-27T18:37:19.975Z | F41: 2025-07-27T18:37:19.975Z | G41: =VLOOKUP(B41,tasks!B41:C132,2,FALSE) -> marketing_9 | H41: =LEFT(G41,FIND("_"&RIGHT(G41,LEN(G41)-FIND("@",SUBSTITUTE(G41,"_","@",LEN(G41)-LEN(SUBSTITUTE(G41,"_",""))))),G41)-1) -> marketing | I41: TRUE
A42: 59 | B42: 355 | C42: 27 | D42: 9 | E42: 2025-07-27T18:37:27.161Z | F42: 2025-07-27T18:37:27.161Z | G42: =VLOOKUP(B42,tasks!B42:C133,2,FALSE) -> marketing_10 | H42: =LEFT(G42,FIND("_"&RIGHT(G42,LEN(G42)-FIND("@",SUBSTITUTE(G42,"_","@",LEN(G42)-LEN(SUBSTITUTE(G42,"_",""))))),G42)-1) -> marketing | I42: TRUE
A43: 60 | B43: 356 | C43: 29 | D43: 11 | E43: 2025-07-27T18:37:34.054Z | F43: 2025-07-27T18:37:34.054Z | G43: =VLOOKUP(B43,tasks!B43:C134,2,FALSE) -> marketing_11 | H43: =LEFT(G43,FIND("_"&RIGHT(G43,LEN(G43)-FIND("@",SUBSTITUTE(G43,"_","@",LEN(G43)-LEN(SUBSTITUTE(G43,"_",""))))),G43)-1) -> marketing | I43: FALSE
A44: 61 | B44: 357 | C44: 27 | D44: 9 | E44: 2025-07-27T18:37:40.998Z | F44: 2025-07-27T18:37:40.998Z | G44: =VLOOKUP(B44,tasks!B44:C135,2,FALSE) -> marketing_12 | H44: =LEFT(G44,FIND("_"&RIGHT(G44,LEN(G44)-FIND("@",SUBSTITUTE(G44,"_","@",LEN(G44)-LEN(SUBSTITUTE(G44,"_",""))))),G44)-1) -> marketing | I44: TRUE
A45: 62 | B45: 358 | C45: 27 | D45: 9 | E45: 2025-07-27T18:37:47.504Z | F45: 2025-07-27T18:37:47.504Z | G45: =VLOOKUP(B45,tasks!B45:C136,2,FALSE) -> marketing_13 | H45: =LEFT(G45,FIND("_"&RIGHT(G45,LEN(G45)-FIND("@",SUBSTITUTE(G45,"_","@",LEN(G45)-LEN(SUBSTITUTE(G45,"_",""))))),G45)-1) -> marketing | I45: TRUE
A46: 63 | B46: 359 | C46: 27 | D46: 9,10 | E46: 2025-07-27T18:37:57.240Z | F46: 2025-07-27T18:37:57.240Z | G46: =VLOOKUP(B46,tasks!B46:C137,2,FALSE) -> marketing_14 | H46: =LEFT(G46,FIND("_"&RIGHT(G46,LEN(G46)-FIND("@",SUBSTITUTE(G46,"_","@",LEN(G46)-LEN(SUBSTITUTE(G46,"_",""))))),G46)-1) -> marketing | I46: TRUE
A47: 64 | B47: 360 | C47: 26,27 | D47: 10 | E47: 2025-07-27T18:38:03.819Z | F47: 2025-07-27T18:38:03.819Z | G47: =VLOOKUP(B47,tasks!B47:C138,2,FALSE) -> marketing_15 | H47: =LEFT(G47,FIND("_"&RIGHT(G47,LEN(G47)-FIND("@",SUBSTITUTE(G47,"_","@",LEN(G47)-LEN(SUBSTITUTE(G47,"_",""))))),G47)-1) -> marketing | I47: TRUE
A48: 65 | B48: 361 | C48: 26 | D48: 9 | E48: 2025-07-27T18:38:10.634Z | F48: 2025-07-27T18:38:10.634Z | G48: =VLOOKUP(B48,tasks!B48:C139,2,FALSE) -> marketing_16 | H48: =LEFT(G48,FIND("_"&RIGHT(G48,LEN(G48)-FIND("@",SUBSTITUTE(G48,"_","@",LEN(G48)-LEN(SUBSTITUTE(G48,"_",""))))),G48)-1) -> marketing | I48: TRUE
A49: 66 | B49: 363 | C49: 27,29 | D49: 9 | E49: 2025-07-27T18:38:30.065Z | F49: 2025-07-27T18:38:30.065Z | G49: =VLOOKUP(B49,tasks!B49:C140,2,FALSE) -> marketing_19 | H49: =LEFT(G49,FIND("_"&RIGHT(G49,LEN(G49)-FIND("@",SUBSTITUTE(G49,"_","@",LEN(G49)-LEN(SUBSTITUTE(G49,"_",""))))),G49)-1) -> marketing | I49: TRUE
A50: 67 | B50: 364 | C50: 29 | D50: 8 | E50: 2025-07-27T18:38:37.416Z | F50: 2025-07-27T18:38:37.416Z | G50: =VLOOKUP(B50,tasks!B50:C141,2,FALSE) -> hr_0 | H50: =LEFT(G50,FIND("_"&RIGHT(G50,LEN(G50)-FIND("@",SUBSTITUTE(G50,"_","@",LEN(G50)-LEN(SUBSTITUTE(G50,"_",""))))),G50)-1) -> hr | I50: TRUE
A51: 68 | B51: 365 | C51: 29 | D51: 8 | E51: 2025-07-27T18:38:44.835Z | F51: 2025-07-27T18:38:44.835Z | G51: =VLOOKUP(B51,tasks!B51:C142,2,FALSE) -> hr_1 | H51: =LEFT(G51,FIND("_"&RIGHT(G51,LEN(G51)-FIND("@",SUBSTITUTE(G51,"_","@",LEN(G51)-LEN(SUBSTITUTE(G51,"_",""))))),G51)-1) -> hr | I51: TRUE
A52: 69 | B52: 366 | C52: 29 | D52: 8 | E52: 2025-07-27T18:38:53.462Z | F52: 2025-07-27T18:38:53.462Z | G52: =VLOOKUP(B52,tasks!B52:C143,2,FALSE) -> hr_2 | H52: =LEFT(G52,FIND("_"&RIGHT(G52,LEN(G52)-FIND("@",SUBSTITUTE(G52,"_","@",LEN(G52)-LEN(SUBSTITUTE(G52,"_",""))))),G52)-1) -> hr | I52: TRUE
A53: 70 | B53: 367 | C53: 29 | D53: 8 | E53: 2025-07-27T18:39:00.649Z | F53: 2025-07-27T18:39:00.649Z | G53: =VLOOKUP(B53,tasks!B53:C144,2,FALSE) -> hr_3 | H53: =LEFT(G53,FIND("_"&RIGHT(G53,LEN(G53)-FIND("@",SUBSTITUTE(G53,"_","@",LEN(G53)-LEN(SUBSTITUTE(G53,"_",""))))),G53)-1) -> hr | I53: TRUE
A54: 71 | B54: 368 | C54: 29 | D54: 8 | E54: 2025-07-27T18:39:08.404Z | F54: 2025-07-27T18:39:08.404Z | G54: =VLOOKUP(B54,tasks!B54:C145,2,FALSE) -> hr_5 | H54: =LEFT(G54,FIND("_"&RIGHT(G54,LEN(G54)-FIND("@",SUBSTITUTE(G54,"_","@",LEN(G54)-LEN(SUBSTITUTE(G54,"_",""))))),G54)-1) -> hr | I54: TRUE
A55: 72 | B55: 369 | C55: 29 | D55: 8 | E55: 2025-07-27T18:39:15.718Z | F55: 2025-07-27T18:39:15.718Z | G55: =VLOOKUP(B55,tasks!B55:C146,2,FALSE) -> hr_6 | H55: =LEFT(G55,FIND("_"&RIGHT(G55,LEN(G55)-FIND("@",SUBSTITUTE(G55,"_","@",LEN(G55)-LEN(SUBSTITUTE(G55,"_",""))))),G55)-1) -> hr | I55: TRUE
A56: 73 | B56: 370 | C56: 29 | D56: 8 | E56: 2025-07-27T18:39:23.376Z | F56: 2025-07-27T18:39:23.376Z | G56: =VLOOKUP(B56,tasks!B56:C147,2,FALSE) -> hr_7 | H56: =LEFT(G56,FIND("_"&RIGHT(G56,LEN(G56)-FIND("@",SUBSTITUTE(G56,"_","@",LEN(G56)-LEN(SUBSTITUTE(G56,"_",""))))),G56)-1) -> hr | I56: TRUE
A57: 74 | B57: 371 | C57: 29 | D57: 7 | E57: 2025-07-27T18:39:29.038Z | F57: 2025-07-27T18:39:29.038Z | G57: =VLOOKUP(B57,tasks!B57:C148,2,FALSE) -> hr_8 | H57: =LEFT(G57,FIND("_"&RIGHT(G57,LEN(G57)-FIND("@",SUBSTITUTE(G57,"_","@",LEN(G57)-LEN(SUBSTITUTE(G57,"_",""))))),G57)-1) -> hr | I57: TRUE
A58: 75 | B58: 372 | C58: 29 | D58: 8 | E58: 2025-07-27T18:39:36.721Z | F58: 2025-07-27T18:39:36.721Z | G58: =VLOOKUP(B58,tasks!B58:C149,2,FALSE) -> hr_9 | H58: =LEFT(G58,FIND("_"&RIGHT(G58,LEN(G58)-FIND("@",SUBSTITUTE(G58,"_","@",LEN(G58)-LEN(SUBSTITUTE(G58,"_",""))))),G58)-1) -> hr | I58: TRUE | J58: 29 | K58: 8
A59: 76 | B59: 373 | C59: 26,30 | D59: 10 | E59: 2025-07-27T18:39:44.070Z | F59: 2025-07-27T18:39:44.070Z | G59: =VLOOKUP(B59,tasks!B59:C150,2,FALSE) -> hr_10 | H59: =LEFT(G59,FIND("_"&RIGHT(G59,LEN(G59)-FIND("@",SUBSTITUTE(G59,"_","@",LEN(G59)-LEN(SUBSTITUTE(G59,"_",""))))),G59)-1) -> hr | I59: FALSE
A60: 77 | B60: 374 | C60: 29,26 | D60: 8 | E60: 2025-07-27T18:39:52.400Z | F60: 2025-07-27T18:39:52.400Z | G60: =VLOOKUP(B60,tasks!B60:C151,2,FALSE) -> hr_11 | H60: =LEFT(G60,FIND("_"&RIGHT(G60,LEN(G60)-FIND("@",SUBSTITUTE(G60,"_","@",LEN(G60)-LEN(SUBSTITUTE(G60,"_",""))))),G60)-1) -> hr | I60: TRUE
A61: 78 | B61: 376 | C61: 29 | D61: 8 | E61: 2025-07-27T18:40:10.510Z | F61: 2025-07-27T18:40:10.510Z | G61: =VLOOKUP(B61,tasks!B61:C152,2,FALSE) -> hr_14 | H61: =LEFT(G61,FIND("_"&RIGHT(G61,LEN(G61)-FIND("@",SUBSTITUTE(G61,"_","@",LEN(G61)-LEN(SUBSTITUTE(G61,"_",""))))),G61)-1) -> hr | I61: TRUE
A62: 79 | B62: 377 | C62: 29,26 | D62: 8,10 | E62: 2025-07-27T18:40:22.723Z | F62: 2025-07-27T18:40:22.723Z | G62: =VLOOKUP(B62,tasks!B62:C153,2,FALSE) -> hr_15 | H62: =LEFT(G62,FIND("_"&RIGHT(G62,LEN(G62)-FIND("@",SUBSTITUTE(G62,"_","@",LEN(G62)-LEN(SUBSTITUTE(G62,"_",""))))),G62)-1) -> hr | I62: TRUE
A63: 80 | B63: 378 | C63: 29,27 | D63: 8 | E63: 2025-07-27T18:40:33.047Z | F63: 2025-07-27T18:40:33.047Z | G63: =VLOOKUP(B63,tasks!B63:C154,2,FALSE) -> hr_16 | H63: =LEFT(G63,FIND("_"&RIGHT(G63,LEN(G63)-FIND("@",SUBSTITUTE(G63,"_","@",LEN(G63)-LEN(SUBSTITUTE(G63,"_",""))))),G63)-1) -> hr | I63: TRUE
A64: 81 | B64: 379 | C64: 29,27 | D64: 8 | E64: 2025-07-27T18:40:41.854Z | F64: 2025-07-27T18:40:41.854Z | G64: =VLOOKUP(B64,tasks!B64:C155,2,FALSE) -> hr_17 | H64: =LEFT(G64,FIND("_"&RIGHT(G64,LEN(G64)-FIND("@",SUBSTITUTE(G64,"_","@",LEN(G64)-LEN(SUBSTITUTE(G64,"_",""))))),G64)-1) -> hr | I64: TRUE
A65: 82 | B65: 381 | C65: 29 | D65: 8,10 | E65: 2025-07-27T18:40:56.514Z | F65: 2025-07-27T18:40:56.514Z | G65: =VLOOKUP(B65,tasks!B65:C156,2,FALSE) -> hr_19 | H65: =LEFT(G65,FIND("_"&RIGHT(G65,LEN(G65)-FIND("@",SUBSTITUTE(G65,"_","@",LEN(G65)-LEN(SUBSTITUTE(G65,"_",""))))),G65)-1) -> hr | I65: TRUE
A66: 83 | B66: 382 | C66: 26 | D66: 7 | E66: 2025-07-27T18:41:04.294Z | F66: 2025-07-27T18:41:04.294Z | G66: =VLOOKUP(B66,tasks!B66:C157,2,FALSE) -> hr_20 | H66: =LEFT(G66,FIND("_"&RIGHT(G66,LEN(G66)-FIND("@",SUBSTITUTE(G66,"_","@",LEN(G66)-LEN(SUBSTITUTE(G66,"_",""))))),G66)-1) -> hr | I66: FALSE
A67: 84 | B67: 383 | C67: 29 | D67: 8 | E67: 2025-07-27T18:41:12.750Z | F67: 2025-07-27T18:41:12.750Z | G67: =VLOOKUP(B67,tasks!B67:C158,2,FALSE) -> hr_21 | H67: =LEFT(G67,FIND("_"&RIGHT(G67,LEN(G67)-FIND("@",SUBSTITUTE(G67,"_","@",LEN(G67)-LEN(SUBSTITUTE(G67,"_",""))))),G67)-1) -> hr | I67: TRUE
A68: 85 | B68: 384 | C68: 29 | D68: 8 | E68: 2025-07-27T18:41:21.964Z | F68: 2025-07-27T18:41:21.964Z | G68: =VLOOKUP(B68,tasks!B68:C159,2,FALSE) -> hr_22 | H68: =LEFT(G68,FIND("_"&RIGHT(G68,LEN(G68)-FIND("@",SUBSTITUTE(G68,"_","@",LEN(G68)-LEN(SUBSTITUTE(G68,"_",""))))),G68)-1) -> hr | I68: TRUE
A69: 86 | B69: 385 | C69: 29,28 | D69: 8 | E69: 2025-07-27T18:41:28.992Z | F69: 2025-07-27T18:41:28.992Z | G69: =VLOOKUP(B69,tasks!B69:C160,2,FALSE) -> hr_23 | H69: =LEFT(G69,FIND("_"&RIGHT(G69,LEN(G69)-FIND("@",SUBSTITUTE(G69,"_","@",LEN(G69)-LEN(SUBSTITUTE(G69,"_",""))))),G69)-1) -> hr | I69: TRUE

Sheet tasks
B1: ID | C1: Deepflow ID | D1: Required Skills | E1: Sector | F1: Tags | G1: Manpower Needed | H1: Roles Required | I1: Estimated Time | J1: Embedding | K1: Created At
A2: 0 | B2: 295 | C2: computer_programmers_0 | D2: Programming,Workflow Chart Creation,Diagram Analysis,Computer Science Knowledge,Symbolic Logic | E2: Software Development | F2: Program Analysis,Software Review,Workflow Design | G2: 1 | H2: Software Developer | I2: 8 | J2: [0.008025651,-0.012875193,0.0051227557,-0.024397977,0.0029046026,0.007984668,-0.032758314,0.0040128254,0.00013287147,-0.022075662,0.013578718,0.00039551943,0.002366713,0.012335596,-0.008380828,-0.00033852877,0.002786779,-0.0071991794,0.008100784,-0.014767197,-0.023400748,0.025190298,0.002737259,-0.01242439,-0.016174247,0.032758314,0.011625241,-0.050790414,0.003684969,0.0055394066,0.018728795,-0.02065495,0.011693544,-0.025477171,-0.02304557,-0.010587028,-0.0032051373,0.0012465372,0.0056725983,-0.012178497,0.023004588,0.018537546,-0.012882023,-0.01804576,-0.0014582778,0.010266002,-0.0026416343,-0.0092414515,-0.005792129,0.017840851,-0.0057238257,0.0036098352,-0.026009938,0.008326186,0.007957347,0.005430121,0.0062429314,0.01323037,0.0053584026,-0.022171287,0.004186999,0.0045626676,-0.0137699675,-0.013462602,0.0015607328,-0.01261564,-0.0026296813,0.024356995,0.011379348,-0.009719575,0.039342765,0.029589036,-0.01883808,0.009582968,0.027348684,-0.004596819,-0.004364588,-0.0014360792,-0.0029746133,0.0328676,0.012601979,-0.016146926,-0.0063419715,0.010361627,0.0072879735,-0.004589989,-0.011734526,0.011734526,-0.009029711,-0.0018100403,-0.0044397213,0.0112359105,0.021597538,0.0052115503,0.0016939245,-0.009787878,-0.011604749,0.027840469,0.0043372666,-0.045845248,-0.0030548698,0.008797479,-0.018715134,-0.0049110153,-0.01961674,-0.022977266,-0.0038318213,-0.014931125,0.0328676,-0.0240428,-0.02763556,0.03483474,-0.004989564,-0.0019449396,0.013305504,-0.017594958,0.022471821,-0.027116453,0.00027598845,-0.031310283,0.017021209,0.012595149,0.021925393,-0.016707014,0.02066861,0.03144689,-0.007738776,-0.016310854,-0.010798769,-0.016857281,0.0059184902,-0.0064205206,0.012888853,0.0124175595,-0.008776988,0.0019381092,-0.021010129,0.043960072,-0.0025135654,-0.017540315,0.005778468,0.012601979,-0.0007846354,-0.010006449,-0.004163093,0.006256592,0.015791748,0.0122468015,0.0069020595,-0.018441921,-0.009931316,-0.012731755,0.027717523,-0.001000645,-0.0070352512,0.00701476,-0.014166127,0.00036051392,-0.0034629828,-0.0010774863,-0.008858952,0.016187908,-0.020313434,-1.0565684e-05,-0.004272378,0.01543657,0.009487343,0.00902288,-0.006649337,-0.005938981,-0.017253442,0.013879253,-0.03185671,0.0021464345,0.011898453,0.0038352364,-0.007096724,-0.009931316,-0.025436189,-0.005689674,-0.00084995053,-0.010395778,0.010641671,0.0059184902,-0.033796526,-0.0013754598,0.038987584,-0.014958447,0.01743103,-0.0106143495,0.010791939,0.019398168,-0.0075406963,0.002704815,-0.6574613,-0.020354416,-0.0064410116,-0.021460932,0.023906194,0.011905284,0.010682653,0.011502294,-0.0073221256,0.019507453,0.034944024,0.017349066,0.009931316,0.00883163,-0.010505064,-0.02263575,-0.010908054,-0.047648456,0.0110446615,0.028004397,-0.01021819,0.005587219,-0.015463891,-0.011290553,-0.009439531,0.0067347162,0.028687432,0.0041221105,0.0075611873,0.011119795,-0.0077251154,0.008121275,0.0061848736,-0.014739876,0.061636996,0.0025203957,-0.0075065447,0.011556936,0.028359575,0.024575567,-0.032949563,-0.010429931,0.007895874,0.025067352,-0.010750957,0.023086552,0.021788787,-0.00400258,-0.012335596,-0.012882023,0.010867072,-0.02006754,-0.004159678,0.036801875,0.005969718,0.0050442065,0.0149721075,-0.016529424,0.0058843386,0.006075588,0.011106134,0.0143710375,-0.034725454,0.0036234958,-0.006430766,0.019343525,-0.024616549,-0.023031909,-0.012158006,0.004070883,0.011679883,-0.0017639356,-0.0030719459,-0.012301444,-0.012369747,0.03308617,0.018974686,-0.0041801687,0.0010057677,-0.00018185783,-0.0016247673,0.016980227,-0.0050783586,-0.017909154,0.028960645,0.0044260607,-0.016925585,-0.021966375,0.0110651525,-0.0004836735,0.02666565,0.023619318,-0.003285394,-0.018400937,0.0021105753,0.02225325,-0.010368457,0.012082873,0.0014821839,-0.025477171,-0.015491213,-0.026993508,-0.007301634,-0.0039342763,0.016324515,0.0075270357,-0.030627249,-0.0022915793,0.03409706,-0.0019517699,0.0026074827,-0.014958447,-0.001358384,-0.00822373,0.007513375,-0.029343145,0.005293514,-0.011611579,-0.0025835764,-0.02866011,-0.0022266912,-0.0019398167,0.006591279,-0.018182367,0.0025818688,0.018346295,-0.014603268,0.002482829,-0.0016187908,0.008114445,0.0025921143,0.00045720593,-0.0020866692,0.0038898792,-0.007328956,-0.022102984,0.008032481,0.0002576319,-0.016338175,-0.037211698,-0.017116833,-0.006031191,-0.0015624404,-0.011078813,0.0031880615,-0.029671,-0.035709023,0.005354987,0.00961029,0.021419948,-0.008633551,0.0037259508,-0.020914504,0.045380786,0.012977648,-0.013244031,0.015245321,-0.0058775083,-0.012998139,-0.025422528,0.0016409894,-0.0015880542,-0.029179215,-0.012349256,0.011283723,-0.00092038844,-0.002976321,0.009220961,-0.011106134,-0.029479751,-0.0053413264,0.006871323,-0.015518534,0.0028294688,-0.0033827263,0.016707014,-0.008531095,0.0006155845,0.0064239358,-0.015177017,-0.0048666177,0.004607065,-0.025873331,-0.02285432,0.016406478,0.012499523,0.028359575,0.026802257,0.004210905,-0.0010305276,-0.011112965,0.022280572,0.0077865887,-0.010723636,-0.019876292,0.033031527,-0.029124573,0.0028584977,-0.012082873,0.032157246,0.024807798,0.02284066,0.0022864565,0.012574658,0.011802829,-0.029616358,0.013599209,-0.028113684,0.015942015,0.010949036,0.008114445,-0.003037794,-0.0020815465,0.005225211,0.0130391205,0.0006292451,-0.016966566,0.012957157,-0.017881833,0.0029421693,0.008367168,-0.01363336,0.018510224,-0.024725834,0.024152085,0.01863317,-0.0004887963,0.027799487,-0.013203049,-0.027143775,-0.013879253,0.0014070502,0.006468333,0.0063214805,0.008503774,0.033960454,-0.00450461,-0.03308617,0.03223921,0.022116644,-0.015149696,-0.0033571126,0.025081012,-0.03669259,0.019657722,-0.000881114,0.052948803,0.0113656875,-0.022881642,-0.009705914,-0.012533676,0.0065093148,-0.003828406,0.021119414,0.018346295,-0.003387849,0.03390581,0.0098425215,0.018810758,0.031829387,-0.00020288247,0.02284066,0.009507835,0.019971916,-0.018783437,-0.015163356,-0.014767197,-0.014876482,-0.008087124,0.00345786,0.016064962,0.0014830377,-0.0060243607,0.01823701,-0.01142716,-0.0026091903,0.011078813,0.0095419865,0.016310854,0.008018821,-0.0018305314,0.002462338,0.0077865887,0.028796718,0.0068747383,-0.010703144,0.009760557,-0.0015965921,-0.00084909674,0.010873903,-0.0016435508,0.0118369805,0.011570597,0.02285432,-0.008770158,-0.015737105,0.02786779,-0.0069259657,-0.020613968,0.0029489996,-0.0029285087,0.016488442,-0.0016981935,-0.037840087,0.036118843,0.0007308465,-0.012513184,-0.0044704583,-0.0136196995,-0.004525101,0.00902288,0.009043371,-0.0024606304,-0.0029404617,-0.010962697,-0.011727695,-0.0100132795,-0.0012439758,0.016119605,0.029233858,-0.022717714,-0.0083398465,-0.007397259,0.01022502,0.0740409,0.01463059,0.0040811286,0.016078623,-0.014002198,-0.0074109198,-0.049970772,-0.024425298,0.026009938,-0.015668802,0.020026559,-0.00781391,0.009664932,-0.031802066,-0.0041733384,-0.00073468854,0.009733235,0.0055598975,-0.0011620118,-0.023373427,-0.00450461,-0.031009747,0.02665199,-0.008401319,-0.001021136,0.0133396555,0.02644708,0.049588274,-0.02143361,-0.03390581,-0.0049110153,0.036637947,-0.010566537,0.020613968,-0.003951352,0.062456638,0.029233858,0.046801496,0.0110446615,-0.004665123,0.016406478,0.014275412,0.014616929,-0.025121994,0.014562286,0.009043371,-0.0052183806,0.022922624,-0.012082873,-0.023933515,0.0031436644,0.01022502,-0.0033536972,0.013278183,0.018769776,0.028878681,-0.00092892634,0.003046332,0.004460213,-0.028550824,-0.022198608,-0.010429931,0.019152276,-0.0073221256,0.012970817,-0.007048912,0.009801539,-0.007875383,-0.025162976,0.013865592,-0.0122672925,-0.014357377,-0.011386178,-0.0136401905,0.0089409165,0.008572077,0.01022502,-0.00881797,-0.009972298,-0.005775053,-0.047757745,-0.046364352,-0.015463891,-0.0052183806,-0.016174247,0.012123855,-0.02846886,-0.0023632979,-0.004251887,0.004508025,-0.0033980946,-0.009760557,-0.014261751,-0.013489923,-0.012164837,0.017171476,0.017868172,0.014808179,0.0074450714,-0.017622279,-0.008934086,-0.026720293,-0.0033246684,-0.0070215906,0.015559517,-0.0018749286,-0.0060585123,-0.00761583,-0.0236603,-0.0033998021,0.019042991,-0.006287329,0.032184567,-0.002923386,0.029780285,0.031829387,0.016119605,-0.0075885085,0.022594767,-0.026365116,-0.009596629,-0.005771638,0.02162486,0.04043562,-0.018346295,0.02405646,0.008688194,-0.013435281,-0.0017724734,0.0038557274,-0.01041627,0.017103173,-0.0097127445,-0.020559326,-0.00057673693,-0.009603459,-0.00042796353,0.002272796,-0.01825067,-0.0017963797,-0.013305504,0.028878681,0.026132884,-0.010347966,0.003999165,-0.03289492,0.0038557274,-0.0010971235,-0.021406287,0.0074792234,0.009057032,0.0054676877,-0.027362345,0.004528516,0.00031846465,-0.02463021,-0.020695932,-0.007069403,0.014084163,0.03221189,0.003975258,-0.008852121,0.013086933,-0.0072060097,-0.008367168,-0.00027235984,0.010081583,-0.0057613924,-0.035599735,0.010279663,0.02805904,-0.0009127043,0.0013993661,-0.009248282,0.030709213,0.026037259,-0.0022864565,-0.011761847,-0.0010441884,-0.019794328,-0.009528326,0.016078623,0.0061165704,-0.0037122902,-0.033823848,0.009869843,0.019521113,0.01463059,0.0011107841,0.020982808,0.020586647,-0.0066390913,0.0039035399,0.01142716,0.026228508,-0.01861951,-0.0027287211,-0.04133722,0.010901224,0.02304557,0.008046142,0.016201569,0.021010129,0.009637611,-0.003244412,0.011597918,-0.014466662,-0.012403899,0.025559135,-0.02986225,0.003807915,-0.023837889,-0.009835691,-0.0114135,0.0056452765,0.00883163,0.008858952,0.029015288,-0.0010826091,-0.030900462,0.01684362,-0.033523314,0.049861487,0.0028004397,0.052156482,0.032102603,0.033140812,-0.016939245,-0.016146926,0.0067381314,-0.008578908,0.013503584,0.030354034,8.975495e-05,-0.013052781,0.00066382374,0.0011082228,-0.0027645805,-0.03346867,-0.0001445044,-0.0012038476,0.004668538,-0.013264522,0.013257692,-0.027294042,0.02885136,0.0002544302,-0.012055552,0.0038830487,-0.014302733,-0.0057579773,0.0048188055,-0.03065457,0.021570217,-0.00051910593,-0.008749667,0.007192349,-0.0005664914,-0.016256211,0.003848897,0.017362727,-0.008312525,-0.0032256285,0.006727886,0.022731375,0.01646112,-0.015491213,-0.003746442,0.014193448,0.029370466,-0.0015778088,-0.014644251,-0.021693163,0.0067620375,0.023168515,-0.010245511,-0.012560997,-0.042184185,-0.011707204,-0.0034817662,0.015108714,-0.011625241,0.025941635,0.0010151594,0.00781391,0.00038100494,0.023305124,-0.0012952033,0.013776798,-0.044615787,0.007315295,0.010505064,0.008018821,0.011727695,0.0036815538,-0.02644708,0.0089409165,0.031091712,-0.0014762074,0.011768677,0.0052422867,0.00070694025,-0.027430648,0.011352027,-0.027430648,-0.025900653,0.04248472,-0.008647212,-0.019152276,-0.0075065447,0.0014514474,0.009057032,-0.019534774,-0.011577427,0.0017639356,-0.0060619274,-0.0052422867,-0.016064962,-0.0122672925,0.0050442065,-0.01721246,-0.012841041,0.021460932,-0.013496754,0.01142716,0.007977838,0.0028602052,-0.006748377,-0.035162594,-0.020299774,0.002923386,0.011741356,-0.013483093,-0.008756497,0.0023615903,0.017895494,-0.018510224,0.0036337413,-0.012888853,-0.02584601,0.0048392965,0.009999619,0.015600499,0.018551206,-0.023837889,-0.021310663,-0.015190678,-0.014753536,-0.027020829,0.0078002494,-0.016720675,0.020518344,0.023878872,-0.0071786884,-0.04232079,-0.03128296,-0.041801687,-0.046173103,-0.0071035544,-0.0029250935,0.013927065,0.02064129,0.007895874,0.01122908,-0.021064771,0.006154137,-0.008975068,-0.0038659729,0.0053413264,0.008346677,0.020805217,-0.009036541,0.015928354,-0.036446698,0.010580198,0.005549652,-0.0044192304,-0.0140705025,-0.03464349,-0.023947176,-0.021788787,-0.004805145,-0.0023035326,0.016297193,0.016488442,-0.018086743,0.014193448,0.00097588496,-0.01823701,-0.023400748,0.00016745008,-0.020313434,-0.0032187982,0.0010527263,0.0013327702,-0.007253822,-0.011918944,-0.0021805863,0.012164837,-0.006167798,0.002296702,0.035982236,0.008052972,0.0018680983,-0.010949036,-0.018687813,-0.019097634,-0.011406669,-0.010081583,-0.030818498,0.0025255184,-0.027731184,0.0068986444,-0.016898263,-0.005430121,-0.0196304,0.008367168,-0.030299392,0.015764426,0.0057374863,0.024111103,0.0037020447,-0.0002486671,-0.017731564,-0.016993888,-0.014862821,-0.0015846391,0.0039137853,-0.0026296813,0.004767578,-0.017622279,0.007772928,-0.0045011947,0.026843239,-0.026938865,0.01081926,0.2006481,-0.007943686,0.004344097,0.017936476,0.014097824,0.012151176,0.037129734,0.017157815,-0.0018868817,0.009555647,0.008995559,0.010272833,-0.041583113,-0.008169088,-0.0030343789,-0.013435281,-0.014043181,-0.03147421,-0.014043181,-0.010655331,0.028605467,-0.0010817553,-0.0063692927,-0.017253442,0.015696123,0.03147421,-0.017608618,0.021447271,0.03199332,0.02225325,-0.015108714,0.0034271234,-0.008189579,0.009678593,0.009118505,-0.0003726805,0.026187526,-0.0038215758,0.017280763,-0.031392246,-0.010484573,-0.0009938146,0.014043181,-0.034370273,0.008913595,0.019480132,-0.008169088,-0.021884412,0.0034527374,0.009692254,-0.0027987321,0.015532195,0.029889572,0.040708832,0.0061814585,0.011106134,-0.015969336,0.005638446,-0.0036542322,5.2775056e-05,-0.0164338,0.013653851,-0.010102074,-0.0064068595,-0.012533676,-0.019425489,-0.002564793,0.012226311,0.011522785,-0.01782719,-0.016870942,-0.027239399,-0.0052388716,-0.011659392,-0.026187526,-0.01763594,0.048003636,0.045162212,0.002749212,0.031173676,-0.011461312,-0.018906383,-0.030326713,-0.033769205,0.0023632979,0.00059253204,0.04324972,0.016297193,-0.015545856,0.0053788936,-0.020299774,0.009876673,-0.029097252,0.0020047051,-0.0013882668,0.011891623,0.0026740783,-0.0002469595,-0.0154229095,0.015368267,-0.022471821,0.066991985,0.016283533,0.03508063,-0.019206919,0.010136226,0.002873866,0.014439341,0.013141576,-0.008886273,-0.0051398315,-0.005068113,0.014166127,0.0031709857,-0.01182332,0.018592188,0.00013799423,-0.017472012,-0.013660681,0.007438241,0.012007739,-0.0009374643,-0.0035312863,0.013305504,0.0033554048,-0.011338366,-0.018100403,0.0064990693,-0.009104844,-0.025695743,0.020518344,-0.032840278,-0.010696313,-0.0016307438,-0.012998139,-0.0077660973,-0.002588699,0.0046582925,0.0044977795,0.008879443,-0.0010928545,0.025914313,-0.008968238,0.004436306,0.009528326,0.012513184,0.009876673,0.004665123,-0.032539744,-0.03803134,-0.002716768,0.011877962,-0.0002828188,-0.013401128,0.03770348,-0.0020149506,-0.023960836,-0.011085643,-0.0030531622,0.0033485745,-0.030135464,0.011406669,0.046255067,0.017157815,-0.0033366214,-0.011474973,-0.17682387,0.001774181,6.659582e-05,-0.016993888,0.030599928,0.008264712,0.021515574,0.014589608,-0.011474973,0.0126293,-0.004429476,-0.0017775962,-0.035599735,-0.007492884,0.015013089,0.0101635475,-0.009801539,0.04062687,0.024575567,0.0073631075,0.02006754,0.0019295713,6.0832725e-05,0.015682463,-0.009951807,0.008585738,-0.026488062,0.014357377,0.016993888,-0.006560542,0.0004273232,-0.002585284,0.00531059,-0.006290744,0.0038625577,-0.0030019348,-0.021542896,-0.024397977,-0.029971536,-0.006475163,0.02064129,0.03652866,0.003285394,-0.016338175,0.006840586,0.017553976,0.04152847,-0.013155237,0.0018117479,-0.0016025687,0.018701473,0.00029882742,0.0005173983,-0.022622088,0.0018971271,-0.0029046026,-0.0032409967,0.011249571,-0.036555983,-0.01101734,0.013271352,-0.021501914,-0.0038967095,0.0022079076,-0.013653851,0.0030036424,-0.018769776,0.023988158,0.002416233,-0.01704853,0.010402609,-0.017185137,-0.0026996923,-0.0009255112,0.009391719,-0.00170417,-0.018059421,0.009234621,0.025955295,-0.011317875,0.02103745,0.009398549,0.013203049,-0.013763137,0.017116833,-0.017116833,-0.0077524367,-0.010757787,-0.0029899818,-0.008476453,0.012321935,-0.020340756,-0.0168163,-0.009726405,0.024999047,-0.0021208208,-0.016297193,-0.012164837,0.006174628,-0.010375287,0.011317875,0.01659773,-0.023933515,-0.0018510224,0.023783246,0.026679311,0.01982165,0.015737105,0.041227937,0.014330055,-0.030135464,0.018988347,0.0103138145,0.019411828,0.0075611873,0.022021018,-0.0059082448,-0.0064580874,-0.0016999011,0.0049315062,0.047648456,0.029916894,0.014903803,0.010566537,0.001259344,0.007472393,-0.07469661,-0.022362536,0.006447842,0.027430648,-0.013974877,0.008722345,-0.016201569,0.015354606,0.000121558725,0.025518153,0.00025186883,-0.03204796,-0.022062002,-0.027020829,0.004463628,-0.00094002567,-0.01621523,-0.010730466,0.012601979,0.041255258,-0.009343906,-0.02065495,-0.0011543276,-0.010798769,-0.0019483548,0.02023147,-0.024425298,-0.008462792,0.022430839,0.0026740783,0.0047983145,-0.015778087,0.0131484065,-0.024001818,-0.006840586,0.0118164895,-0.022130305,-0.050134704,0.047047388,-0.025381546,0.0043816636,0.002885819,0.036118843,-0.034534205,-0.010006449,-0.0012977647,-0.023373427,0.010668992,-0.0053447415,-0.03308617,-0.036392055,-0.016857281,-0.04251204,-0.00900922,0.030599928,-0.020627629,0.0067347162,-0.0133191645,-0.008264712,0.01161841,-0.016406478,-0.0071035544,-0.007936856,0.005477933,-0.0022608428,-0.006553712,-0.019944595,-0.010129396,0.005495009,-0.022731375,-0.02263575,0.013325995,-0.025354225,0.023742264,-0.006096079,-0.005652107,-0.016488442,-0.0026279737,0.02004022,-0.0043372666,0.0073221256,-0.026009938,0.041173294,-0.003568853,0.027376005,0.021297002,-0.018059421,0.008087124,0.0082169,-0.02203468,0.021693163,0.006570788,0.014207109,-0.008968238,0.012909344,-0.031392246,0.011850641,-0.005826281,-0.01662505,0.021228699,-0.015149696,-0.023837889,-0.083603375,0.0078002494,-8.367167e-05,6.472815e-05,0.009145826,-0.0018766362,0.0064580874,-0.006837171,-0.0048153903,-0.0037259508,-0.02486244,-0.0008802602,-0.019165937,-0.0057852985,-0.009979128,0.0013054489,0.0120214,0.012943496,0.009330246,0.0005080066,-0.0025699157,-0.0047061048,0.0001445044,0.012076043,-0.010409439,0.0029097253,-0.012841041,0.0032461195,-0.01721246,-0.013660681,0.016488442,-0.015245321,0.017472012,0.03204796,-0.017690582,-0.005314005,-0.0007876237,0.012786398,0.037812766,0.045216855,-0.003568853,-0.03226653,0.0072674826,-0.020586647,-0.009002389,-0.020709593,0.0013600916,0.0009579553,0.015054071,-0.00076371746,0.003083899,0.0155731775,-0.0046753683,-0.020559326,-0.0028380067,-0.022772357,0.009268773,0.012902514,0.01704853,-0.008585738,0.022499142,0.0041050347,-0.0028106852,-0.019111294,-0.014780858,0.0021635105,-0.017075852,0.025750386,0.0026689556,-0.0013788751,-0.036610626,0.0004401301,-0.019575756,0.015149696,0.011153947,-0.006652752,-0.026788596,0.03322278,-0.013114254,0.00842181,0.0136196995,0.0139202345,-0.022704054,0.026597347,0.022676732,0.0011457896,-0.028113684,-0.022417178,-0.009746896,0.0122468015,-0.012144346,0.0052115503,-0.014876482,0.008647212,0.0033810188,0.010580198,-0.013291843,-0.013503584,0.002564793,0.021215038,-0.003787424,-0.014603268,0.0044226456,-0.009944976,-0.02583235,0.0015854929,-0.012642961,-0.019958256,-0.002725306,0.006130231,0.021597538,0.00033041774,0.0033536972,-0.007438241,-0.005959472,-0.011297383,-0.014138806,-0.02825029,-0.04087276,0.026214847,-0.030435998,-0.0023684206,0.020327095,-0.008838461,0.032321174,0.03729366,-0.0013370392,-0.030927783,0.005798959,-0.013196219,0.009671763,-0.0019090803,-0.016174247,0.004388494,-0.008237391,-0.0016896556,-0.030435998,-0.0007291389,-0.0041528475,0.07513375,0.023537355,-0.013756307,1.967725e-05,-0.024835119,0.0034390767,0.02906993,-0.0192479,0.01744469,-0.036118843,0.0377308,-0.009391719,0.0031060975,-0.019275222,-0.015682463,-0.012158006,-0.016911924,0.020299774,-0.0023154856,0.0065024844,-0.012499523,0.00701476,0.026324134,0.017786207,-0.029042609,-0.026952526,0.02042272,-0.008572077,0.003924031,-0.023305124,-0.021160396,0.019685043,-0.0116457315,-0.008544756,0.01682996,-0.0089614075,-0.0022813338,-0.013776798,0.012943496,0.02464387,0.011031001,0.014712554,-0.04106401,-0.027171096,-0.028441539,-0.011652562,-0.015982997,-0.0044021546,0.0018458996] | K2: 2025-07-27T18:28:47.883Z
A3: 1 | B3: 296 | C3: computer_programmers_1 | D3: Debugging,Problem-solving,Attention to detail,Knowledge of the programming language used | E3: Software Development | F3: Error Correction,Code Review,Quality Assurance | G3: 1 | H3: Developer | I3: 4 | J3: [-0.000316098,0.028327798,0.019661551,-0.017982466,-0.012207223,0.02767783,-0.032796334,-0.013229569,-0.008165231,-0.019011581,0.035883684,0.015247181,-0.0019075902,0.0075558852,-0.009370381,-0.03141515,0.022044769,0.01695335,-0.0014480421,-0.023642609,-0.031469315,0.01978342,-0.00895061,0.006106997,-0.00534193,0.013060307,-0.00869333,-0.046960235,-0.01805017,-0.009133413,0.026364353,-0.013398833,0.016479412,-0.020514635,-0.009113101,-0.0008145766,-0.01377121,-0.010169301,0.006740039,-0.0089302985,0.024143627,0.042004224,-0.011462468,0.004597174,0.017061677,0.023696773,-0.011002073,-0.016560659,-0.010196383,0.02632373,-0.010670318,-0.0019922215,-0.022952016,0.002960404,0.010460433,0.018348072,-0.0028825433,-0.0016181511,-0.009011544,-0.01871368,-0.013012913,-0.0015199787,0.0019262091,-0.007136114,-0.006327038,-0.012511896,0.0012973984,0.02927567,0.025660219,-0.017129382,0.028923605,-0.005531504,0.0076912954,0.008219395,0.014651376,-0.015490918,-0.018077252,0.0021242464,0.013344668,0.00922143,0.006750195,-0.0009876477,-0.03222761,0.019729257,-0.0013177098,0.011780681,-0.012274928,0.0131009305,0.008273559,-0.0082532475,-0.010629695,0.014245146,0.025348777,0.016005477,-0.0047698217,-0.010148989,-0.010785417,0.0355587,-0.02700078,-0.019499058,0.009979727,0.032688007,-0.030494362,-0.009058937,-0.017251251,-0.0067840475,0.007582967,-0.010013579,0.0077725416,-0.0048747645,-0.011604648,0.022302048,0.025375858,-0.022775983,0.0047765924,-0.0039912136,0.01390662,-0.002103935,-0.004851068,-0.02781324,0.019715715,0.027664289,0.0015826059,-0.021530211,-0.0016274605,0.014529507,-0.0021919515,-0.010304711,0.0010477359,-0.006469219,0.021408342,-0.002244423,0.025484186,0.007725148,-0.013622259,-0.008903216,-0.019228239,0.014989901,-0.01296552,-0.016899183,0.008280329,0.026107073,0.00045700918,0.005582283,0.009201119,0.0030128753,0.0069600805,0.022545787,0.023954052,-0.0040182956,0.0060968413,-0.0033700196,0.013324357,0.0102640875,0.0005357163,0.002879158,-0.0038117953,0.0024306118,-0.0100609725,-0.02418425,-0.009424545,0.00621871,0.0013244803,-0.014962819,-0.002406915,0.027352845,0.011746828,0.0009436393,0.007610049,-0.0051455847,-0.006780662,0.013574866,-0.028409045,0.019553224,0.015355509,0.0023087426,0.022004146,-0.0023679847,-0.021557292,-0.0014471958,0.012647307,-0.01618151,0.022098932,0.01149632,-0.011401533,0.0039742873,0.010853122,0.012213994,0.008219395,-0.012762405,0.031171411,0.014285768,-0.027244518,-0.025822712,-0.6621014,-0.032552596,-0.01737312,-0.008124608,-0.011956714,0.03461083,0.026269564,0.019404272,-0.0090318555,0.014177441,0.01818558,0.032254692,-0.018767845,-0.013473308,-0.015409673,-0.009553185,0.001745098,-0.045551967,0.016750233,0.02097503,-0.02606645,0.004945855,-0.010209924,-0.01911991,-0.0041909437,-0.00022173408,0.0055382745,-0.010128678,0.020609422,0.039079364,-0.010609384,0.007393393,0.017088758,0.008056902,0.062721975,-0.0037373195,0.0007392547,0.012647307,0.012708241,0.045254067,-0.018632434,-0.0018889713,0.022044769,0.031388067,0.0007984966,0.013392062,0.009986497,0.0044651492,-0.02419779,-0.0045125424,0.00962766,-0.019187616,-0.022437459,0.014800327,0.004664879,-0.012017649,0.011049466,-0.0145836705,0.013547784,-0.006993933,-0.010710942,0.031469315,-0.039648086,-0.0112932045,-0.024279036,0.0059478898,0.008463133,-0.010988532,-0.013717046,-0.016086724,-0.00057253096,-0.00641167,-0.016601281,0.01150309,-0.0015919154,0.047528956,0.022247884,0.0022359597,8.918026e-05,-0.0042010993,0.009729218,-0.021042734,-0.005118503,-0.010128678,0.016817939,0.0045125424,-0.016899183,-0.015721116,-0.0064861453,0.0001894684,0.021624997,-0.010135449,0.0046208706,-0.012511896,0.004891691,0.026960157,-0.01683148,0.0071835076,0.02352074,0.0016816246,-0.0050067897,0.00076887565,0.006736654,-0.0060392916,0.012654076,0.008097526,0.003163519,0.0035646716,0.022748902,0.013513931,0.001536905,-0.013689964,-0.0041774027,-0.0082871,0.019688632,-0.02540294,-0.006577547,0.010650007,5.8818776e-05,-0.020934407,0.0025270917,0.0072376714,0.022803066,-0.0029417851,-0.013060307,0.0046479525,-0.007853787,0.015842985,-0.002955326,-0.013439455,-0.001167066,0.00014895115,-0.020392766,-0.0023290543,-0.031902626,-0.007962116,0.007975657,-0.013243111,-0.010501056,-0.01991883,-0.002031152,-0.008720412,-0.0049797073,0.017562693,-0.0038659591,-0.021597916,-0.044847835,-0.0086053135,0.00040771143,0.0028537684,0.0034698846,0.017142922,-0.020893782,0.03610034,-0.0010756642,-0.012234305,0.005971587,-0.01349362,-0.015098229,-0.055897303,0.025145661,-0.008300641,-0.030358952,-0.01497636,0.0010968221,-0.011103631,0.005951275,0.016993972,-0.040270973,-0.026120614,-0.018686598,0.024617562,-8.473712e-05,0.0005399479,-0.004065689,0.018767845,-0.018767845,-0.007461098,0.01163173,-0.0044990014,0.01711584,0.006360891,-0.019675093,-0.020379225,0.029221507,-0.009309446,0.00654708,0.031442232,0.023344707,0.009322988,-0.024387365,-0.004299272,-0.0025964892,-0.0024543086,-0.008280329,0.030900592,-0.010121907,-0.0015445218,-0.02338533,0.044008292,0.024103003,-0.0017484833,0.019972995,-0.012782716,0.010927597,-0.02859862,0.0007743767,-0.010934368,0.015531542,-0.0035782126,-0.0027031247,-0.012471273,-0.013791522,-0.008117837,0.0151117705,0.028327798,-0.011828075,0.02314159,-0.019079287,-0.008456362,0.008774577,-0.0061036116,0.016790856,-0.026107073,0.022478081,0.01429931,0.0036831556,0.025782088,-0.0045125424,-0.0058327913,-0.0038795003,-0.002787756,0.012992602,0.0068077445,0.0152878035,0.017224168,0.012586372,-0.03100892,0.02900485,0.015179476,0.008828741,-0.0012550827,-0.010656777,-0.004928929,0.0049763224,0.018794926,0.051239192,0.0017239403,0.0066621783,0.006201784,-0.0058598733,0.00494924,0.0031262813,0.002198722,0.00088016584,0.022897853,0.022261426,0.007163196,0.030981837,0.03192971,0.0041096974,0.01924178,-0.010243776,0.0067298836,0.0024289193,0.0053148475,0.0065843174,-0.017657481,0.0016249216,-0.0066994163,0.008815199,-0.0019177459,-0.015842985,-0.013595177,0.0041909437,0.0070751794,-0.022356212,0.014922196,0.00048536068,0.0046039443,-0.015369049,-0.014326392,0.021868736,0.029708983,0.011604648,-0.0007980735,0.004539625,0.0027369773,-0.025470646,0.021719785,-0.0049560107,0.013974326,0.008097526,-0.0036120652,0.0059038815,-0.007779312,0.023222838,-0.012681158,-0.01336498,-0.026757041,-0.011333828,0.0030196458,-0.025037333,-0.003957361,0.03447542,0.004289116,-0.018740762,-0.01723771,0.0007595662,-0.01523364,0.00049001543,0.0010570453,-0.0073730815,0.0010892053,0.022220802,-0.024075922,-0.014732623,-0.021083357,0.012085354,0.026635172,-0.014258686,-0.02190936,0.021706244,0.012065043,0.08330431,0.015057607,-0.023480117,0.017996006,0.00655385,-0.0102844,-0.023913428,3.054662e-05,0.027163273,-0.024522774,-0.009262053,-0.0009842623,-0.005253913,-0.00420787,-0.006790818,0.0018449631,0.016452331,-0.013134782,-0.0138050625,0.004052148,0.005839562,-0.0046581086,0.013216029,-0.014367015,0.03339214,0.012119207,0.025633138,0.023493657,0.004441452,-0.0098849395,0.009180807,0.027447633,-0.011516632,0.0020565414,-0.010778646,0.070792414,0.0059952834,0.02044693,0.02205831,-0.015694033,0.013425915,-0.002901162,0.016425248,-0.0138795385,0.041110516,-0.00013974748,-0.0147597045,0.025998745,-0.039918907,-0.022735361,0.020243814,0.0030518058,0.001547907,0.0023967593,0.0054299464,0.0038964264,-0.0027792929,-0.003916738,-0.006079915,-0.05375782,-0.015044065,-0.018090794,-0.008761035,-0.003713623,-0.014732623,-0.0035443602,0.0015580629,-0.004099542,-0.033798367,-0.004539625,0.005057568,-0.025321694,-0.015991936,0.008111067,0.008713642,0.008327723,0.009424545,0.000761682,0.0013515623,-0.0033649418,-0.024766512,-0.03260676,0.011171335,-0.005545045,-0.0052606836,0.03155056,-0.0013769518,-0.01925532,-0.005589053,0.018117875,0.007244442,-1.3488118e-05,-0.00031948328,-0.0042315666,-0.01350716,0.0050203307,0.0050981916,0.014082653,0.014502425,-0.019444894,-0.0021276316,-0.049370535,-0.021963524,-0.009559955,0.008463133,0.008761035,-0.012342634,0.013243111,-0.004702117,-0.007921493,0.017833514,-0.02165208,0.01563987,0.012044731,-0.0013769518,0.025903957,0.015138852,0.009099561,0.013446226,-0.017535612,0.0009597193,-0.044983245,0.04208547,0.0411376,0.003490196,0.011516632,0.0076235905,-0.024143627,0.0018094179,0.010365645,-0.028381962,0.037237786,-0.024671726,-0.03062977,-0.010209924,-0.030711018,0.00030615384,0.012538978,-0.0061103823,-0.013019684,-0.0068415967,-0.0003708968,0.0015521386,0.003849033,0.03542329,-0.031090166,-0.01404203,0.0011916092,-0.01256606,0.041868813,-0.014949278,-0.000691438,-0.028950686,0.0024763127,-0.008408969,-0.021760408,0.00044854605,-0.022640573,0.027786158,0.031090166,-0.005037257,-7.5004515e-05,0.023331165,-0.0019295943,0.001693473,0.014339933,-0.005839562,0.0017019361,-0.008388657,0.00869333,0.014096195,-0.015531542,0.009153725,-0.01550446,0.0075152623,0.01095468,0.0064353663,-0.026418516,-0.0062085544,-0.02685183,-0.010358875,-0.020893782,0.0040893857,0.006831441,-0.019824043,0.018497024,0.02005424,0.004133394,-0.012640536,0.021665622,0.017197087,-0.0005340237,0.010291169,0.027258059,0.036560737,-0.023480117,-0.006909302,-0.02713619,0.00042231035,0.010291169,0.029519409,0.020487553,0.019539682,0.0011636808,-0.021949982,0.04213963,-0.012999373,-0.024915464,0.009647972,-0.016005477,-0.0102640875,-0.0010756642,0.014597212,0.01390662,0.017576234,0.0006237329,0.0018805081,0.018957417,0.0043500504,-0.028490292,-0.0008441975,0.0026675796,0.039187692,-0.005653373,0.012681158,0.041868813,0.009918792,-0.019729257,-0.0029180883,0.014502425,-0.013656111,0.028571537,0.026757041,0.0016401552,-0.0044008293,0.01203119,-0.0019177459,-0.013195717,-0.010270858,0.01844286,-0.0006749349,-0.0021614842,-0.011211959,0.015314885,-0.011211959,0.023344707,-0.011530173,0.02392697,-0.019282402,-0.014163899,-0.0033040072,0.014177441,-0.028138226,0.019756338,0.0049695517,0.0066994163,0.017454365,-0.01149632,-0.0074137044,0.012024419,-0.007582967,0.0050812652,-0.038835626,0.0026320345,0.016668987,0.021963524,-2.0708228e-05,-0.021692703,0.03006105,0.033852533,-0.013676423,-0.0126947,-0.0075355736,-0.007149655,0.0072512124,0.02193644,-0.019295944,-0.024956087,-0.013920161,-0.009146954,0.00855792,0.020081323,0.000929252,0.01203119,0.00013223646,-0.010223465,-0.01029794,-0.011685894,0.008496986,-0.026161237,-0.021381259,-0.0033141628,-0.0039505907,0.0021970293,0.012281699,0.0049424698,-0.017874137,0.015247181,-0.02165208,0.023507198,0.0035985243,-0.019715715,-0.014448261,-0.001607149,-0.017048135,-0.03447542,0.013317586,-0.038456477,-0.018253285,0.0020785455,-0.008036591,0.02018965,-0.003060269,-0.01109009,0.00069355377,-0.0021733325,0.013459767,-0.011733288,-0.023642609,0.026784124,-0.014515966,-0.013974326,0.016655445,-0.0061747017,-0.0042857304,0.004482075,-0.004918773,0.0020599265,-0.036154505,-0.020297978,-0.00801628,0.007921493,-0.035369124,-0.013067078,0.008219395,-0.011821304,-0.0052437573,0.024536315,-0.0017891063,-0.010399498,-0.017061677,0.009654743,0.00481383,0.030277705,-0.003050113,-0.004248493,-0.027054943,-0.012742093,-0.036831554,0.012227534,-0.040595956,0.033040073,0.012518667,-0.0098104635,-0.00042061773,-0.020501094,-0.013128012,-0.010216694,-0.009512561,-0.00095464144,0.02564668,0.024739431,-0.007298606,0.010433351,-0.015680494,0.014434719,-0.021205226,-0.007907951,0.015518001,0.0056330613,0.021855194,-0.0112932045,-0.0028097602,-0.00907925,-0.01082604,0.008564691,-0.013371751,-0.0043771323,-0.004810445,-0.016736692,-0.0018297294,0.00628303,0.013114471,-0.00108582,0.003568057,0.00052852265,-0.0031567486,0.0008425049,-0.01764394,0.0014268842,0.013046766,0.024441529,-0.024021758,0.01309416,-0.027867405,-0.003703467,0.010907286,-0.01431285,0.013825375,0.0055924384,-0.027664289,0.024400905,-0.006540309,-0.011002073,-0.0036526883,-0.022437459,-0.0021428652,0.000513289,-0.011516632,-0.012626994,-0.014664917,-0.015612788,-0.008104296,0.0040961565,0.0016917803,-0.023981133,-0.018009547,-0.03929602,0.008937068,-0.0016706225,0.0060054394,-0.016357543,-0.0021107055,-0.0070277858,0.008612084,-0.017982466,-0.013920161,-0.029194424,-0.010094825,0.0055585857,-0.018361613,-0.0003395832,-0.0129519785,0.031713054,-0.009417774,0.0038930413,0.19943205,-0.012058272,0.0007566041,0.026689336,-0.008774577,0.023304082,0.033365056,-0.008632395,-0.012491585,0.038293984,0.01911991,-0.008172002,-0.03409627,-0.0058767996,0.000788764,-0.0028046824,-0.03130682,-0.023290543,-0.018361613,-0.017318955,0.015071147,0.0044042147,-0.022098932,-0.012897815,0.040731367,0.0151117705,-0.019702174,0.017684562,0.040081397,0.0033717123,-0.02487484,-0.00400814,0.021096898,0.011239041,0.021191685,-0.008212624,0.018456401,-0.009512561,0.015314885,-0.010988532,0.011956714,0.0034021796,0.024008216,-0.0403793,-0.012329092,0.04211255,0.0022139556,-0.015409673,0.010115136,0.023588445,-0.014177441,0.0055653565,0.019458435,0.013865997,-0.0017569464,0.0060189804,0.008199084,0.016154429,-0.009600578,0.008375117,-0.0076235905,0.01684502,-0.019295944,0.018388696,-0.015098229,0.020000076,-0.011286435,0.022911394,0.013412373,-0.032417186,-0.008713642,-0.03087351,-0.007935033,-0.00016344426,-0.030494362,-0.01990529,0.0010604305,0.02954649,0.024576938,0.025443563,-0.002493239,-0.017874137,-0.01350716,-0.012349403,-0.018266827,-0.041245926,0.009681825,0.0014361937,-0.011266123,-0.02151667,-0.0063033416,-0.017616859,-0.002411993,-0.0025643294,0.009045397,0.022098932,-0.01738666,0.002325669,0.012897815,-0.01457013,-0.0047495104,0.0411376,-0.00045066184,0.01109686,-0.006564006,0.0018534261,-0.0068382113,0.0124238795,-0.0086053135,-0.0014302694,-0.0016325384,-0.021286473,0.0063947435,0.0011492935,-0.00048282175,0.011421844,0.0037237785,-0.03929602,-0.00077649247,0.005924193,0.029708983,-0.022708278,0.008300641,0.02754242,0.0013659496,-0.012051501,-0.02377802,-0.015937772,0.0048713796,-0.03504414,0.0040115253,-0.028300717,0.011320286,-0.012383256,0.013615489,-0.011936403,0.003163519,0.005707537,-0.018889714,0.014421179,0.02660809,-0.0027454405,0.011103631,0.0015529849,-0.0065132272,-0.009857858,-0.0010011886,0.015829444,-0.021313554,-0.0026540386,-0.025077956,-0.0028182233,0.005866644,0.0042180256,0.011550484,-0.00273867,-0.028029896,-0.004021681,0.022423917,0.010135449,-0.023425952,0.00935684,0.031036003,0.011652041,-0.010419809,-0.0060460623,-0.17484155,0.009444857,-0.004901847,-0.010033891,0.0129519785,0.021611456,0.008747495,0.0108666625,-0.010352104,0.0014463494,0.008314182,-0.042004224,-0.0382669,-0.006069759,0.009471939,-0.0025592514,-0.014651376,-0.0035274338,0.040975105,0.011516632,0.014461802,-0.0037610163,0.001115441,0.018266827,0.021557292,0.016154429,-0.009336528,-0.0075220326,0.01390662,0.0005357163,-0.0004043262,-0.0014404253,0.015748197,0.0036662293,0.009289135,0.005480725,-0.016736692,-0.005626291,-0.017738728,-0.007867329,0.0014319621,0.038375232,0.026134156,0.008706871,0.0051929783,0.025836254,0.030169377,-0.02819239,0.019837584,-0.0019600617,0.026811205,-0.031360988,0.00077691564,-0.012843651,0.012897815,0.0046005594,0.0049390844,0.019972995,-0.02472589,-0.014773245,-0.0027217437,-0.025782088,0.009600578,0.0041029267,-0.003155056,-0.033094235,-0.020203192,0.021543752,-0.028002815,-0.011442156,-0.015084689,-0.02434674,0.0004832449,-0.005886955,0.003327704,-0.0047427397,-0.027285142,0.013683193,0.0073053767,-0.014962819,0.0035579011,0.00095887296,0.0142316045,0.007941804,-0.033771288,-0.006723113,-0.015531542,0.024170708,0.007819935,-0.021340637,0.04869348,-0.04387288,-0.008023051,0.0069397693,0.03726487,0.0035748275,-0.0017671022,0.0055416594,-0.003001027,-0.008056902,-0.0028926989,0.007447557,-0.019404272,0.0054434873,0.0062254807,0.019404272,0.0039201234,0.008226166,0.041733403,0.004810445,-0.020907324,0.025145661,0.002687891,0.004383903,-0.003028109,0.023940511,0.00935684,0.0039370493,0.004502387,-0.0041096974,0.0601221,-0.010670318,-0.015572165,0.017833514,0.007847017,-0.012803027,-0.08530838,-0.021340637,0.022410376,0.014109735,-0.0074137044,0.027339306,0.004708887,0.021543752,-0.013324357,0.026770582,0.00020142256,-0.008456362,-0.0038930413,-0.02165208,-0.016344003,0.01565341,-0.025118578,-0.003554516,-0.015044065,0.015518001,-0.019228239,-0.01431285,-8.7487635e-05,-0.0060359067,-0.041218843,0.028544456,-0.022640573,-0.006205169,0.014448261,-0.012241076,0.0025643294,-0.016262757,0.010345334,-0.0058361767,0.00089201424,0.010406269,-0.022938477,-0.037671097,0.044089537,-0.0152878035,0.005504422,0.004617485,0.017968925,-0.017224168,0.0045802477,0.0096344305,-0.013195717,0.02421133,-0.01015576,-0.005893726,-0.051699586,0.004844297,-0.024441529,-0.02927567,-0.014218064,-0.021286473,0.010453662,-0.012085354,-0.020812538,-0.006320268,-0.0034529583,0.015220098,0.0055721267,0.009194348,0.014326392,0.011245811,-0.020744832,-0.021733325,0.014001408,-0.037616935,-0.009837546,0.020162567,-0.03328381,-0.0023070502,-0.034719158,0.0037339344,-0.0098849395,0.0076506725,0.013087389,0.00034973898,-0.014258686,0.00054291,-0.007941804,-0.019282402,0.0004578555,0.01777935,-0.023277001,-0.016073182,0.0011941481,-0.03341922,-0.0007540652,0.017034594,0.010237006,-0.0028571538,0.0065572355,-0.0129519785,0.026567467,-0.018131416,-0.010886975,0.018239744,-0.0073798522,-0.01859181,-0.067271754,0.00030721174,-0.012139518,-0.00013054383,0.0030771953,0.0044956165,0.025145661,-0.016235674,-0.0046716495,0.00045066184,-0.026919534,-0.010629695,-0.008199084,-0.014434719,-0.028923605,-0.007271524,0.014502425,0.0032329168,0.014014948,0.007427246,-0.0053148475,0.0018500409,0.008408969,0.017657481,-0.005653373,-0.0010062666,0.0029925639,-0.016993972,-0.009099561,-0.011665583,0.023290543,-0.00054883416,-0.009593808,0.021570833,-0.012545749,-0.009241741,0.0013684887,0.015193016,0.012904585,0.039187692,0.011347369,-0.021083357,0.009675054,-0.027975732,-0.014272228,-0.018998042,-0.03542329,0.011800993,0.005589053,-0.009566725,0.0011162873,0.013229569,0.005094806,-0.013358209,-0.0069126873,-0.044820752,-0.014434719,0.020419847,0.011591107,-0.017061677,0.031631805,-0.0029383998,0.0053588557,-0.015680494,0.026702877,-0.008564691,0.016019018,0.017671023,0.015721116,-0.0016680835,-0.021272931,-0.011814534,0.008056902,0.018740762,0.025592515,-0.01936365,-0.0068179,0.011313517,-0.038456477,0.0339067,0.0021140906,0.019471977,-0.015220098,0.017142922,0.023439493,-0.012620224,-0.0066114,-0.0151117705,0.0054874956,0.009715677,-0.011692665,0.012356174,-0.0025863335,0.010392727,-0.024021758,0.007603279,0.008740724,-0.005629676,0.010704171,0.013852457,-0.014800327,0.0011983797,-0.0037914836,-0.01791476,-0.044414524,0.01163173,-0.025430022,-0.015382591,-0.004702117,0.013466537,0.035233717,0.0030991994,0.043114584,0.0011255967,-0.01565341,-0.0006461602,-0.023073886,-0.01176037,-0.021895818,0.0030247238,-0.022126015,-0.002144558,0.024766512,-0.03244427,0.039756414,0.01270147,0.020501094,-0.026499763,-0.00026299187,-0.010636466,0.003916738,-0.022423917,0.0031652118,-0.0030805804,-0.011211959,-0.0068652937,-0.014962819,-0.0033243187,0.0053487,0.07447557,0.009099561,-0.021232309,-0.030331869,0.007156425,-0.009377152,-0.006056218,0.0076709837,0.021679161,-0.03008813,0.042762518,-0.029031932,0.010196383,-0.024279036,-0.011103631,-0.005616135,0.007928263,0.010832811,0.008984462,0.008808429,0.008131378,0.020704208,0.018822009,0.009431316,-0.03580244,-0.014096195,0.029438162,0.001199226,0.002620186,-0.039241854,-0.0026049523,0.008984462,-0.03501706,0.005958046,0.007461098,-0.023710314,-0.025023792,-0.003798254,0.021476047,0.044902,0.016520036,0.032796334,-0.03257968,-0.018537646,-0.030331869,-0.012742093,-0.0022545788,-0.004065689,0.003727164] | K3: 2025-07-27T18:28:57.031Z
A4: 2 | B4: 297 | C4: computer_programmers_2 | D4: Programming,Software Development,Code Revision,Bug Fixing,System Analysis,Requirements Gathering,Problem Solving | E4: Software Engineering | F4: Program Revision,Efficiency Improvement,Adaptation,Software Maintenance | G4: 3 | H4: Software Developer,Systems Analyst,Project Manager | I4: 40 | J4: [0.016256252,0.0025177284,0.0014107516,-0.010764275,-0.0010855236,0.028832879,-0.020141827,-0.004458799,-0.015446185,-0.017437028,0.018961051,0.018700182,0.011347798,0.002558918,-0.013098366,-0.01929057,0.024494218,0.005660169,-0.0077986075,-0.014141841,-0.00045694967,0.011279148,-0.012583492,-0.01447136,-0.00027395526,0.015034287,0.007633848,-0.038553677,0.0006066919,0.009535445,0.019784847,-0.012810037,0.015446185,-0.016338632,-0.027363775,-0.012885551,-0.013812322,0.0057047913,-0.0027871784,0.003823789,0.026787119,0.008794028,-0.011237958,0.0011653289,0.003930196,0.013929027,-0.0035285952,-0.0063500986,-0.015665865,0.02419216,0.0018878671,-0.001385008,-0.016887829,-0.00718076,0.009981669,0.013922162,-0.023354633,0.01904343,-0.03166125,-0.014608659,-0.0032883212,0.007935907,-0.022091478,-6.591445e-05,-0.015885543,-0.005340948,0.01302285,0.01934549,0.012810037,-0.008848948,0.03621959,0.0193043,-0.0016690461,0.004692208,0.027803134,-0.013661293,-0.0039198985,0.0014879826,0.006353531,0.0087597035,0.023478203,0.016256252,-0.015185317,-0.0018415286,-0.011739101,0.00719449,0.009535445,0.009638419,-0.0017900413,-0.013537724,-0.0126933325,0.01425168,0.023025114,0.0025022822,-0.0020766538,-0.00041318545,-0.012343219,0.037702423,-0.004338662,-0.01213727,0.011457637,0.0106613,-0.026512519,-0.0056567364,-0.012157864,0.012192189,0.0005037173,-0.028311143,0.003356971,-0.0034856892,-0.023642961,0.034297395,0.012720792,-0.018137254,0.035670392,-0.020334044,0.02412351,-0.029876355,-0.011629261,-0.008897003,0.017491948,0.006305476,0.011814616,-0.023272254,0.020059446,0.017464487,-0.024343189,-0.0014708202,-0.005165891,-0.00021667566,0.0002700937,0.00035869476,0.025743643,0.01438898,-0.020004526,-0.0121990545,-0.013462209,0.027185287,-0.009102952,-0.032073148,0.007414169,0.027830593,-0.007434764,-0.008588079,-0.0017548583,-0.0020285991,0.0009199062,-0.0021710473,0.024796277,-0.017725356,0.005797468,-0.00838213,0.01448509,0.003943926,-0.004959942,-0.0041944976,-0.004410744,0.0017222497,-0.023327174,-0.017519407,0.009933613,0.009075493,-0.009590365,0.002437065,-0.006332936,0.022228777,-0.00488786,-0.015583485,0.0010683612,0.002776881,0.008107531,0.028256223,-0.034928974,0.009116682,0.01948279,0.006219664,-0.013263125,0.009521715,-0.009844369,-0.0030497636,-0.007620118,-0.008999977,0.03157887,0.02398621,-0.022626946,0.0069507835,0.026498789,0.0075034136,0.020388965,-0.014320331,0.029025098,0.017794006,-0.0019599493,-0.0142104905,-0.65815854,-0.027858054,-0.010482811,-0.009734529,-0.0089931125,0.020114366,0.027610915,0.02382145,-0.009418741,0.011059469,0.01438898,0.022324886,0.0056944937,-0.02163839,-0.011629261,-0.0024353487,-0.008629269,-0.030837452,0.019839767,0.0056224116,-0.028077733,0.010668166,-0.002056059,-0.012961066,0.017176159,0.0053375154,5.2506304e-05,-0.0052276757,0.006126987,0.010338647,0.0130159855,0.015707055,0.004177335,-0.00071996386,0.058709234,-0.001717101,0.004445069,6.811339e-05,0.027679564,0.038334,-0.01086725,-0.021240221,0.008842083,0.036384348,-0.005011429,0.015583485,0.027446156,-0.0068237814,-0.030453013,-0.0047196676,0.007729958,-7.980529e-05,-0.015157857,0.021967908,-0.005567492,-0.023560582,-0.006113257,-0.013407289,-0.0010666449,-0.020622374,-0.0071464353,0.009576635,-0.024247078,-0.008162451,-0.022215048,0.0069988384,-0.002493701,0.0014407858,0.0119656455,0.0016381538,-0.0103043225,-0.0036418673,-0.0035526226,-0.0043626893,-0.0052517033,0.033199,0.032265365,-0.020938164,-0.013633833,-0.011080064,0.006926756,-0.010228807,0.005598384,-0.015501105,0.030178415,0.006480533,-0.009336361,-0.029217318,0.0046372884,0.0016167008,0.034736756,0.015322616,-0.019867226,-0.0032883212,-0.004270012,0.026141811,-0.020196745,-0.009164737,0.029986195,-0.011306608,-0.0026104054,0.005646439,0.015006827,-0.0023924424,0.024617787,0.008862678,-0.012405003,-0.012219649,0.025469044,0.021858068,0.009906154,-0.026636088,-0.018755103,-0.0073661143,0.0053100553,-0.03336376,-0.011231093,-0.018192174,-0.010036588,-0.026869498,-0.0014450764,0.001978828,0.01686037,-0.017574327,0.0028609768,0.02154228,-0.0036350023,0.0005153019,0.0025194446,-0.018164715,-0.007201355,-0.006247124,-0.0052620005,-0.0010185902,0.0025005657,-0.00029133222,0.018356934,-0.010009129,-0.0011987956,-0.027404966,0.004245985,-0.0071464353,-0.0067276717,0.0054576523,-0.0056327092,-0.029299697,-0.02640268,-0.011670452,0.036494188,0.0010546312,-0.0027751648,0.012775712,-0.021212762,0.048603997,0.0117322365,-0.020498805,0.009171601,-0.025263095,-0.010469082,-0.0287505,0.009075493,-0.011642992,-0.032787103,-0.009096087,0.0023134954,-0.006820349,0.0022276833,0.03089237,-0.012851226,-0.03797702,0.0066315625,0.011697912,-0.010469082,-0.0014116097,-0.014759689,0.017231079,-0.014141841,-0.011244823,0.003731112,-0.008684189,0.018068604,0.010942765,-0.024507947,-0.0020749376,0.022269968,-0.009906154,0.012810037,0.019592628,0.011244823,-0.006329504,-0.01204116,0.006621265,0.0060652024,-0.010434756,-0.009013708,0.022077749,-0.028118923,-0.003399877,-0.020594914,0.035066273,0.024301998,-0.005667034,-0.004784885,0.0026189866,0.021157842,-0.033034243,0.004716235,-0.021995367,0.020141827,0.007228815,0.00062857394,-0.0081761805,-0.0012751684,-0.014059462,0.017848926,0.011395852,-0.009082357,0.027954163,-0.018658992,0.0009156155,-0.00271338,-0.0065835076,0.023107493,-0.030727612,0.0215972,0.017464487,0.008677324,0.028585741,0.004012576,0.001222823,-0.010215078,0.010695625,0.019716198,-0.00037928968,0.023395823,0.028146382,0.03130427,-0.027185287,0.058379717,0.02378026,0.011196768,0.0047093704,0.0087597035,-0.014567469,0.01934549,0.0016664718,0.047038782,0.013496534,-0.0021281412,0.020237936,-0.0017969062,0.0050903764,-0.0017376959,0.00423912,0.007681903,0.0027803134,0.0430571,0.010723085,0.035285953,0.03089237,0.008560619,0.027803134,-0.009329496,0.0063363686,-0.013421019,0.0012048024,0.0062162317,-0.029958734,0.026498789,-0.011560611,0.008848948,0.009185332,-0.0067173745,0.0028472468,2.6574948e-05,0.0033037674,-0.0075308736,0.019084621,-0.0067414017,-0.005306623,-0.0139770815,0.003998846,0.029025098,0.018645262,0.020759674,0.010530866,0.006566345,-0.004050333,-0.020237936,0.016105223,-0.009768854,0.013729943,0.002684204,0.0156109445,-0.0038684113,-0.007990827,0.019606357,-0.002325509,-0.012130405,-0.0034822568,-0.00045780776,0.018288285,-0.009102952,-0.029162398,0.04300218,-0.009151007,-0.012507978,-0.039432395,-0.015844354,-0.0023838612,-0.021185301,-0.0071533,0.009858099,-0.0005972525,-0.00029369205,-0.028283682,-0.01691529,-0.015652135,0.032594886,0.022215048,-0.014649848,-0.003926764,-0.0029828302,0.020842053,0.0877618,0.020086907,-0.006487398,0.014128111,-0.010194482,-0.011134984,-0.054233275,-0.013922162,0.013654428,-0.03547817,0.0008714223,-0.0031922117,0.0022602917,-0.018658992,-0.010263132,0.0047814525,0.02894272,-0.016997669,-0.010414162,-0.009267711,-0.003985116,0.0067414017,0.02174823,-0.017478216,0.01709378,0.017437028,0.030260794,0.03372074,-0.004149875,-0.014073191,-0.02406859,0.03586261,-0.005378705,0.022269968,-0.015432456,0.051240146,0.006847809,0.014993098,0.0215972,-0.006659022,0.01447136,0.0104210265,0.016160144,-0.0058043334,0.032896943,0.0053958674,-0.01447136,0.020265395,-0.029793976,-0.030535392,0.005011429,0.012906146,-0.02391756,0.0030223036,0.004712803,0.0015300305,-0.0011593221,-0.004826075,-0.010009129,-0.041436967,-0.020938164,-0.027363775,0.0154049955,-0.011581207,0.007187625,0.004850102,0.015816893,-0.01661323,-0.030755071,0.0022929003,-0.004898157,-0.026553709,-0.008540024,0.00087442575,-0.006919891,-0.0075720632,-0.0053134877,-0.014155571,-0.0025005657,-0.0081761805,-0.049070816,-0.046681806,0.022887815,-0.01068876,0.0051624584,0.01702513,-0.030150954,-0.013970217,-0.01695648,0.009411876,0.0022620081,0.0041292803,-0.01082606,0.0011361528,0.0027030825,0.0024885521,0.0037688692,0.012130405,0.00422539,-0.0040743607,-0.0060034175,-0.020567454,-0.01686037,-0.04083285,0.01948279,0.0061372845,-0.002586378,0.006662455,-0.0077848774,-0.0038443839,0.01675053,-0.018398123,0.012981661,0.0025211608,0.039487317,0.015075477,0.03635689,-0.0016638974,0.021226492,-0.006147582,0.003816924,-0.027816864,0.041629188,0.03599991,-0.023437012,0.015336346,0.0010923885,-0.02165212,-0.0063638287,0.0080594765,-0.005292893,0.034846596,-0.01680545,-0.02836606,-0.014032002,-0.024810007,0.0057700085,-0.00021227778,-0.01680545,-0.0054576523,-0.0106613,-0.0018912996,0.012713927,0.004963374,0.022517106,-0.028585741,0.016366092,-0.0057562785,-0.01909835,0.015940463,-0.013572048,-0.008910733,-0.006562913,0.0041842,-0.009343226,-0.025798563,-0.019729927,-0.020512534,0.024768816,0.027308855,0.00604804,-0.00075214345,0.010434756,0.0026464465,0.009068627,0.011471367,-0.011478232,-0.0046750456,-0.010393566,0.016352361,0.022462185,0.0034685268,0.018260824,-0.03146903,0.017656706,0.014237951,-0.008656729,-0.012370679,-0.019469058,-0.024631517,-0.006247124,-0.0031063994,0.0010820911,0.01672307,-0.0337482,0.0067173745,0.019592628,0.0109153045,0.0014828339,0.018755103,0.012150999,-0.0037688692,0.009013708,0.016160144,0.020114366,-0.015995383,-0.0015737946,-0.038800817,0.000657321,0.0044004465,0.011684181,0.028393522,0.023299713,0.008560619,-0.00843705,0.013702483,-0.008615539,-0.022517106,0.032347746,-0.0013112095,0.0070709204,-0.0061647445,-0.010475947,0.0074896836,-0.0020320315,0.008224236,0.015899274,0.026183002,-0.018823752,-0.002203656,0.017739085,-0.0033123486,0.02383518,0.005945065,0.035423253,0.05027905,0.015212776,-0.025015956,-0.014608659,0.013585778,-0.0034444993,0.025153255,0.034297395,-0.0045858007,-0.010372972,0.02143244,-0.00845078,-0.02139125,-0.0019410707,0.01086725,-0.013221934,0.0054885447,-0.0040091434,0.015363806,-0.022009099,0.028118923,0.004221957,0.025166985,-0.007043461,-0.0151441265,-0.0010426175,0.023038844,-0.027377507,0.016942749,0.029491916,0.004925617,0.0130159855,-0.024933577,-0.01455374,0.0010014276,-0.004091523,0.007496549,-0.009446201,-0.0066384273,0.010517136,0.017656706,-0.012679602,-0.03583515,0.011697912,0.033885498,-0.015693324,-0.03871844,-0.011649856,0.0012854659,0.0063981535,0.015102937,-0.019276839,-0.034544535,-0.01320134,-0.010201347,0.0011267135,0.021720769,-0.006700212,0.0031424407,-0.018713912,-0.011011414,0.011931321,-0.0017780276,0.017807735,-0.039350014,-0.0071052453,-0.0017007967,-0.0060102823,0.006593805,0.012727657,-0.01898851,-0.011780291,0.020869512,-0.020745944,0.015789434,0.0018775697,-0.0049908343,-0.0075651985,0.012631548,-0.022077749,-0.0052139456,0.029601756,-0.02398621,0.003950791,-0.003109832,-0.00063071924,0.019606357,-0.020416426,-0.003490838,0.005138431,-0.012967931,0.007894717,-0.016173873,-0.012858091,0.022942735,-0.02139125,0.006339801,0.008251696,-0.0054370575,0.00854689,-0.0016192751,-0.0014665296,-0.011505692,-0.024439298,-0.009418741,-0.008629269,0.01433406,-0.0064290455,-0.031606328,-0.011629261,-0.016009113,-0.0031218457,0.011347798,-0.011787156,-0.0011799169,-0.013606373,0.009659015,0.0041292803,0.009274577,-0.013572048,-0.014608659,-0.034654375,-0.019084621,-0.04149189,-0.00014298449,-0.047258463,0.025304284,0.018192174,-0.012350083,0.0059107402,-0.018398123,-0.050251592,-0.008498834,-0.002184777,0.0047883177,0.010997684,0.0012399855,-0.008231101,0.018755103,0.00068520993,0.020031987,-0.019743659,-0.009967938,0.00955604,0.008183046,0.025125796,-0.0075926585,-0.015157857,-0.005519437,0.006054905,-0.004235687,0.0032213877,-0.0050766463,-0.029409537,-0.020320315,0.010249402,0.0060171476,0.0094873905,0.012624682,-0.0029622351,0.002135006,-0.016022842,0.0032196715,-0.00851943,-0.016572041,-0.0111212535,0.0024971333,-0.0043764194,0.009384416,-0.018425584,-0.010235672,0.0045960983,-0.014038866,0.004297472,0.001271736,-0.015171587,0.0078054722,-0.002474822,-0.0007354101,-0.0167368,-0.004925617,-0.011711641,0.0076407134,-0.009370686,0.0003591238,-0.020485075,-0.01672307,0.00719449,-0.0038855737,-0.008498834,-0.018370664,-0.011045739,-0.04335916,-0.003109832,0.004191065,0.013702483,-0.003998846,-0.001596964,-0.015391266,0.012123539,-0.020251665,-0.0016733367,0.0009868396,-0.0008658445,-0.0020457616,-0.011807751,-0.0012314043,-0.0064290455,0.03830654,-0.020169286,0.013729943,0.21407726,0.0065560476,-0.00058051915,0.048109718,0.0075583337,0.02894272,0.020402694,0.006820349,-0.008732243,0.034791674,0.011155578,-0.00537184,-0.014581199,-0.011581207,0.0022225345,-0.010173888,-0.025153255,-0.017601786,-0.013455343,0.021404982,0.025784833,0.009350091,-0.025647532,-0.013633833,0.045940388,0.020210477,-0.027432425,0.021295141,0.038334,-0.01418303,-0.016297443,-0.014114381,0.006799754,0.010105238,0.0059107402,-0.0083684,0.027308855,0.0056086816,0.0004959942,-0.022475917,0.0072974646,0.0026498789,0.026993068,-0.05077333,0.019729927,0.035395794,-0.010311187,-0.0026258517,-0.0025915266,0.014773418,-0.011903861,-0.014855798,0.025386665,0.027473615,-0.0037688692,-0.002665325,0.00035140073,0.0025915266,0.0046613156,0.0087597035,-0.011052604,0.017395837,-0.028228762,-0.0036967872,-0.010723085,0.0015180168,-0.014237951,0.0043146345,0.008862678,-0.025990782,-0.008752839,-0.032567423,-0.0069988384,-0.0043009045,-0.01697021,-0.012260839,0.015748244,0.036768787,0.015583485,0.025263095,-0.006281449,-0.017958766,-0.02158347,-0.020951893,0.00048741297,-0.020993082,0.037565123,-0.009967938,-0.01887867,-0.021350062,-0.016091492,-0.019647548,-0.025359204,-0.018507963,-0.0025486206,0.035093732,-0.007201355,-0.0004346385,-0.00042648634,-0.003985116,-0.0014579484,0.0630479,0.004671613,-0.010647571,-0.010400431,-0.0066246972,-0.006473668,0.012048025,0.008011421,-0.0034788242,-0.006253989,-0.015226507,0.015954193,-0.013489669,0.007002271,-0.0018689885,0.020581184,-0.0436063,0.009082357,0.0033809985,0.02399994,-0.0067894566,-0.00087313855,0.016173873,-0.003145873,-0.006562913,-0.023244793,0.0031304269,-0.013256259,-0.03586261,0.005032024,-0.034434695,0.00118764,-0.0022208183,-0.023340903,-0.01452628,0.010002263,0.011581207,-0.016187603,-0.0073386542,0.0126933325,0.021363791,-0.00019447177,0.015967924,0.0034959866,0.013826053,0.010544596,0.0061716093,-0.023382092,-0.0055846544,-0.023368362,-0.008828353,0.014718499,-0.002191642,0.016091492,-0.0008671317,-0.032045685,-0.01893359,0.030453013,-0.0028420982,-0.015514836,0.017697897,0.046214987,0.030013654,-0.00488786,-0.0050423215,-0.17826958,0.013064041,0.005625844,-0.015583485,0.023739072,0.014787149,0.01904343,0.014114381,-0.006068635,0.0039473586,0.0005243122,-0.025455315,-0.05321726,-0.015459916,0.022407267,-0.0076407134,-0.020704754,0.026910687,0.019716198,0.014649848,0.015583485,-0.00042283934,-0.00010892779,-0.0068031866,0.019441599,0.025908401,-0.017505677,-0.0030377498,0.009308902,-0.011512557,-0.007434764,-0.0052997577,0.021281412,0.010702491,-0.0006826356,-0.020910703,-0.0065800752,0.002239697,0.00038980166,0.0031338595,0.0075240084,0.027624644,0.025166985,0.006147582,0.017697897,0.01433406,0.04503421,-0.019853497,-0.0008298034,-0.013929027,0.008402725,-0.03124935,0.0019565169,-0.020718483,0.029464457,0.000791188,-0.008931328,0.011759696,-0.027089177,0.002452511,0.0035045678,-0.0045892335,0.01071622,-0.0025898104,-0.0046098283,-0.028022813,-0.015913004,0.032512505,-0.015885543,-0.0064324783,0.009940479,-0.009157872,-0.007949637,-0.0063569634,0.015748244,-0.0037002196,-0.022077749,-0.0032986188,0.008718514,-0.012734522,0.0119656455,0.002924478,0.023739072,-0.009480526,-0.006538885,-0.0037894642,0.016160144,0.0035938125,0.014086922,-0.009700204,0.029134938,-0.024535408,-0.018356934,-0.004050333,0.020636104,-0.0033380922,-0.0026464465,0.0006135568,-0.009192197,0.013853512,0.01709378,0.003957656,-0.018617803,-0.0036281373,0.003583515,0.006895864,0.014951908,0.0070503256,0.015501105,0.0111487135,-0.034160096,0.025400395,0.0015986802,0.014636119,-0.014704769,0.024988497,0.0062711514,-0.016173873,-0.0112654185,0.0031750493,0.059697792,-0.011128118,0.010517136,0.0013412437,0.009343226,-0.020306585,-0.080622226,-0.02162466,0.015006827,0.017395837,-0.0154049955,0.014773418,-0.005505707,0.013771133,-0.00030227329,0.019084621,0.006401586,-0.023107493,-0.017903846,-0.025029685,-0.0039027361,-0.007407304,-0.021185301,0.003985116,0.0017660139,0.02877796,-0.0017917575,-0.016146412,0.0069130263,0.0070125684,-0.034022797,0.049674932,-0.032128066,-0.014608659,0.007915312,-0.011629261,0.011704776,-0.022942735,0.0021470198,-0.003398161,-0.008903868,-0.0023134954,-0.023739072,-0.03168871,0.024906116,-0.027075447,0.011594936,0.00093020365,0.02666355,-0.030507933,-0.0005037173,-0.008107531,-0.012830632,0.025949592,-0.009514851,-0.024988497,-0.05739116,-0.005354678,-0.023642961,-0.023423282,0.0020972488,-0.004022873,0.00712584,-0.00842332,-0.008951923,-0.022022828,-0.009858099,0.00839586,0.0075651985,0.0034753918,-0.0025417556,0.0034221883,-0.005265433,-0.030535392,0.026636088,-0.042727582,-0.0142104905,0.021789419,-0.03146903,-0.0070365956,-0.019908417,-0.0008289453,-0.017656706,-0.010524001,0.022558296,-0.008725379,-0.0023049142,-0.02156974,0.015830625,-0.006302044,0.0018466773,0.028640661,-0.0031046832,-0.00943247,-0.003356971,-0.019977067,0.011910725,0.012253974,0.029189859,-0.0075171436,0.0031613193,-0.007462224,0.017711626,-0.00084095896,-0.0048947246,0.003569785,-0.0218718,-0.013633833,-0.08128126,0.017945034,-0.009734529,-0.019455329,0.004784885,0.0018209337,0.01692902,-0.022558296,-0.0005002848,-0.003926764,-0.01684664,-0.007908447,-0.002437065,-0.020265395,-0.03135919,0.017464487,0.010565191,-0.0012665872,0.01680545,0.003624705,-0.025304284,-0.013386694,-0.0011069766,0.027418695,-0.01665442,0.00024413555,0.001985693,-0.0071189753,-0.019729927,-0.017972495,0.000629003,0.0027785972,0.009315766,0.018356934,-0.01647593,-0.0048089125,0.008086937,0.031606328,0.03297932,0.046544507,-0.005667034,-0.027446156,0.0047471276,-0.039350014,-0.0139496215,-0.019963337,-0.010723085,0.0033586873,-0.0006980818,0.007832932,0.008848948,0.019276839,-0.0025829454,-0.011546882,0.004953077,-0.05783052,-0.0033209298,0.0036693271,-0.0029914114,-0.011533152,0.028036542,-0.013750537,0.008148721,-0.022064017,0.00237528,0.00058995845,0.0046956404,0.03179855,-0.015556025,-0.004445069,-0.02836606,-0.014814608,-0.005879848,0.014938178,0.023807721,0.0116155315,-0.017148698,0.023464473,-0.011553747,0.01935922,0.018370664,0.017409567,-0.022036558,0.019167,0.020512534,-0.0064565055,-0.0049565095,-0.011011414,-0.005430192,0.004657883,-0.024507947,0.008347806,-0.007510279,0.009205926,-0.00845078,0.035780232,0.00021249232,-0.0040880903,0.0071327053,0.014951908,-0.02176196,-0.0017711626,0.009810044,-0.015418726,-0.027597185,0.013221934,-0.015693324,-0.022215048,-0.015665865,-0.0015274561,0.014787149,0.0070983805,0.011128118,-0.0060652024,-0.02180315,-0.0075857933,-0.009761989,-0.024370648,-0.027418695,-0.0054095974,-0.017931305,0.0118489405,0.024562867,-0.010105238,0.024823736,0.024384378,0.0072837346,-0.021185301,-0.013084635,-0.014128111,-0.007462224,-0.004544611,0.020814594,-0.004472529,-0.0086429985,-0.016585771,-0.022599487,-0.00035247338,0.0014356371,0.065409444,0.022530837,0.0012305462,-0.0077505526,-0.0052105132,0.009885559,0.020375235,0.004826075,0.015459916,-0.029491916,0.02165212,-0.027679564,0.015844354,-0.021350062,-0.019716198,-0.008560619,-0.0058558206,0.023148684,-0.003803194,0.019167,0.009535445,0.018713912,0.032073148,0.00727687,-0.044292796,-0.019963337,0.02162466,0.007887852,-9.079997e-05,-0.032924403,-0.017560598,0.022091478,-0.013029716,-0.007716228,0.011800886,-0.019922147,-0.01677799,-0.011711641,0.02432946,0.026031971,0.0066246972,0.015185317,-0.029684136,-0.02621046,-0.034544535,-0.0072837346,-0.009995398,-0.0069507835,0.022201318] | K4: 2025-07-27T18:29:02.672Z
A5: 3 | B5: 298 | C5: computer_programmers_3 | D5: Programming,Software Development,Inventory Management,Data Storage,Data Retrieval,Equipment Control | E5: Software Development | F5: Inventory Tracking,Data Management,Equipment Control | G5: 2 | H5: Developers | I5: 40 | J5: [-0.004020535,-0.01679997,-0.006936717,-0.028188609,-0.015184853,0.03194341,-0.014384197,0.0043069767,0.00710237,-0.012810494,0.010153145,0.026835777,0.011499075,0.02813339,-0.0060118213,0.0059842123,0.014246153,-0.0008347355,-0.004351841,-0.012637939,-0.01793193,0.004396705,-0.0008066953,0.007965146,0.00016435877,-0.01548855,0.0023070623,-0.036774952,0.012002936,0.016496273,0.010705321,-0.024613267,0.024323374,-0.023067173,-0.020389115,-0.013307453,-0.015806051,-0.0062188874,0.0020861917,-0.0079168305,0.032964934,0.031142753,-0.009628577,0.016592903,0.01586127,0.017103666,-0.006681335,0.0054320362,-0.008427593,0.005466547,-0.014798329,0.019229546,-0.015060613,-0.006771064,0.00744748,0.034869943,-0.007475089,0.00020652694,-0.014259958,-0.020513356,-0.007951342,0.004866055,-0.025759032,-0.0026142106,-0.00015821151,0.003651267,0.0011768261,-0.0079168305,0.016855186,-0.009179934,0.030645793,0.024420004,0.0054354873,0.015875073,0.0041723833,-0.0073163384,0.019422807,0.0033078822,0.00998059,0.018484108,0.01914672,-0.013134898,-0.02299815,-0.012969245,-2.3915065e-05,0.0053906227,0.0062464965,0.02274967,-0.00024632248,-0.0078063947,-0.0040067304,0.0051110834,0.015378115,0.009442218,-0.024295764,-0.0014667187,0.020471944,0.040999103,-0.003627109,-0.019657481,0.012120274,0.021203576,-0.022501191,-0.0094008045,-0.029182527,-0.00018722234,0.0012070233,-0.027070452,0.015309093,-0.002446832,-0.033102978,0.042186283,0.02043053,-0.013728487,-0.0055424715,0.0004257798,0.020278681,-0.021093141,-0.007861612,-0.02334326,0.001012036,0.014087402,0.025400117,-0.02840948,0.019284762,0.03188819,-0.013348866,0.0013096936,0.017448777,-0.0065294867,0.0054769004,-0.009159227,0.01051206,0.0082895495,-0.04853631,0.016620511,-0.0018860277,0.031832974,-0.006098099,-0.03028688,0.009076401,0.022321735,-0.018235628,-0.010988312,0.0025555417,0.0032026235,0.0018342612,0.010829561,-0.013500715,-0.0018791256,-0.014356588,-0.02215608,-0.002234589,-0.014660285,0.0016737849,-0.020692814,-0.009663088,-0.007171392,-0.0023432989,-0.019795526,0.0084483,-0.006229241,-0.0016565294,-0.008579442,0.013293648,0.032247107,0.0027488035,-0.01667573,-0.005042061,0.0054769004,-0.0008476772,0.017255515,-0.02509642,-0.013197018,-0.017379755,0.012458482,-0.012983049,0.017959539,-0.022901518,-0.012976147,0.00525603,-0.007419871,0.022901518,0.016979426,-0.026255991,-0.007002288,0.00021159575,-0.004669342,0.0061809253,-0.015447137,0.03163971,0.0069091083,-0.018249432,-0.011657826,-0.6506848,-0.030811448,-0.014591264,-0.012099567,-0.00960787,0.02932057,0.037354738,0.03616756,0.0020585828,0.022321735,0.028657958,0.024364786,0.003520125,-0.013127996,-0.003979122,-0.007965146,-0.010194558,-0.01811139,0.01902248,0.0074543823,-0.036001906,0.022418365,0.0038169199,-0.011947718,0.014087402,-0.0071230764,0.003989475,0.013328159,0.010097927,0.0027211946,-0.006501878,0.018373672,0.013873434,0.010449939,0.054058075,-0.006940168,-0.01840128,0.026601102,0.032026235,0.03208145,-0.01214098,-0.015695617,0.018415086,0.013576639,0.0066123134,0.020223463,0.030673403,0.0024174976,-0.009083303,-0.026780559,0.021106945,-0.025413923,-0.03544973,-0.013107289,0.016137358,0.010836463,0.004086106,5.262932e-05,0.022018036,-0.014605068,0.009904666,0.013341964,-0.0394254,-0.00610155,-0.034014072,-0.012720766,-0.0039411597,-0.014936374,0.0038031153,-0.0056874175,0.026573492,-0.013252235,0.017752474,-0.011457662,0.005135241,0.0145360455,0.021907602,-0.002234589,-0.008096288,-0.0009801133,-0.006067039,-0.008096288,0.0014020106,-0.016703337,0.024820331,0.006643373,0.0031491315,-0.023577936,0.018125193,0.018608347,0.02359174,0.008123896,0.009614773,0.0035615382,-0.027387952,0.01855313,-0.018773999,-0.0020948194,0.019229546,-0.009352489,-0.0145360455,-0.0037202889,-0.0013062424,0.0062464965,0.008310256,0.015971705,-0.008544931,0.0003166387,0.04246237,-0.012127176,0.0066261175,-0.01454985,-0.010967605,0.0004098185,0.0023432989,-0.03194341,0.007002288,-0.015447137,-0.017821496,-0.008896943,-0.014660285,-0.004955784,0.034455813,-0.0006125708,-0.011002116,0.020223463,-0.0070575057,-0.0041171657,-0.006974679,-0.01679997,0.0010499981,-0.013604248,0.004831544,-0.01586127,0.015033005,0.0039998284,0.018912043,-0.017959539,-0.014218544,-0.030369706,-0.012534406,-0.014066695,0.0058116573,0.0012786336,0.016758556,-0.029292962,-0.020251073,0.0036616202,0.026918603,-0.016841382,0.0042724656,0.014232349,0.010242874,0.04646565,0.015819855,-0.024944572,-0.011657826,-0.03268885,0.012582721,-0.012631036,-0.018677369,0.0014667187,-0.016868992,-0.01711747,-0.0048418976,0.003627109,0.008310256,0.025248269,-0.0309771,-0.031474058,0.015999313,0.027277518,-0.02215608,0.014577459,-0.013976967,0.006674433,-0.014881155,-0.023067173,0.021728145,-0.009835644,0.016192576,0.003463182,-0.028989265,0.017738668,0.016841382,0.007847808,0.012541308,0.019754114,0.0064949756,-0.008827921,-0.032219496,0.0052146167,0.011664728,0.0007221433,-0.021037923,0.03636082,-0.018263238,0.005780597,-0.0131418,0.024696093,0.015806051,-0.0057598907,0.0035373806,0.014646481,0.015806051,-0.028326653,0.01442561,-0.026683928,0.026960015,0.021300208,0.0028954754,0.0028230022,0.009242054,0.004151677,0.020886075,0.024640875,-0.014453219,0.0064570135,-0.017793886,-0.0060083703,0.015060613,-0.033958852,0.01771106,-0.048729572,0.004093008,0.0005021355,0.008324061,0.031308405,-0.004393254,-0.022542605,-0.0023208668,-0.015833661,0.014467023,0.0024675387,0.020968901,0.029983182,0.022570213,-0.009959883,0.05634961,0.026062729,-0.0035253016,0.023122389,0.023646958,-0.022100864,0.017559212,0.00059229555,0.020761834,0.008144603,-0.025455335,0.009959883,-0.013721585,-0.0036029515,-0.02430957,-9.835643e-05,0.008779606,0.004227601,0.03404168,-0.008158407,0.02337087,0.024985986,0.007965146,0.016813774,-0.011133258,0.0149225695,0.00067469064,-0.01067081,-0.0068676947,-0.023301847,0.016192576,-0.01855313,0.018318454,4.8854676e-05,0.0063845403,0.013583541,0.0059220926,0.0046900488,-0.006022175,0.0057081245,0.0073577515,-0.0038169199,0.0039963773,-0.017448777,0.0300384,0.019643677,0.008579442,0.031087535,-0.027871108,0.01961607,-0.009739012,0.010622495,-0.0013286746,0.020913685,0.012534406,0.026338818,0.003093914,0.001842889,0.026352622,-0.006933266,-0.01899487,0.0240887,-0.0022760024,0.015253875,-0.0056149443,-0.024033481,0.047514785,-0.0051490455,-0.010443037,-0.015640398,-0.0056494554,-0.013383377,-0.009725208,0.0053492095,-0.0071161743,-0.003370002,0.004293172,-0.011623315,-0.018125193,-0.012175491,0.019754114,0.016579099,-0.0010499981,-0.018663565,0.0017445325,0.028796002,0.06283768,0.017862909,-0.010615593,0.016413445,-0.019478025,-0.024516635,-0.039121702,-0.014032184,0.02274967,-0.010953801,0.0036685225,0.01132652,0.0048557017,-0.028437087,0.0054285848,-0.0112160845,0.008358572,-0.021824775,-0.02196282,-0.0309771,-0.0059151906,0.004300074,0.010374015,0.01163712,0.026960015,-0.0020482296,0.04221389,0.04039171,0.006139512,-0.028381871,-0.00797895,0.03213667,-0.018194215,0.020044006,-0.023260433,0.023301847,0.027733063,0.032992546,0.023923045,0.028161,0.013638759,-0.000732928,0.019574655,-0.01016695,0.022514995,0.00088607066,-0.0066192155,0.025248269,-0.0026349172,-0.030093618,0.005366465,0.009801133,-0.018856827,-0.003157759,0.022418365,0.0011293734,0.008337865,-0.012099567,-0.012437775,-0.054665472,-0.014398001,-0.012520601,0.0152676795,-0.013700878,-4.39746e-05,-0.0035822447,-0.0020689361,0.004386352,-0.025952294,0.003439024,0.010298091,-0.02255641,-0.016330618,-0.00052758737,0.018539324,0.0055148625,0.013252235,0.0002922653,0.0018308101,-0.014149522,-0.037271913,-0.034925163,0.0021396838,-0.026918603,-0.012720766,0.027760671,-0.029182527,-0.008903845,-0.011857989,0.019422807,-0.00581856,-0.013576639,0.025165442,0.010698419,-0.006974679,0.009676892,0.021769557,0.010091025,0.01736595,-0.014177131,0.001661706,-0.010367113,-0.019063892,-0.040971495,0.035477336,0.0022673747,-0.014115011,-0.0034459264,0.01051206,0.020706618,0.0094008045,-0.014577459,0.016413445,-0.018056171,0.0309771,0.02477892,0.015944095,-0.003585696,0.015971705,0.0015978607,0.0097666215,-0.012727668,0.028188609,0.028796002,-0.0025227563,0.014687894,0.0037720555,-0.016137358,-0.006774515,0.008869334,-0.019008676,0.026048925,-0.02487555,-0.036636908,-0.011989132,-0.007178294,0.002935163,0.022666844,-0.010691517,-0.019795526,-0.0017221004,0.0057874997,0.029707095,0.010139341,0.006439758,-0.024737505,0.007274925,-0.012658645,-0.0026573492,0.03707865,0.009883959,-0.006708944,-0.019892158,0.0036409136,-0.017959539,-0.04668652,-0.03426255,-0.02381261,0.045582168,0.030010791,0.019643677,-0.00078814564,0.007785688,-0.014453219,0.016868992,0.012486091,-0.013238431,0.0065881554,-0.0063845403,-0.014398001,0.009718305,-0.008772704,0.010939997,-0.009090205,0.009276565,0.0012631037,-0.0011949444,-0.016744751,-0.003792762,-0.035532556,-0.015046809,0.0019412454,0.014591264,0.014149522,-0.05980071,0.00024589107,0.015792247,0.0065812534,0.009097108,0.013197018,0.012575819,-0.011568097,-0.009435316,0.0206514,0.016040726,-0.0145360455,0.014328979,-0.042848893,-0.022915324,0.014342784,-0.0040826546,0.021037923,0.024240548,-0.011354129,0.0023553777,0.010905486,-0.0055424715,-0.01548855,0.0019792076,-0.017669648,-0.0042759166,-0.022542605,-0.02885122,-0.0028057466,0.017048448,0.011726848,0.00700919,0.01761443,-0.014087402,-0.0178353,0.035532556,-0.012210002,0.039342575,0.00973211,0.02863035,0.046824563,0.023619348,-0.01679997,-0.015723225,0.009835644,-0.0002838532,0.028147196,0.0319158,-0.014853547,-0.027429366,0.02593849,-0.015971705,-0.010091025,-0.017669648,0.016372032,-0.020126833,-0.007620035,-0.012527504,-0.004189639,-0.033213414,0.011947718,-0.012589623,0.010884779,-0.016040726,-0.0015409174,0.0059497016,-0.000437643,-0.036277995,0.013272942,0.033241022,-0.008586344,0.011706141,-0.010201461,-0.023177607,0.004921273,-0.006729651,0.00027263715,0.0010689792,-0.00017676118,0.03376559,0.012838103,-0.012851907,-0.020982705,0.013341964,0.025137834,-0.010615593,-0.024516635,-0.012071958,-0.0050179036,0.012147882,0.0010784697,-0.025013594,-0.033379067,-0.024420004,-0.019905962,-0.0017876714,0.015350506,0.00738536,-0.0058461684,-0.010070318,-0.002443381,0.0040101814,-0.0036305604,0.0172141,-0.02102412,-0.015833661,0.00047021278,0.008137701,-0.009725208,-0.007889221,0.004627929,-0.0038203709,0.009704501,-0.031584494,0.028492305,0.008786508,0.0011095296,-0.020679008,0.0152676795,-0.030424923,-0.0016177045,0.017918127,-0.006367285,-0.01736595,-0.0032750966,-0.005028257,0.0077304705,-0.03920453,0.004393254,0.0007342221,-0.011540488,0.010456842,-0.02183858,-0.035781037,0.022045646,-0.00860705,0.00040313197,0.016606707,-0.014605068,0.02934818,0.002869592,-0.0030749326,0.0062879096,-0.035284076,-0.01167163,-0.0067020417,0.014508436,-0.010035807,0.012058154,0.010028905,0.0011604334,-0.0115957055,-0.0038790398,0.012444677,0.00043915285,0.0004119754,-0.0030801094,0.012189295,0.016648121,-0.016703337,0.0004089557,-0.04138563,-0.022694454,-0.03498038,0.005031708,-0.030866664,0.025151638,0.004189639,-0.026904799,-0.02297054,-0.013155605,-0.045416515,-0.0234675,-0.002227687,0.00064578763,0.019201936,0.028078174,0.014660285,0.029265353,-0.006515682,0.004393254,-0.009580262,0.002062034,0.0027453525,0.0073301424,0.016289206,-0.02124499,-0.018166605,-0.040640187,-0.00973211,0.005859973,0.016868992,0.0016893148,0.00023898888,-0.021300208,-0.011395542,-0.0028488855,0.0012622409,0.020251073,0.0035684404,-0.012168589,-0.017131275,0.0005051552,0.012596526,-0.0051732035,0.0035028695,0.017186493,-0.004828093,0.0053492095,-0.017172689,-0.0030852861,-0.0059600547,0.008724389,-0.0053423075,0.012016741,-0.006567449,0.013652563,0.0015538591,-0.003385532,-0.012099567,0.00879341,-0.0025141286,-0.0006699454,-0.009055695,-0.00378586,-0.030645793,-0.020320093,0.0039031974,0.007050603,-0.0034580051,-0.016109748,0.003157759,-0.041606497,0.0033251378,-0.0076476443,0.01679997,-0.008993574,0.004672793,-0.012071958,-0.024489027,-0.025193052,0.0069850325,-0.012085763,-0.010995214,-0.008959063,-0.020126833,-0.012851907,-0.0040412415,0.0067952215,-0.004824642,0.013459302,0.2118149,0.020251073,-0.005935897,0.022211298,0.016620511,0.013169409,0.03241276,0.020458138,0.010663908,0.01711747,0.005004099,-0.007178294,-0.015502354,-0.0112367915,-0.009538849,-0.010691517,-0.016758556,-0.021396838,-0.022307929,0.022100864,0.025897076,-0.0018532423,-0.018277042,-0.0262836,0.003923904,0.01921574,-0.021659123,0.032578412,0.019809332,0.0041344212,-0.00041521082,-0.017849104,-0.0015952723,-0.015543767,0.016454859,0.0014649932,0.004721109,-0.0030559516,-0.0054182317,-0.019188132,0.015157244,-0.013473106,-0.0011785517,-0.02618697,-0.0022552959,0.009428414,-0.02487555,-0.010463744,-0.0009145423,-0.029845139,-0.0060911966,-0.022169886,0.011802772,0.03638843,-0.012285926,0.016026922,-0.004020535,0.015336702,0.011574999,-0.012479188,-0.010284287,0.017531604,-0.018069975,-0.010974508,-0.036305603,0.022349343,-0.019132914,-0.0010534491,0.0034683584,-0.034538638,-0.009000476,-0.023798807,-0.0053043454,-0.010815756,-0.018125193,-0.021134553,0.016192576,0.022680648,0.020320093,0.028492305,-0.01326604,-0.012009839,-0.029596658,0.0029420652,-0.019132914,-0.010139341,0.029375788,-0.02932057,-0.010739832,-0.0041723833,-0.004086106,0.0028195512,-0.006298263,-0.00463138,0.008993574,0.026242187,0.0008567363,0.0014511888,-0.0065398403,-0.00029808903,-0.021010315,0.06217507,0.0006004919,0.0037582512,-0.012161687,0.013569737,0.0003696994,0.01514344,0.0131418,0.007143783,-0.005998017,-0.022225102,0.0060497834,-0.0041482258,-0.0038272731,0.0047797775,0.004493336,-0.033848416,0.006567449,4.1548043e-05,0.023854023,-0.02356413,0.004589967,0.022722062,-0.0047763265,-0.00073379074,-0.01279669,-0.0032233302,-0.001515897,-0.028519915,0.016620511,-0.028685568,0.00035675778,-0.019188132,0.0059289946,0.010643202,0.029817529,0.01207886,-0.012962342,0.013286746,0.018801609,0.028934047,0.017421167,-0.0023174156,0.014839742,0.011568097,0.01204435,0.007295632,-0.007129979,-0.033102978,-0.01996118,-0.012417069,0.019422807,-0.0075924266,0.02324663,-0.014729307,-0.033020154,-0.0031370525,0.018787805,0.0097597195,-0.026821973,0.00189293,0.04555456,0.012071958,-0.027857304,0.0028799453,-0.17912605,0.01038782,0.010843365,-0.024944572,0.009580262,0.012782886,-0.0020033652,0.026987625,-0.011333422,0.013749194,0.010339504,0.010891681,-0.03282689,-0.023978263,0.0063776383,0.008427593,-0.025372509,0.043097373,0.010415428,0.00069280894,0.012244513,0.0016202928,-0.021507274,-0.019919766,0.006270654,0.026104143,-0.014273762,0.011761359,-0.0061533167,-0.019132914,0.0004158579,-0.004269014,0.019767918,0.020734226,0.0021672926,-0.010650104,0.014011478,0.00024847942,-0.0074405777,0.0064984267,0.00093611167,0.043953247,0.028657958,0.00916613,0.020899879,0.02368837,0.038265828,-0.02356413,0.0050179036,-0.015543767,0.008482811,-0.023715978,-0.0069125593,-0.019643677,0.016841382,-0.0024416554,0.0040067304,0.0072887293,-0.020416725,-0.029651877,-0.008972867,-0.01617877,-0.0011751006,-0.015226266,0.0005564903,-0.02709806,-0.016786166,0.028713176,-0.014101206,0.0037720555,-0.0015020926,-0.006370736,-0.0022225103,0.011685435,0.005363014,0.0042034434,-0.002543463,0.014950178,-0.0022328636,-0.019036284,0.007840906,0.0021293305,0.019629873,-0.014632677,0.0028592388,-0.0001653294,-0.0018739488,0.0020723874,0.021272598,0.012782886,0.022307929,-0.025759032,0.010139341,0.015737029,0.01285881,0.0075648176,-0.015626594,0.01214098,0.019878352,0.0060083703,-0.0042828186,0.0007230061,0.00463138,-0.009587164,-0.017573016,0.0050800233,-0.003485614,0.0047349134,0.017973345,0.015033005,-0.023495108,0.013721585,0.01758682,0.015115831,-0.0024727152,0.025055008,-0.00738536,-0.022418365,-0.022349343,0.00073206524,0.03622278,0.011105649,-0.011927011,-0.0016539411,-0.001200121,-0.008627757,-0.075206436,-0.013224627,0.009497435,0.02077564,-0.023771197,0.057095047,0.0058772285,0.020941293,-0.008441398,0.01620638,-0.017200297,-0.020223463,-0.015819855,-0.016882796,0.007050603,-0.0026901348,-0.010063416,-0.015157244,-0.002947242,0.032053843,-0.011195378,-0.0069505214,0.007930635,-0.021134553,-0.023867829,0.022597821,-0.03685778,-0.018028561,0.028064368,-0.013321257,0.01226522,-0.014177131,0.00094042555,-0.006025626,-0.030314488,0.012486091,-0.032053843,-0.02522066,0.023633152,-0.02512403,0.010843365,-0.0025555417,0.012030545,-0.014715503,0.020899879,-0.010815756,-0.029265353,0.019409003,-0.018456498,-0.013914847,-0.04928175,-0.023867829,-0.030839056,-0.0040377905,-0.001138864,-0.008020363,0.021507274,-0.010753637,-0.008862432,0.01617877,-0.00663302,0.014259958,0.00074888935,0.0009421511,-0.021548687,-0.017628234,-0.01771106,-0.009359391,0.016951818,-0.020195855,-0.013507617,0.0039549638,-0.04133041,0.0065398403,-0.025966099,-0.0034528284,-0.0097528165,-0.010449939,0.016137358,-0.014839742,0.004424314,-0.03163971,-0.0012216904,-0.009476729,0.00869678,0.035974298,-0.011153964,0.009304173,-0.00013998536,-0.027263714,0.01586127,0.0101117315,0.03232993,-0.0009067773,-0.0015245248,0.007861612,0.005359563,0.0017091588,-0.011692337,0.015391919,-0.012465384,-0.015184853,-0.08989433,0.011354129,-0.012879516,-0.011112551,0.0003487771,-0.011699239,0.001373539,-0.021314012,0.019257154,0.0046900488,-0.036774952,-0.00056382397,-0.006149865,-0.016151162,-0.038900834,0.008192918,0.01467409,0.0076959594,0.032274716,0.0034649074,-0.024696093,-0.001508132,-0.004493336,0.008406887,-0.020251073,0.020085419,-0.012354949,0.007309436,-0.011581901,-0.016910404,0.005166301,0.0051110834,0.0032647434,0.011340324,-0.024834137,-0.008551833,-0.002446832,0.02863035,0.026973821,0.009242054,0.0108640725,-0.024972182,-0.00378586,-0.021521078,-0.01699323,-0.015226266,0.012085763,-0.012361851,0.010422331,-0.008972867,0.019588461,0.00916613,0.004969588,-0.012002936,-0.0112436935,-0.030673403,0.0061636698,-0.006429405,-0.005659809,-0.0016988054,0.0073163384,-0.0024606364,0.007930635,-0.0115957055,0.013072778,0.00055001955,-0.028547524,0.017048448,-0.003319961,-0.0009421511,-0.032109063,-0.014591264,0.0076545463,-0.0016522155,0.008206722,-0.017200297,-0.007744275,0.01811139,-0.004596869,0.022321735,0.014467023,0.009835644,-0.022087058,0.027595019,0.01946422,0.015171048,-0.022238906,0.013072778,-0.007958244,0.006001468,-0.026463058,0.021093141,-0.0300384,0.0025572672,0.013866532,0.025855662,-0.0011397267,0.0068884017,0.021631513,0.04812218,0.009566457,-0.010001296,0.0067538084,-0.00041866192,-0.018359868,0.024916964,-0.01514344,-0.015433332,-0.020830857,0.011402444,0.016813774,0.0035322038,0.0012380832,0.0007100644,-0.022073254,0.0062188874,-0.024420004,-0.009987492,-0.03213667,0.022611627,-0.004258661,0.024916964,0.0020861917,-0.015875073,0.02459946,0.025082616,-0.0031836424,-0.036029514,0.0044415696,0.0018894789,-0.002700488,0.0053492095,0.030424923,-0.020609986,-0.010235972,-0.008054874,-0.016579099,-0.0021793714,0.0018480656,0.08012081,0.020458138,-0.005366465,0.0034079643,-0.01842889,0.0073922626,0.013700878,0.008731291,-0.0036340114,-0.025607184,0.04149606,0.001484837,0.0052525788,-0.024765115,-0.0056149443,-0.0079237325,-0.003930806,0.03520125,-0.012037447,0.02112075,-0.008579442,0.023301847,0.03197102,0.014950178,-0.043235417,-0.016758556,0.027733063,0.006432856,0.0034269453,-0.04953023,-0.0018549678,0.0010698419,-0.0040723016,-0.0053181495,0.007847808,-0.010242874,-0.02074803,-0.016938014,0.01736595,0.009877057,-0.0076476443,0.023495108,-0.030811448,-0.013335062,-0.013473106,-0.025607184,-0.009414609,-0.014149522,0.013997674] | K5: 2025-07-27T18:29:08.802Z
A6: 4 | B6: 299 | C6: computer_programmers_4 | D6: consultation,problem-solving,communication,technical knowledge,engineering understanding,program analysis | E6: Engineering | F6: consultation,program intent,problem identification,suggestions for improvement | G6: 1 | H6: manager,engineer,technical specialist | I6: 8 | J6: [0.010695338,0.00030129508,-0.0009621045,-0.033588666,0.013319878,0.020615553,-0.013857025,-0.0024409576,-0.009553052,-0.022709746,-0.0046303403,0.012653544,-0.00025030016,0.015407271,-0.020724343,-0.012062003,0.02640858,-0.0007598246,0.005167487,-0.008743932,-0.012918717,-0.002185983,0.01168124,0.0013258684,-0.010974111,0.0016675345,0.023076909,-0.025551863,-0.013965813,-0.008308775,0.003807622,-0.0022913725,0.007091696,-0.013353874,-0.012510758,0.0020499965,0.0003707757,-0.0061465898,0.024409577,0.0020465967,0.03372465,-0.009226684,-0.0067551294,-0.012864323,0.010389369,0.024763143,-0.00040625967,-0.02136348,-0.016141597,0.024219196,-0.0012332276,0.005476856,-0.016386373,0.011946414,-0.009417065,0.023797637,-0.03043378,0.021553861,-8.50978e-05,-0.0019905025,-0.0017967216,-0.002738428,-0.012401969,0.0037634263,-0.007941612,-0.011545254,-0.008424364,0.010389369,-6.055649e-05,0.012973112,0.010130994,0.0069387113,0.0012646745,-0.005769227,0.021431472,-0.010960512,-0.014387372,-0.007982408,-0.00091450923,0.008437962,-0.0014941517,-0.017610252,-0.009111095,0.010042603,0.0014346576,0.017583055,0.01661755,0.0012230286,-0.009893018,-0.01873894,-0.005765828,0.021989018,0.02105071,-0.010266981,0.011871622,-0.00044663067,0.0031463876,0.011477261,0.016141597,-0.021553861,0.002024499,0.00987942,-0.020316383,-0.0019769038,-0.041747857,-0.019146899,0.013714239,0.0007088296,0.016481563,-0.022002615,-0.012442765,0.046262607,0.0016760336,-0.0067007346,0.016263986,-0.024831135,0.007785227,-0.0070576994,-0.02296812,-0.013353874,0.03372465,-0.013075102,0.010042603,-0.03002582,0.01864375,0.008621545,-0.029998623,-0.0041135917,-0.02538868,-0.012673941,0.007384067,-0.012898319,0.003335069,0.023335284,-0.016658347,-0.01319069,-0.018575756,0.014441767,-0.022641752,-0.034295797,0.009607446,0.021798637,0.002991703,-0.005167487,0.0013853625,0.0049227113,0.027346885,-0.0022947723,0.005055298,0.012422367,0.003940209,-2.4129637e-05,-0.001228978,0.009797827,-0.0142921815,-0.0042597773,-0.007486057,0.020329982,-0.014496161,0.0060479995,0.0073296726,-0.021812234,0.02740128,0.006187386,0.0020143,0.01854856,0.0008018954,0.016359176,0.012735136,-0.010912917,-0.0023610657,0.039218508,-0.030760147,0.013211088,0.018670946,-0.0011958313,-0.011864822,-0.0004462057,0.0017372275,-0.009675439,0.0029373085,0.012864323,0.009859022,0.012347574,-0.0332351,0.0052728765,0.023620855,0.0148769235,0.0035186508,-0.012707938,0.035846043,0.022410575,-0.004643939,-0.008696336,-0.6509946,-0.034513373,-0.017365476,-0.00634717,-0.0019735042,0.010205787,0.011620047,-0.003688634,-0.007839622,0.020438772,0.013177092,0.018086204,-0.01117809,-0.0107089365,-0.0014822528,-0.008546752,-0.011708437,-0.024015216,0.030270595,-0.001118489,-0.016603952,-0.020724343,-0.007934812,-0.015053705,0.006132991,-0.019133301,0.0021570858,0.00080359523,-0.0042869747,0.020669948,-0.004915912,0.010872121,-0.0054530585,-0.02468155,0.058365405,0.027482871,0.0072956756,0.00997461,0.012123196,0.028393982,-0.017732639,0.0011728836,0.01933728,0.021771438,0.00614319,0.029400282,-0.003386064,0.0068741175,-0.022804936,-0.033153508,0.016631149,-0.012653544,-0.015271284,0.008308775,0.0292099,-0.023539264,0.027986022,-0.009233483,0.007574448,0.010525355,0.010137794,0.019160498,-0.034975726,-0.009389868,-0.01973164,0.0128099285,-0.010627345,-0.009131494,0.015148896,-0.0048411195,0.008648741,0.031358488,-0.014536957,0.015176093,-0.0046201413,0.0074996557,0.0051640873,-0.004178185,0.0053544682,0.021621853,0.012816728,-0.015162495,0.0037022324,-0.009825025,0.028366784,-0.00037630016,-0.027034117,-0.043379694,-0.00093150756,0.009090697,0.03165766,0.0018851128,-0.011416066,-0.014020208,0.011728835,0.025592659,-0.020996315,-0.0068775173,0.026979722,-0.011660842,-0.0072480803,0.005718232,0.01138207,-0.0023967621,0.016168796,0.0031378886,-0.030950528,-0.017963817,0.033153508,0.002349167,0.011354873,-0.0008805126,0.013340276,-0.013061503,0.010926516,-0.032990325,0.010314576,0.01682153,-0.016386373,-0.02387923,0.009757032,-0.00493971,0.01269434,-0.027877232,0.010770131,0.018902123,0.004290374,0.011354873,-0.010620546,-0.00012291905,-0.014700141,-0.024763143,-0.0017474266,-0.02247857,-0.010906117,-0.021621853,0.013979413,-0.0017899224,0.007078097,-0.0014788532,-0.0037634263,-0.008091196,0.01440097,0.004463757,-0.008125193,-0.035465278,-0.023403278,-0.00070415507,-0.020452369,0.0067449305,-0.008859521,-0.0032619762,0.0057998244,0.03998003,0.008879919,-0.027129307,0.00947146,-0.03739629,-0.022723345,-0.031032119,0.003034199,-0.0014159594,-0.05186525,-0.01057975,-0.0018341179,-0.010953712,-0.008580748,-0.0044977535,-0.027061313,-0.032391984,0.0036308395,0.010736134,0.0065103536,0.0006731332,-0.019214893,0.011334475,-0.013061503,-0.026884532,-0.0013207688,-0.011416066,-0.012673941,-0.00020089881,-0.0029067115,-0.004167986,0.011450063,-0.0030953928,0.004382165,0.012136796,0.0062111835,-0.009627844,-0.02801322,0.02880194,0.0030562966,-0.0065715476,-0.0072208834,0.03658037,-0.02065635,0.011008107,-0.016386373,0.032283194,0.029264295,-0.00016732713,0.024124006,0.0028965124,0.016998313,-0.01693032,-0.013952215,-0.006367568,0.038456984,0.013938616,0.0015366474,-0.006316573,-0.005769227,-0.0029033117,0.004946509,0.014727338,0.010416566,0.03184804,-0.028176403,-0.009124694,-0.006302974,-0.026123006,0.025415877,-0.013455864,0.009090697,0.03706992,0.030705752,0.013755035,0.008852721,0.0015969914,0.013047905,0.031684853,0.005731831,0.0130887,0.020234792,0.017691843,0.027020518,-0.02650377,0.04705133,0.023702446,-0.0028285193,0.027958825,0.016699143,-0.012170792,0.0221522,0.014822529,0.032881536,0.016236788,0.0073568695,0.03486694,-0.0056298412,-0.012238785,-0.016372774,-0.0027588261,0.013870623,0.013163493,0.02912831,0.030243399,0.041231107,0.026435776,0.0028438177,0.013313078,0.015665645,-0.009029504,-0.007717234,0.00574203,0.00021035412,-0.02640858,0.001148236,-0.01319069,0.026340585,-0.000534172,-0.0035084516,-0.023607256,0.018575756,0.022546561,-0.0015136998,0.024056012,-0.010348572,0.004575946,-0.0048717163,-0.011722037,0.018711742,0.02134988,0.007343271,-0.0048377197,-0.01189202,0.008594347,-0.02226099,0.008172789,-0.004524951,0.015652046,-0.012401969,0.037695456,0.0011966812,-0.0007989207,0.00082059356,-0.00614319,-0.0033078715,0.01400661,-0.0029084112,-0.002357666,-0.017079905,-0.024844734,0.045392293,-0.024028815,-0.0053714667,-0.03758667,-0.0006416863,-0.0068741175,-0.014618549,-0.011613247,0.0032857738,-0.016549557,-0.0017882225,-0.0332351,-0.029182702,-0.018371776,0.029454676,-0.008907116,0.0024562562,-0.025266292,0.0064491597,0.03144008,0.07212724,0.017691843,0.0047289305,0.004089794,0.010702138,-0.028475573,-0.037314694,-0.05246359,0.005245679,-0.016807932,0.010334974,0.0050247014,0.02095552,-0.020601954,0.0069965054,0.0068741175,0.0044195615,-0.011558852,-0.026136605,-0.017392673,0.013653045,-0.018575756,0.019799635,-0.0061465898,0.012252384,0.015380073,0.0071868864,0.035465278,-0.008539952,-0.036389988,-0.0075336522,0.02084673,0.002378064,-0.006010603,-0.024287188,0.043706063,0.024395978,0.015896821,0.0027044315,-0.020765139,0.0039334097,0.024912726,0.015842427,-0.018018212,0.012163992,-0.007622043,0.0074792574,0.023702446,-0.0016437368,-0.029046716,0.015992012,0.00057836756,-0.028557165,-0.006843521,0.009498657,0.005126691,-0.0024647554,-0.015488862,0.004320971,-0.014672943,-0.022709746,-0.037831444,0.005932411,-0.015393672,-0.007384067,-0.009383068,0.00684692,-0.0056128427,-0.012918717,0.028856335,-0.008471959,-0.009362671,-0.032799944,0.008859521,0.020261988,-0.003566246,0.013863823,-0.0065307515,-0.015543257,0.030841738,-0.030896133,-0.018983716,0.017487863,-0.021921024,-0.0010258482,-0.006880917,-0.042890143,-0.010103797,-0.044358797,-0.001058145,0.0090023065,-0.009838623,0.021703446,0.003715831,0.0017363776,0.016209591,0.00876433,-0.0007615244,0.016835129,-0.01975884,-0.02457276,-0.027673254,-0.038511377,-0.020914724,0.005065497,0.016671944,0.0063403705,0.008009605,0.0006671838,-0.0014117098,0.037749853,-0.022192998,0.023593659,-0.01036897,0.0151081,0.022995317,-0.0066837366,0.021431472,0.020588357,0.003848418,-0.016060006,-0.03233759,0.0342686,0.0107089365,-0.04925431,0.021213895,0.009886218,-0.021866629,-0.019214893,0.00066505896,-0.014346576,0.030841738,-0.018303784,-0.023947222,-0.016998313,-0.0059596086,-0.0051538884,0.00584062,-0.0015349477,-0.027550865,0.0061907857,0.005198084,-0.0015995412,-0.00624518,0.021785038,-0.023634454,-0.0029849038,0.011803628,-0.013979413,0.030488173,-0.0009791028,0.0015850926,-0.008716735,0.0021009916,0.008682738,-0.056787964,-0.014795331,-0.0043685664,0.019813234,0.024232794,-0.018018212,-0.01724309,0.017542258,-0.006908114,0.0015323979,0.0141018005,-0.028448377,0.010239784,-0.04169346,0.012837126,0.036226805,0.008431163,0.026870932,-0.024939924,-5.636003e-05,0.01521689,0.0021383876,-0.013047905,-0.009607446,-0.022206595,-0.01693032,-0.0017712242,0.0021536862,0.008213584,-0.017732639,0.035274897,0.043706063,0.016046407,0.019622851,0.016263986,0.016563157,0.0016785833,0.007241281,-0.010022205,0.017787034,0.009757032,-0.02801322,-0.04675216,-0.009043102,0.0124835605,0.0069965054,0.020397976,0.02397442,0.0032415781,-0.007934812,0.02507591,-0.0072276825,-0.0075880466,0.005884816,-0.0133266775,-0.016168796,7.367706e-05,-0.009185888,0.008723534,0.022696147,-0.0036512376,0.02084673,0.035574067,0.00052439794,-0.004106792,0.018779736,-0.0077920263,0.030977724,0.013979413,0.032827143,0.03666196,0.0140338065,0.0006880067,-0.008111595,0.013285881,0.0013420167,0.028122008,0.020669948,-0.0066837366,-0.016073605,0.013319878,0.0035118514,-0.015937617,-0.02659896,0.0001607403,-0.0020465967,0.013884222,-0.008213584,-0.001993902,-0.02247857,0.022587357,0.0040286,0.0002630489,-0.012565153,-0.0006569848,0.010810927,0.033371087,-0.0054428596,0.017895823,0.019187694,-0.011912418,0.006061598,-0.0221522,-0.016631149,0.044875544,0.01057295,0.014061004,-0.03402382,-1.0345067e-05,0.002376364,0.02064275,-0.007615244,-0.006357369,0.033126313,0.03244638,0.014686542,-0.012456363,-0.010130994,-0.017555857,0.014727338,-0.012565153,-0.0047289305,-0.015189692,-0.021213895,-0.020438772,0.017800633,0.023253692,-0.013938616,0.013211088,0.0035832443,-0.014074603,0.0130003095,-0.002731629,0.013061503,-0.021513065,-0.021499466,-0.005167487,-0.007010104,0.021404276,0.0094510615,0.0012068802,0.0007033052,0.026816538,-0.004161187,0.022492167,-0.017365476,0.008587548,-0.019078907,0.027523668,-0.012306779,-0.031113712,0.017719042,-0.026530966,0.0072888765,0.012837126,0.026544565,0.024531964,-0.023226494,-0.008587548,0.0025735446,-0.017379075,0.008043601,-0.026707748,-0.019255688,0.029155506,-0.020275587,-0.014387372,-0.006316573,-0.013041105,0.01622319,0.004473956,0.015937617,0.0047221314,-0.027850036,-0.0155160595,-0.0017168296,0.005306873,-0.017623851,-0.02901952,-0.012714738,-0.0056366404,0.00026347383,0.002609241,-0.00059961545,0.009104297,-0.0030104013,0.005429261,-0.008798326,0.035737254,-0.029645057,-0.011905618,-0.0261774,-0.057658277,-0.023988018,0.0060785967,-0.015475264,0.02054756,-0.0052932748,-0.017107101,-0.007506455,-0.017977415,-0.07838262,-0.026000619,-0.00574203,0.0050315005,0.009899817,0.02356646,-0.0064423606,0.031358488,-0.009036303,0.009804627,-0.01974524,-0.021322682,0.0053544682,-0.008131993,0.019119702,0.005782826,-0.002699332,0.0022097807,0.023607256,0.00054437097,-0.005174286,0.010960512,-0.0034778547,-0.028285192,0.0069761076,-0.012721538,0.01128688,0.0016037908,0.0015986913,-0.016699143,-0.006595345,-0.002760526,-0.016345577,-0.02367525,-0.00856035,-0.003454057,0.008682738,-0.0015332478,-0.013673442,0.015624849,0.010436964,-0.01721589,0.0041985833,-0.0074044648,-0.021499466,0.019786036,0.027265294,0.0052014836,-0.014387372,-0.001017349,-0.003998003,-0.014917719,0.0120348055,-0.014713739,-0.0118104275,-0.007214084,0.011341274,-0.030950528,-0.0031174906,0.005167487,0.014496161,-0.035302095,-0.0010734434,0.021227492,-0.007084897,-0.0046779355,0.007982408,-0.016875925,0.0030545967,-0.021907425,0.006302974,-0.035601266,-0.0045011532,0.019038111,-0.009117895,0.010865321,0.004045598,0.040061623,-0.017311081,0.020493167,0.1843977,-0.0056196423,0.0010215986,0.023076909,0.0029339087,0.0050383,0.026789341,0.017256686,0.0070509003,0.012469962,0.009192687,0.0033775647,-0.025361482,-0.0029628058,0.009029504,-0.013442266,-0.032473575,-0.04422281,-0.046806555,0.03448618,0.026789341,-0.0070373015,-0.008737133,-0.026639756,0.022097806,0.011042104,-0.02397442,0.0043175714,0.047894444,-0.01239517,-0.020574758,-0.021377077,0.012884721,0.013149895,0.012116397,-0.004875116,0.0048479186,0.00046872848,-0.00068248226,-0.005772627,-0.0023253693,-0.00041645867,0.011354873,-0.028557165,0.017596653,0.026734946,-0.008199986,-0.01823579,0.0021111905,0.022981718,-0.019595655,-0.00048572678,0.03998003,0.028747546,0.00013789881,0.015080903,0.0038314196,0.013666644,-0.0035730454,-0.01178323,-0.020411573,0.0125175575,0.0007143541,-0.003535649,0.0039742053,0.010858522,0.018874926,0.0064049643,-0.0067619286,-0.0045079524,0.0070576994,-0.029373083,-0.012361173,0.016481563,-0.03905532,-0.035546873,0.021485867,0.012524357,0.009464661,0.022383379,-0.010566151,0.0039572073,-0.020601954,-0.011817227,-0.010872121,-0.0073976656,0.023688849,0.00856715,0.011742434,-0.0032704754,-0.0036614365,-0.025320686,-0.01752866,-0.00966864,0.013918218,0.03663476,0.004293774,0.0014091601,-0.021825833,-0.0046779355,-0.013836627,0.05548249,0.0053136726,0.01580163,-0.015883224,0.0031191905,-0.0076492405,0.0059698075,-0.01198721,0.012503958,-0.00916549,-0.017569456,0.02126829,-0.0017440269,0.004201983,0.012354374,0.008893517,-0.03396943,0.014047406,-0.013816228,0.01985403,-0.022587357,-0.0012578751,0.023321684,-0.020697145,-0.012340775,-0.0048445193,0.013319878,-0.008737133,-0.0142921815,0.025878232,-0.026449375,-0.002527649,-0.0010844923,-0.0033231701,-0.02759166,0.0015553456,0.013687042,-0.020778738,0.011307278,0.021921024,0.00029385832,-0.015040107,0.037450682,0.010409767,-0.000957005,0.0053918646,0.0019514062,-0.030596962,0.008635143,-0.007574448,-0.010627345,0.02901952,-0.020901125,0.036036424,-0.0011813827,-0.014496161,-0.026476571,-0.008431163,0.014088201,-0.024803938,0.0035016525,0.037913036,-0.010232984,-0.004715332,-0.012544755,-0.1742803,-0.00056901854,0.018575756,-0.01833098,0.033479877,0.02568785,0.0061295917,0.005157288,0.006962509,-0.015842427,0.006676937,-0.003212681,-0.036199607,-0.020438772,0.0137414355,-0.0068843164,-0.013727837,-0.016508762,0.021798637,0.02094192,0.01873894,-0.0090023065,0.00095360534,0.0023610657,0.003142988,0.032283194,-0.019826831,-0.01098091,-0.0070576994,-0.02106431,-0.0046303403,0.009512256,0.015040107,-0.008533153,0.001571494,-0.015584053,-0.011858023,0.008981909,-0.017746238,0.018970117,0.014904121,0.026870932,0.028937927,0.0037702257,-0.021200296,0.0074792574,0.024545563,-0.01622319,0.010974111,-0.016331978,0.006299575,-0.024341583,-0.0077104345,-0.003182084,0.009219885,0.009621045,0.004691534,0.0042257807,-0.0024341585,-0.005245679,0.0025055513,-0.0221658,0.006126192,0.0064117634,-0.027210899,-0.019269288,-0.01128008,0.019514063,-0.0105865495,0.0036920335,0.007982408,-0.00433457,-0.008118394,-0.03606362,0.007200485,-0.0029288093,-0.010300977,-0.005949409,0.0069829067,-0.021309085,0.0062893755,0.0010241483,0.0034659558,-0.00074920064,-0.0141018005,0.00054139626,0.013449065,-0.021472268,0.015638448,-0.00624518,0.042373393,-0.037913036,-0.016739938,-0.020778738,0.017460667,0.0061533893,-0.00845836,-0.012191189,-0.0074724583,0.008648741,0.02106431,-0.008084398,-0.01269434,0.008988707,-0.0067041344,0.020887526,-0.0038620166,0.014183392,0.03195683,0.0028863135,-0.011715237,0.005361268,-0.0033452678,0.033371087,-0.007506455,0.03415981,-0.00011526981,-0.0061703874,0.0045997435,0.010606947,0.029998623,0.0003807622,0.00043494432,-0.0004844519,0.007669639,-0.018086204,-0.10873481,-0.032555167,0.0090023065,0.031793643,0.009831824,0.027564464,0.0070169033,-0.0069251126,-0.03679795,0.054666575,-0.010008606,-0.022655351,-0.0110013075,-0.018154198,0.011864822,-0.0151081,-0.021445071,-0.00034612813,-0.019908424,0.030732948,0.016739938,-0.0038314196,-0.0060921954,0.005752229,-0.016182393,0.01782783,-0.025347883,-0.0026534365,0.035982028,-0.010606947,0.008308775,-0.020805934,-0.0075336522,-0.008607945,-0.010933314,0.00028790892,-0.018276585,-0.024409577,0.030053016,0.012782731,0.007683237,-0.005527851,-0.0018528161,-0.028285192,0.0078124246,-0.018099803,-0.028094811,0.02801322,-0.010532155,-0.014169794,-0.029509071,-0.0074792574,-0.029427478,-0.0054870555,0.028693153,0.015244086,-0.013761834,-0.003042698,-0.026830137,-0.005589045,-0.010171791,-0.0074180635,-0.008553551,0.023824835,0.008111595,0.013965813,-0.018167796,-0.023852032,0.0045283507,-0.036389988,-0.006829922,0.009961011,-0.0251983,0.0066905357,-0.037233103,0.006789126,0.00322288,-0.0107769305,0.025443075,0.009689039,-0.0012519257,-0.036933932,0.011762832,0.0003656762,-0.0031395883,0.018262988,0.013517058,-0.031358488,0.01531208,-0.013149895,0.019595655,0.008601146,0.018806932,-0.008859521,0.0043073725,-0.018766137,-0.003505052,-0.0045487485,-0.010899318,0.02880194,-0.0148089295,0.01027378,-0.059181325,0.009097497,-0.006377767,0.0013658145,0.012585551,0.023648053,0.0148089295,-0.021472268,0.021866629,0.008818724,-0.037042722,0.010083399,-0.013952215,-0.008573949,-0.015488862,0.017188694,0.007737632,0.009757032,0.023022514,-0.008349571,-0.0372603,-0.0040863943,0.0029594062,0.018793335,-0.0006535851,0.020506764,-0.00046490386,-0.008805126,-0.013857025,0.00024307588,0.015842427,0.016168796,0.013251885,0.020588357,-0.013347075,-0.012911919,0.03445898,0.031576067,0.0034880538,0.043651666,-0.016440768,-0.0138094295,0.015692841,-0.014088201,-0.0135850515,-0.0053952644,-0.031032119,0.004762927,0.00342516,-0.010858522,1.7927909e-05,0.001985403,-0.021594657,-0.012021206,-0.00927428,-0.031249698,0.0016369375,0.01047096,-0.0034659558,-0.0047969236,0.017107101,-0.014863324,0.014468963,-0.010851723,0.014917719,0.0008346171,0.005609443,0.023512065,0.0075268527,-0.01592402,-0.027469274,-0.019677246,0.0077648293,0.032364786,0.004603143,-0.024518367,0.0029577063,0.030379385,-0.018480565,0.027360484,0.00917229,0.0110013075,-0.0008703136,0.0057862257,0.020207593,0.005599244,-0.006285976,0.009641442,0.010532155,0.009281078,-0.016195992,0.012299979,-0.014142596,0.017787034,-0.0055176523,0.027170103,0.010464162,-0.0005044249,0.015556856,0.002296472,-0.0005889915,-0.009675439,0.01168124,-0.0015043507,-0.05327951,-0.011307278,-0.03244638,-0.019323682,-0.03062416,0.004827521,0.0043141716,0.0051538884,0.021336282,-0.0028064214,-0.017596653,0.00046575378,-0.006024202,-0.024001617,-0.036090817,-0.009036303,-0.0033367688,0.012578751,0.026218198,-0.0045385496,0.012463163,0.01682153,0.013714239,-0.034513373,-0.016563157,-0.019106103,-0.013965813,-0.0067483303,0.002548047,-0.0110693015,-0.011728835,-0.0068129236,-0.010647743,-0.0137754325,-0.0031582864,0.053741865,0.0023967621,0.0070509003,0.008199986,-0.0151081,0.019106103,0.006238381,0.030977724,0.014210589,-0.04691534,0.01582883,-0.01833098,0.0035900436,-0.014196991,-0.0068129236,0.006819723,-0.007316074,0.02991703,-0.0014814029,0.0028778142,0.015257685,0.0075404514,0.008254381,0.010402967,-0.046317004,-0.018602954,0.014917719,0.02246497,1.349241e-05,-0.041666266,-0.029536268,0.02084673,-0.024463972,-0.01631838,0.0042529777,-0.040360793,-0.021540262,-0.002860816,0.01592402,0.005901814,0.014061004,0.020792335,-0.026762143,-0.039436087,-0.046996936,0.00815919,-0.011021706,0.005714833,-0.009750232] | K6: 2025-07-27T18:29:20.588Z
A7: 5 | B7: 300 | C7: computer_programmers_5 | D7: Program Testing,Software Application Testing,Debugging,Quality Assurance,Attention to Detail | E7: Software Development | F7: Testing,Quality Assurance,Software Applications,Trial Runs | G7: 2 | H7: Software Tester,Quality Assurance Specialist | I7: 16 | J7: [-0.007341734,-0.006608237,0.016792696,-0.023228545,0.008261141,0.036749233,-0.0019469792,0.0055029206,-0.0018421939,-0.010999081,0.010363609,0.010613741,0.0035559412,-0.00549278,-0.014480658,-0.030259302,0.022552509,-0.011648074,0.0027514603,-0.021308606,-0.021105796,0.02040272,-0.018983047,0.0044212653,0.00022710532,0.010113476,-0.008511274,-0.046375964,-0.0042691575,-0.0034849576,0.011100486,-0.011438503,0.0029390599,-0.020024141,-0.006297261,-0.0018286732,-0.015386544,0.017495772,-0.00026978,-0.011810322,0.01667101,0.04353662,-0.0115872305,0.012858176,0.011857645,0.023444876,-0.007943405,-0.0069293533,-0.014020955,0.02410739,-0.012567481,-0.011702157,-0.014494179,0.0017205077,0.034018055,0.013351681,0.009917426,0.00014312917,-0.008274661,-0.007787917,-0.02763629,0.007023998,-0.025405375,-0.0018692353,-0.003160461,-0.004884349,-0.00048167456,0.026419427,0.019321065,-0.018996568,0.020172868,0.015967933,0.014075037,0.0060741697,0.026541114,-0.022133369,-0.012662126,0.0032027133,0.012959581,0.0054454575,0.0036843878,-0.004100149,-0.034829296,-0.0012143269,-0.013290837,0.0029289194,-0.009944467,0.008409869,0.009092663,-0.0036843878,-0.015143172,0.0021903517,0.011600751,0.026000286,-0.006706262,0.0058409376,-0.007923124,0.04199526,-0.024594134,-0.017725624,0.005824037,0.017022548,-0.009106184,-0.006256699,-0.0035593214,0.00032618662,-0.00021654229,-0.009552367,0.008166497,-0.02333671,-0.019158816,0.021078754,0.022092806,-0.02333671,0.013466607,0.010268964,0.021606062,-0.00024548502,-0.010316286,-0.0290154,0.008950696,0.012310588,0.025513541,-0.011763,0.015535272,0.033017524,-0.01371674,-0.019334586,0.0036742473,-0.00071068126,0.011857645,0.0016748754,0.022809403,0.0090183,-0.01884784,-0.0071051223,-0.02194408,0.031692497,-0.02336375,-0.027203627,0.00922787,0.02804191,-0.005438697,-0.0074228584,0.014913321,0.015670478,0.010147277,0.01726592,0.01412912,-0.005002655,-0.0019486693,-0.007943405,0.0036167845,-0.0012717898,-0.010539377,0.0038871982,-0.008267902,-0.008693803,-0.022822924,-0.027230669,-0.000106158535,0.023972182,-0.0034477757,-0.003043845,0.0047795638,0.030962378,0.02944806,0.0011306676,0.00048378715,-0.012540439,-0.0056246067,0.014669948,-0.038750295,0.015913852,0.007159205,-0.0041508516,0.010437972,-0.0063445834,0.0014965712,-0.0017914913,0.005320391,-0.023106858,0.035207875,0.024688778,-0.024229076,0.014061517,0.0070713204,0.009396879,0.00040625446,-0.03180066,0.019361626,-0.0060268473,-0.011330337,-0.021889996,-0.65634835,-0.01786083,-0.010938237,-0.018009558,0.01314887,0.029502144,0.03593799,0.012121298,-0.016170744,0.009937706,0.0152648585,0.036884442,-0.013189432,-0.026432948,-0.015291899,-0.011539908,-0.0025216085,-0.037290063,0.013466607,0.019510355,-0.033666518,0.021565499,0.0005420951,0.00022161254,0.0036810075,-0.0011754549,7.3624375e-05,-0.017090151,0.021795351,0.025919162,-0.010566419,0.012614803,0.009058862,0.016224828,0.05786855,-0.0034545362,0.006736683,-0.003197643,0.024621176,0.030881254,-0.014805155,-0.0068718903,0.03161137,0.02609493,0.009964748,0.0033007383,0.01884784,-0.007997488,-0.022444345,-0.009045341,0.0070713204,-0.009707855,-0.00883577,0.024769902,0.014358972,0.0047626626,0.0052257464,-0.017955475,0.008409869,-0.0028934274,-0.010715147,0.035965033,0.0011881306,-0.021322127,-0.022200972,0.017806748,0.0149403615,0.00943068,-0.0017779706,-0.0015650198,-0.00018358561,-0.009957988,-0.006141773,-0.011485825,0.0044821086,0.037966095,0.026825048,-0.005857839,-0.0012126368,0.004218455,0.019767247,-0.017414648,0.015440627,-0.012013133,0.017766185,-0.0129257785,-0.010052633,-0.023647685,0.001823603,0.0023086576,0.016603407,0.014480658,-0.009572648,-0.006729923,-0.00036611492,0.023674726,-0.01431841,-0.0029931425,0.025445936,-0.003978463,0.0045361915,0.0135882925,0.0018168426,-0.0027768116,0.011397941,0.017333524,-0.0015286829,-0.0021497896,0.032936398,0.011553429,-0.0034596063,-0.012871697,-0.023809934,-0.022836445,0.011472305,-0.02925877,-0.015237817,0.0053677135,0.0056753093,-0.029042441,0.00036442484,-0.004759283,0.021660144,-0.0049384315,-0.009200829,0.02294461,0.0050060353,0.006135013,-0.0065406333,-0.0058206567,-0.010262203,-0.003390313,-0.01136414,-0.002432034,-0.013993913,-0.006449369,0.006713022,-0.0125877615,0.011918488,-0.028907234,-0.013831665,-0.008355786,-0.003292288,0.025513541,-0.01353421,-0.017320003,-0.04534839,-0.01060022,0.003802694,-0.0063276826,0.008707324,0.028177116,-0.0074025774,0.029556226,-0.009836301,-0.014196724,-0.024837507,-0.0152648585,-0.008484232,-0.051946487,0.018563906,-0.0006823723,-0.024229076,-0.023228545,0.0035289,0.00034372127,-0.024229076,0.03507267,-0.03880438,-0.026568154,-0.0044449265,0.009755177,-0.009849822,0.0148998,-0.012121298,0.026852088,-0.011046403,0.004495629,0.014345451,-0.016157223,0.0077000326,0.019037131,-0.02375585,-0.0010225021,0.024540052,0.0017965615,-0.007963686,0.027325314,0.006439228,0.0020281035,-0.016779175,0.003968322,-0.002411753,0.007983967,-0.0022866866,0.027257709,-0.025026796,0.005861219,-0.007821719,0.034991544,0.0282312,-0.016900862,0.018523345,-0.014967403,0.017414648,-0.008998019,0.02609493,-0.019145297,0.02294461,-0.009288713,0.0039852234,-0.012324108,-0.009951227,-0.009058862,0.017428169,0.00863296,-0.022484906,0.02414795,-0.013791103,0.0069496343,0.016589886,-0.0094104,0.0048099854,-0.03572166,0.01723888,0.019983578,0.013750541,0.03769568,0.007956926,-0.016535804,-0.0134192845,-0.005671929,0.010661064,0.01136414,0.031476166,0.008565357,0.011918488,-0.031313915,0.024080347,0.011992851,0.007571586,-0.0062871203,0.010640782,0.000657866,0.009004779,0.012013133,0.030124096,0.003667487,-0.012378191,-0.0013072817,-0.0094036395,0.009592929,-0.01197257,-0.012641844,0.013392243,0.022200972,0.018645031,-0.0012979861,0.04080544,0.03255782,0.021808872,0.023039255,-0.0068786507,0.0014348831,0.0013461537,-0.014453617,0.02353952,-0.017387606,0.016711572,-0.012932539,0.018090682,0.0049147704,-0.006337823,0.015454148,-0.0046984395,0.012777051,-0.010458253,0.020619052,0.012506638,-0.0085585965,-0.0005691365,-0.021065233,0.018793758,0.011844124,0.012662126,0.0044888686,0.014818676,-0.0073484946,-0.018807279,0.009964748,-0.009768698,-0.002704138,-0.0034190442,0.0005927977,0.003001593,0.010782749,0.015467669,0.005759814,-0.012378191,-0.010410931,-0.009674053,0.0016892412,-0.009647012,-0.020835383,0.027217148,0.014791634,-0.027014337,-0.037181895,0.0014779803,-0.0034410155,0.011269495,8.101851e-05,-0.015792165,0.004553092,0.017347043,-0.0149403615,-0.012709448,-0.012540439,0.02628422,0.0282312,-0.019983578,-0.03593799,0.009870104,0.013655896,0.09080495,0.01354097,-0.007727074,0.016414117,-0.008227339,-0.008308464,-0.02648703,-0.017495772,0.02490511,-0.012499877,-0.011999612,0.013439565,-0.0007833549,-0.006922593,0.0015464289,0.016833259,0.023647685,-0.008943936,-0.006767105,0.007956926,0.009315755,-0.013040705,0.013655896,-0.004691679,0.034207344,0.0037891732,0.026446467,0.023850495,0.013054226,-0.010444732,-0.0052257464,0.030881254,-0.009883624,0.019145297,-0.01549471,0.05062146,-0.010803031,0.017184796,0.0135882925,-0.010316286,0.0045395712,-0.00431986,0.009126465,-0.0141156,0.029529186,0.00020460605,-0.005861219,0.021862954,-0.026716882,-0.022146888,0.020186389,0.0061823353,-0.0016106521,-0.0023982322,0.009146746,-0.00018960654,-0.012851415,0.007571586,-0.0060099466,-0.06360132,-0.02806895,-0.005043217,-0.0010022211,-0.02375585,-0.013392243,0.0020061322,-0.00047575924,-0.014886279,-0.026365343,0.013601813,0.008538315,-0.032828234,-0.003001593,-0.00922787,0.009930946,-0.002763291,0.0006612462,0.005726012,-0.0067535844,0.008964217,-0.009200829,-0.047024958,-0.0010740497,-0.031043502,-0.01039065,0.031016462,0.0049080104,-0.0105731785,-0.014440096,0.0021937317,-0.012594522,0.009667293,0.0054488378,-0.017414648,-0.012398472,0.0020450042,-0.0047761835,0.0003942126,0.010965279,-0.00018337434,-0.012425513,-0.042482007,-0.009971509,-0.021646623,0.012276785,0.009146746,-0.008457191,0.00036970634,-0.0033784823,-0.016238349,0.014953882,-0.02863682,-0.0022258435,0.0077405944,-0.0038871982,0.017009027,0.0074431393,0.016157223,0.023891058,-0.0033413004,0.0034849576,-0.037154853,0.04870152,0.021714227,0.00033527083,0.014061517,-0.004373943,-0.021889996,0.008747886,0.0049620927,-0.012635084,0.024783423,-0.022011682,-0.011654834,-0.0028596257,-0.033233855,0.0001015108,0.026243659,-0.0008632115,-0.0077743963,-0.009829541,0.019632041,0.020375678,0.021538459,0.044185612,-0.02375585,0.0022241534,-0.0046443567,-0.023688247,0.031746577,-0.010039112,-0.0027565304,-0.042995792,-0.00081757916,-0.002531749,-0.031854745,-0.006702882,-0.0184287,0.017698582,0.01706311,-0.000981095,0.0001588681,0.004397604,0.011607512,-0.0014374183,0.027392916,-0.019699644,-0.0031621512,0.0017509293,-0.004022405,0.0043840837,-0.016562844,0.014953882,-0.03412622,0.0017289581,0.010579939,-0.00921435,-0.014196724,-0.00058012205,-0.013040705,-0.017144235,0.0076459497,-0.014142641,0.0036438257,-0.0297996,0.02098411,0.024742862,0.022674195,-0.0059389626,0.043455496,0.012864936,-0.002628084,-0.015562314,0.03474817,0.03180066,-0.020105265,-0.015021486,-0.04805253,0.013088027,0.012959581,0.013527449,0.012831134,0.010336567,0.0016655799,-0.0227418,0.026554633,-0.008950696,-0.023215024,0.014169683,0.0015092469,-0.02312038,-0.0058105164,0.0027801918,0.010167559,0.009281953,-0.00059744547,-0.005766574,-0.0012844654,-0.012689167,-0.014156162,0.008761407,-0.0037519913,0.036019117,0.018185327,0.012641844,0.047565784,0.016360033,-0.025405375,-0.020456802,0.00607755,0.00038533963,0.033071607,0.019158816,-0.0037790327,-0.014751072,0.02233618,-0.0026162534,-0.014886279,-0.014426575,0.002670336,-0.0018895164,-0.0063040215,-0.01471051,0.0061248722,-0.03001593,0.023593603,-0.004867448,0.007916364,-0.02218745,-0.017766185,0.00061730394,-0.0016706502,-0.039561536,0.014304889,0.030556757,-0.00010177487,0.013709979,-0.0030860973,-0.014088558,-0.0024759762,-0.0031537008,0.009728136,-0.017387606,-0.003255106,0.0002016484,0.016143704,0.0026297742,-0.0152783785,0.019172337,0.032665987,-0.017211838,-0.028177116,-0.015846249,0.005472499,-0.003647206,0.025189044,-0.009890384,-0.03531604,-0.010113476,-0.022106327,-0.0034612964,0.02276884,0.018104203,0.0019317685,0.013628854,-0.0022393642,0.0019503594,-0.011492586,0.009586168,-0.027771495,-0.014196724,0.011255974,0.0008606764,0.0056617884,0.018212369,0.0056753093,-0.019794289,0.012324108,-0.035586454,0.013858707,-0.0009134916,-0.025581144,-0.0125877615,0.0139263095,-0.019294024,-0.024174992,0.017401127,-0.031908825,-0.011350619,-0.027568685,0.0012430584,0.022660675,-0.0076662307,-0.021105796,-0.0034173543,-0.0019892314,0.008490993,0.0013224924,-0.029204689,0.01787435,-0.008490993,-0.007531024,0.015156693,0.00055477076,0.012966341,0.00215486,0.003040465,0.019672602,-0.03455888,-0.009910665,-0.007902843,0.028339365,-0.0056989705,-0.018009558,0.005847698,-0.0018269832,-0.0035525612,0.017130714,-0.015589355,-0.0137573015,-0.017914914,0.0072673704,-0.0010368678,0.027555164,-0.004968853,0.021213962,-0.02410739,-0.0054623582,-0.02942102,-0.0036066438,-0.02375585,0.01884784,0.027960785,-0.013669417,-0.015440627,-0.018307013,-0.04507798,-0.006118112,-0.006354724,-0.005222366,0.020375678,0.02120044,-0.007537784,0.014521221,0.001412912,-0.0049113906,-0.030746046,-0.019239942,0.013622095,-0.004553092,0.009281953,-0.007294412,-0.010681344,-0.015156693,-0.009951227,-0.0043908437,0.0024540052,0.003219614,-0.014061517,-0.027325314,0.004532811,0.01841518,-0.00081715663,0.00045252056,-0.006983436,-0.011668355,0.0034883379,0.002235984,-0.0058003757,-0.016454678,0.0011112316,0.017941955,-0.020132307,0.005080399,-0.041887097,0.0022241534,0.0017999418,-0.005218986,-0.00235429,0.009261672,-0.031422082,0.023066295,-0.009985029,-0.013709979,-0.006702882,-0.010458253,-0.020564968,-0.013365202,0.005120961,-0.006334443,-0.014034475,-0.027771495,-0.0074431393,0.00803805,0.0027514603,-0.021105796,-0.018401658,-0.024080347,-0.0014644597,0.0069699152,0.009167028,-0.007943405,-0.025189044,-0.020754257,0.007916364,-0.01805012,-0.0024421746,-0.015913852,0.01590033,0.002237674,-0.0109111965,0.01353421,-0.010370369,0.041481476,0.0015202325,0.013797863,0.20356749,-0.0038398758,0.0071254033,0.039507452,0.003238205,0.03217924,0.024972713,-0.0022799263,0.010870635,0.018983047,0.022606593,-0.009194069,-0.027987827,-0.0060741697,0.00046730883,-0.004002124,-0.029880723,-0.02336375,-0.013872227,0.004407745,0.03039451,-0.0052291267,-0.009511805,-0.009241391,0.033396102,0.024391323,-0.00980926,0.021687185,0.044104487,0.012783811,-0.027014337,-0.00941716,0.011330337,0.017793227,0.014629385,0.0055570034,0.016022017,-0.0047559026,0.009870104,-0.010451493,0.0031503206,0.008889853,0.016576365,-0.04237384,-0.005813896,0.033666518,0.00084293046,-0.010667824,0.0045666127,0.0030269444,-0.01687382,0.0027362495,0.027879661,0.01980781,-0.0019909216,-0.0005991355,0.002533439,-0.008754646,0.0026365344,0.024202034,0.0006908227,0.010539377,-0.0399942,0.017955475,-0.030042972,0.009106184,-0.0032179242,0.049512763,0.00529673,-0.018996568,-0.01608962,-0.009890384,-0.0023390793,-0.010181079,-0.02531073,-0.03474817,0.01703607,0.03942633,0.032828234,0.025743393,0.008781687,-0.0033767922,-0.008457191,-0.016224828,-0.02138973,-0.01314211,0.0122497445,-0.011837363,-0.006408807,-0.0041677523,-0.011026122,-0.0071051223,-0.008031289,-0.014886279,-0.0015650198,0.01235791,-7.7585515e-05,0.005060118,0.0067400634,-0.0032060933,-0.0077338344,0.02961031,0.002670336,0.019294024,-0.006983436,0.011492586,-0.00027928673,0.026067888,0.0029593408,0.0057767145,-0.001431503,-0.017009027,0.010478534,-0.02019991,-7.7968425e-06,0.012939299,-0.007531024,-0.048863772,0.004144091,0.015792165,0.01763098,-0.0068752705,0.0027294892,0.02435076,-0.0013774203,-0.01922642,-0.013642375,-0.0068617496,0.010965279,-0.012276785,-0.014642906,-0.028799068,-0.000598713,-0.011661595,0.012107777,-0.0053609535,0.00903182,-0.001354604,-0.024431886,0.024661737,0.0250944,-0.0032179242,0.0017762806,-0.014020955,-0.008998019,-0.008470712,0.004238736,0.008139455,-0.017117193,-0.0064628893,-0.012905498,-0.01629243,-0.012520159,0.0031655314,0.0141156,-0.0028934274,-0.03039451,-0.011431742,0.026054367,-0.011512867,-0.03296344,0.0035660819,0.05121637,0.021714227,-0.004651117,-8.2127626e-05,-0.1740383,-0.0004529431,0.0018303633,-0.0063479636,0.012777051,-0.019577958,0.00589164,0.0069563948,-0.027825579,0.0041947938,0.013459846,-0.040751357,-0.030908296,0.00054420775,0.03750639,0.013371962,-0.03269303,0.019266982,0.028717944,0.013885748,-0.01863151,0.004411125,0.0016723402,0.006750204,0.034450717,0.0047390014,-0.02375585,0.008200298,0.01137766,-0.014859238,0.0026196335,0.011702157,0.018009558,0.013081267,0.016522283,-0.008842531,-0.009795739,-0.012101017,-0.01197257,0.006648799,0.0082340995,0.025432417,0.0041170497,-0.007571586,0.009775458,0.02844753,0.044645317,-0.029150605,0.028934276,-0.0018354335,0.027933745,-0.035640538,0.0055975653,-0.031340957,0.017968995,0.0059964256,-0.0066995015,0.013480127,-0.015143172,-0.007510743,-0.010106715,-0.031476166,0.018983047,0.006814427,-0.01627891,-0.032206282,-0.029475102,0.019064171,-0.022160409,0.00024083728,-0.0028139935,-0.02925877,0.0063919057,0.00011513712,0.011330337,-0.008700564,-0.017901393,0.016549323,-0.005614466,-0.00073561,0.0013554491,0.009903905,0.021849433,0.005550243,-0.013547731,0.0035627016,-0.015656957,0.01823941,-0.008626199,-0.01158047,0.047187205,-0.029826641,-0.00035872078,0.0038195946,0.033260897,0.018590948,-0.010735427,-0.008362547,-0.008700564,-0.011688636,-0.008098893,0.0014095318,-0.021443814,-0.00017999418,0.0139263095,0.02942102,-0.0018979667,0.022904048,0.02412091,0.006064029,-0.02589212,0.02314742,0.010715147,0.017157754,0.014467138,0.030637883,0.013743781,-0.0117427185,-0.0065000714,-0.012864936,0.05592157,0.003572842,-0.004495629,0.019483313,0.0108976755,-0.017144235,-0.07712201,-0.022633635,0.015170214,0.02882611,-0.023891058,0.027311793,0.00029280744,0.038669173,-0.0020281035,0.018766716,0.004529431,-0.025621707,-0.021538459,-0.03161137,-0.022228014,0.02763629,-0.0013469986,-0.0028106133,0.0020365538,0.011857645,-0.023864016,-0.015765123,-0.0055806646,-0.009586168,-0.026378864,0.020646092,-0.01649524,-0.011539908,0.0021142978,0.009545607,-0.009849822,-0.015805686,0.008180017,-0.015535272,0.0002482314,0.016170744,-0.03742527,-0.035694618,0.04805253,-0.012885217,0.00045759082,-0.0021261284,0.022025203,-0.016508762,0.0013461537,-0.008998019,-0.004684919,0.030827172,-0.0019520496,-0.028988358,-0.04824182,-0.0036370654,-0.033693556,-0.023999223,0.0006037833,-0.019740207,0.017428169,-0.026906172,-0.015359503,-0.007118643,-0.0002537242,0.022985172,0.0077203135,0.0020297936,-0.003589743,-0.008146215,-0.015778644,-0.020902986,0.011323577,-0.026392385,-0.007828479,-0.002631464,-0.018496303,0.008538315,-0.03783089,0.00920759,-0.019334586,-0.0112221725,0.0075580655,-0.008180017,-0.020308075,-0.010471774,-0.005604326,-0.018158285,-0.0028139935,0.011715678,-0.017401127,-0.019699644,-0.01158047,-0.02336375,0.015116131,0.029150605,0.007118643,-0.01822589,0.0035998835,-0.014480658,0.016441159,-0.022904048,-0.002198802,0.013480127,-0.018171806,-0.029285813,-0.08966921,0.006057269,0.010052633,6.776189e-05,0.001489811,0.018577427,0.02590564,-0.019605,-0.010282484,-0.008105653,-0.023742331,0.00026661108,-0.0039480412,-0.015684,-0.025270168,-0.005749673,0.01961852,0.0130947875,0.015859768,0.010120236,-0.006726543,-0.019091213,-0.0029086382,0.0014746002,0.0011332028,0.011215412,-0.008092132,-0.019956537,-0.021714227,-0.012101017,0.020308075,0.010410931,-0.0055401023,0.015940893,-0.032341488,-0.005066878,-0.00013129857,0.023999223,0.013060986,0.015251338,-0.0025841417,-0.02316094,0.015129651,-0.01984837,-0.014453617,-0.0105731785,-0.017225359,0.011904967,0.018509824,-0.015656957,0.008017769,0.010978799,0.005807136,-0.0078690415,-0.022795882,-0.047538742,-0.015373023,0.0073282137,0.0031114486,-0.0038973386,0.042211592,0.0074634203,0.016630448,-0.011898207,0.014642906,0.0075783464,0.01039065,0.0115872305,0.010782749,0.0029542707,-0.029772557,-0.010769229,-0.0030641262,0.011472305,0.030502675,-0.002039934,-0.0176445,0.008910134,-0.02198464,0.020443283,0.01746873,0.039723784,-0.035370123,0.01984837,0.026757443,-0.0067333034,-0.016833259,-0.009295474,-0.005648268,-0.005506301,-0.015738083,0.018185327,0.0020264133,0.013270557,-0.021862954,-0.0011509487,0.01295282,0.0058984007,0.0060133263,0.026257178,-0.00803805,0.006256699,0.008071852,-0.0022427444,-0.024972713,-0.0025232986,-0.028501613,-0.01863151,-0.020902986,0.008315224,0.030259302,0.0004189301,0.031124627,0.0022326037,-0.032611903,0.008660002,-0.025594665,-0.004353662,-0.020673133,0.0019757107,-0.03388285,0.0019317685,0.018901924,-0.010431211,0.026067888,0.010106715,0.0188208,-0.036884442,-0.008538315,-0.0033260896,0.011796801,-0.021362688,0.0017695202,-0.01098556,0.0016495241,-0.007950165,-0.0046984395,-0.0010740497,-0.005780095,0.06760345,0.009748417,-0.011634553,-0.018766716,0.0048201256,-0.011830603,0.0071524447,0.019753726,0.014399534,-0.032314446,0.036424737,-0.016332993,0.0052291267,-0.017996037,-0.005651648,-0.003077647,-0.01197257,0.012371431,-0.0073079327,0.022065764,0.011648074,0.017292961,0.016184265,0.020159347,-0.040345736,-0.018009558,0.021349167,0.011803562,-0.0047728033,-0.048322942,-0.0013723499,-0.016779175,-0.023309669,-0.006195856,0.01118161,-0.02176831,-0.015454148,-0.0027734314,0.027338834,0.022214493,-0.00023851341,0.031638414,-0.029961847,-0.008078611,-0.029069481,-0.010059393,-0.017820269,0.0026382245,0.02120044] | K7: 2025-07-27T18:29:29.434Z
A8: 6 | B8: 301 | C8: computer_programmers_6 | D8: workflow analysis,diagram creation,logical operation understanding,coding,computer programming | E8: Software Development | F8: workflow,charts,diagrams,coding,programming | G8: 1 | H8: developer,system analyst | I8: 24 | J8: [-0.004366161,0.008180591,-0.0076629184,-0.02618334,0.0028097366,0.009467961,-0.02980705,-0.005094989,-0.000464458,-0.027286801,0.01083707,-0.00094764755,-0.0012728958,0.015843509,-0.015189608,-0.004069861,0.01377963,-0.0089707235,0.01102098,-0.015298591,-0.011674882,0.022668615,0.0047101406,-0.024821045,-0.01230835,0.025761029,0.011409234,-0.04198598,-0.0039336313,-0.001501932,0.01603423,-0.013772819,0.0077650906,-0.021660516,0.004904268,-0.0054594036,0.010966488,0.004887239,-0.010189978,-0.0074790083,0.023159042,0.019235628,-0.015175984,-0.014018032,-0.0049860054,0.018840563,0.0011443292,-0.015843509,-0.012274292,0.0061916383,0.0004123076,0.020175613,-0.021864861,0.0024725683,0.00831001,0.020475319,0.005387883,0.008194214,0.004359349,-0.02300919,-0.0041107303,-0.0036441435,-0.004471739,-0.0039472543,-0.013207465,-0.008418993,0.006654819,0.026755506,0.014018032,-0.018581726,0.046454314,0.013248335,-0.02636044,0.011116341,0.029534591,-0.005585416,-0.0037837788,-0.007628861,0.008303198,0.022178188,0.011368365,-0.019508088,-0.0049519483,0.028444754,0.02337701,-0.0027075645,0.0048395586,0.016906101,-0.007404082,-0.006743368,-0.0049178908,0.014508459,0.018132169,0.015489313,0.0162522,-0.0063857655,-0.01533946,0.029125901,-0.00301919,-0.0478711,0.0004997926,0.024453225,-0.019576203,-0.0013035475,-0.021660516,-0.02819954,0.0033257066,-0.015475689,0.026741883,-0.022954699,-0.02521611,0.0341664,0.0010966487,0.0028369827,0.009025215,-0.01855448,0.027164195,-0.020039383,-0.001666259,-0.025883636,0.0045296364,0.022178188,0.015925247,-0.014358606,0.017137691,0.022913828,0.014276869,0.00061047915,-0.003807619,-0.022205435,0.01065316,-0.019944021,0.020938499,0.0074653854,-0.028308524,0.019004038,-0.0073427786,0.03100587,-0.003960877,-0.006654819,0.008923043,0.014753672,-2.9933275e-05,-0.01593887,-0.00037676014,0.015734525,0.011967775,0.01125257,0.0027705708,-0.015462067,-0.013704704,-0.020434448,0.015557427,-0.0052346247,0.008187403,0.022382533,-0.0033257066,0.0055922274,-0.009495207,2.8097367e-05,-0.004308263,-0.0034295816,-0.025570307,0.0048293415,0.006695688,0.016933346,0.004533042,0.0010617399,0.004359349,-0.003913197,0.0016705162,0.01433136,-0.020339089,0.0125739975,0.007261041,-0.00043061344,-0.008078419,0.0034721536,-0.037681125,-0.010189978,-0.0016713677,0.0030770875,0.01437223,0.015584673,-0.03792634,-0.018499987,0.02920764,-0.003967689,0.009665495,-0.004345726,-0.00095956767,0.017260298,-0.007574369,0.010319397,-0.6556461,-0.02548857,-0.010319397,-0.028145049,0.018404627,0.020502564,0.00445471,-0.00070456276,-0.0045500705,0.007642484,0.0321502,0.031850494,0.009406658,-0.00695793,-0.00535042,-0.027423032,-0.011470538,-0.0374904,0.0050541204,0.026469423,-0.009147822,0.0055751987,-0.026483046,-0.0036679837,-0.0088072475,0.0098834615,0.03266787,0.003068573,-0.0019310554,0.011729374,-0.0009970309,0.0071588685,-0.0059804823,-0.01671538,0.061793774,0.0039710947,-0.01065316,0.017709857,0.025188865,0.025393208,-0.004083484,-0.010019692,0.0075675575,0.014930771,-0.011647636,0.027027965,0.026469423,-0.012029079,-0.007989869,-0.016388427,0.007887698,-0.020407204,-0.0022120292,0.019249251,-0.00020711166,0.016933346,0.0059906994,-0.01566641,0.010816635,0.007206549,0.01617046,0.00044955788,-0.041550048,-0.012206177,-0.017505512,0.022232682,-0.031578034,-0.02324078,-0.008923043,-0.0056637484,0.0061201174,0.003702041,-0.006378954,-0.021606024,-0.009563322,0.030787904,0.022954699,-0.0069204667,0.008439427,-0.005609256,-0.0025679292,0.012519506,-0.010298963,-0.018431874,0.041822504,0.011531841,-0.004979194,-0.016102346,0.0113888,-0.0020196047,0.0378446,0.015598296,-0.002452134,-0.02779085,0.0038859511,0.02498452,-0.0070566963,0.012921384,0.016115969,-0.019453596,-0.012587621,-0.009849405,-0.010121864,3.091775e-05,0.014767296,0.019576203,-0.027736358,-0.006600327,0.037054468,0.012151686,0.014399475,-0.01350036,-0.0068864096,0.005217596,0.0055513587,-0.024807421,0.0015726011,-0.010040126,-0.0012916275,-0.037081715,-0.0050915834,-0.00337509,0.017233051,-0.016374806,0.011143587,0.01745102,-0.008902608,-0.00771741,0.0044172467,0.009903897,0.002951075,0.006865975,-0.0016960592,-0.0123151615,-0.014958017,-0.026809998,0.009937954,0.017723478,-0.010074183,-0.040705424,-0.012097194,-0.013493548,0.0063687367,-0.005115424,-0.0035658113,-0.035610434,-0.034002922,0.012969064,0.007601615,0.019739678,-0.0038008075,-0.0066990936,-0.019276498,0.04936963,0.017233051,-0.013084859,0.009495207,-0.018486366,-0.012614867,-0.024276126,-0.01130025,-5.121916e-06,-0.020012137,-0.002767165,0.013895425,0.005455998,0.0031843684,0.0055513587,-0.01634756,-0.023022812,-0.0077378447,0.0074108937,-0.007819583,-0.008875363,-0.006154175,0.01593887,0.0077923364,-0.0018680493,0.015598296,-0.0035692172,-0.009474773,0.01194053,-0.023908306,-0.022232682,0.009393035,0.008119288,0.014917148,0.020938499,-0.014944394,0.0017573626,-0.0005210785,0.03133282,0.008827682,-0.018949546,-0.021851238,0.027518392,-0.027858965,-0.0067297453,-0.011933718,0.033812203,0.035392467,0.0118043,-0.0050404975,0.0217695,0.008017115,-0.019276498,0.009399846,-0.020652417,0.025297849,0.005115424,0.0013324964,-0.016769871,0.0026854272,0.0016483789,-0.0015726011,0.017614495,-0.014426721,0.004488767,-0.0020400393,-0.0058033834,0.0067399624,-0.019249251,0.02190573,-0.025175242,0.013881803,0.0021302914,-0.00234315,0.019576203,-0.0069102496,-0.031360067,-0.0034602333,0.01409977,-0.0009314703,0.022055581,0.014058901,0.018268397,-0.0038280534,-0.028226785,0.03160528,0.032422658,-0.005009846,0.00978129,0.033675972,-0.03917965,0.022995567,0.004488767,0.05841528,0.0036543608,-0.027368538,-0.0009936251,-0.0030089726,0.020570679,-0.0132279005,0.003478965,0.0058578756,-0.0022358694,0.035446957,0.005544547,0.033975676,0.026128849,-0.012178931,0.03266787,0.0030208926,0.021074729,-0.026469423,-0.008201025,-0.017110445,-0.0060690315,-0.0070703193,-9.546719e-05,0.006007728,0.0067774258,-0.016565526,0.007683353,-0.0099652,0.018254774,-0.0044853617,0.013357318,0.012267481,0.014058901,-0.009120576,-0.003383604,0.0055513587,0.030624427,0.0036611722,0.010442004,0.0047339806,-0.0009050758,-0.0051562926,-0.0018901866,0.006682065,0.00780596,0.003821242,0.01837738,-0.00803755,-0.008527976,0.027749982,-0.014631066,-0.01905853,0.0032763234,0.006147363,0.004699923,-0.004042615,-0.028226785,0.041876998,-0.005125641,-0.0055786045,-0.007417705,-0.0011094203,-0.0030924133,-0.003688418,0.015244099,0.006665036,0.006205261,-0.0061201174,-0.012321973,-0.0034619363,-0.016660888,0.020284597,0.005602445,-0.018036807,-0.0037395041,0.0005585416,0.01717856,0.07176579,0.01143648,-0.000520227,0.0118043,-0.022763977,-0.019821417,-0.048661236,-0.027259555,0.032776855,-0.013384564,0.01662002,-0.0062018554,0.006324462,-0.018581726,-0.008929854,0.0045364476,0.01888143,-0.0051052067,0.0009885165,-0.019303743,-0.007949001,-0.026510293,0.011381988,-0.012192555,0.00877319,0.023731207,0.013268769,0.048279792,-0.028335769,-0.028771704,-0.01120489,0.03536522,-0.0046454314,0.025801897,0.00089571,0.05988656,0.027259555,0.03610086,0.01088475,-0.008548412,0.020379957,0.017519135,0.013922672,-0.035065513,0.01433136,0.009215937,-0.025706537,0.022818469,0.002610501,-0.0148899015,0.0061609866,0.0038655167,-0.01855448,0.0036441435,0.016769871,0.023962798,0.0002011516,-0.0005674817,0.00406305,-0.017246675,-0.028444754,-0.0067297453,0.019004038,-0.01969881,0.016333936,-0.012948629,0.0066888765,-0.0011136775,-0.028036064,0.0023176072,-0.013003121,-0.026374063,-0.008902608,-0.0014874577,0.018499987,0.0022358694,0.0061064945,-0.0137660075,0.00020306733,-0.002964698,-0.044356376,-0.04171352,-0.008371313,-0.00015368409,-0.0155438045,0.004161816,-0.029098656,0.0016313501,0.009161444,0.01235603,-0.013786442,-0.0057693264,-0.003647549,0.0015393952,-0.008997969,0.022723107,0.018445496,0.0063959826,0.017042331,-0.017764349,-0.0029425607,-0.03302207,-0.016361183,0.0026139065,0.004676083,-0.013663835,-0.008861739,0.004624997,-0.03269512,-0.0069204667,0.030433707,-0.004274206,0.025883636,0.007247418,0.01304399,0.031087609,0.023594977,0.016238576,0.0119882105,-0.010966488,0.0033427353,-0.008098854,0.02618334,0.030134002,-0.020461695,0.033730466,0.020543434,-0.011811112,-0.0005031983,0.012056325,-0.0043797838,0.021142844,-0.003334221,-0.038280535,-0.012533129,-0.010864316,0.0025679292,-0.002200109,-0.026292324,-0.009161444,-0.0003050267,0.014753672,0.031904988,-0.01754638,0.01396354,-0.029779803,0.0030804933,0.011545463,-0.03067892,0.02213732,-0.008323632,-0.0055275187,-0.034684073,-0.0018816722,-0.00024457483,-0.025938127,-0.015366706,-0.013166597,0.02448047,0.043130312,0.00463862,-0.007921754,0.025011767,-0.0035998689,-0.0014329657,0.004914485,0.0012524615,-0.006154175,-0.016333936,0.0155438045,0.029289378,0.0053163627,0.012301538,-0.011974587,0.036509547,0.023676716,-0.0014031655,-0.0055581704,0.0016304988,-0.015148738,-0.005122235,-0.006256347,0.015244099,-0.018677086,-0.033049315,0.010741709,0.035474204,0.0046488373,0.017382905,0.016020609,0.015584673,-0.0025900665,-0.0064198226,0.018799692,0.016115969,0.0040255864,-0.0018850779,-0.030433707,0.01694697,0.022845713,0.010516929,0.01120489,0.029752558,0.0017020194,-0.0021779716,0.022981944,-0.015448444,-0.0073427786,0.03253164,-0.021701384,0.006627573,-0.018309267,-0.0003071553,-0.00780596,0.02140168,0.013207465,0.014658311,0.025188865,-0.009318109,-0.02392193,0.016960593,-0.026946226,0.046726774,0.008241895,0.059832066,0.02424888,0.02636044,-0.017382905,-0.039615586,0.007955812,-0.009713175,0.0092976745,0.021047482,-0.002845497,-0.0066309785,0.003650955,-0.007492631,-0.002976618,-0.024916405,0.0030907104,0.0065322123,0.0125263175,-0.01557105,0.0048259357,-0.028444754,0.027777229,-0.0043797838,0.0039336313,-0.018064054,-0.020080252,0.000948499,0.00803755,-0.040705424,0.01593887,-0.0033154893,-0.010673594,0.00021424243,-0.0054628095,-0.020952122,-0.0046488373,0.016565526,-0.012499072,-0.01433136,0.002121777,0.022382533,0.019358234,-0.019589825,-0.016538281,0.012560375,0.03160528,0.004730575,-0.010877938,-0.01520323,-0.005653531,0.03027023,-0.0050643375,-0.017628118,-0.050023533,-0.009958388,-0.0014210456,0.0062767817,-0.0046488373,0.023281649,0.0019600042,0.009147822,-0.01290776,0.017560003,-0.0013444165,0.017096823,-0.04244916,0.0063210563,0.0073291557,0.0028489027,0.016660888,0.007887698,-0.012819211,0.0032371574,0.04138657,-0.00035121708,0.016769871,0.0019327584,-0.005411723,-0.03702722,0.017124068,-0.032313675,-0.026741883,0.036482304,-0.01626582,-0.01648379,0.0024163737,-0.010387512,0.003981312,-0.01148416,-0.013268769,0.0044376813,0.0028540115,0.0031077391,-0.0189223,-0.030351968,-0.0019957644,-0.017955068,-0.012635301,0.014440344,-0.01230835,0.01001288,0.0018544262,0.018077675,-0.0055513587,-0.021946598,-0.035310727,0.009672306,0.009611002,-0.0059906994,0.011599956,0.0035385655,0.012165309,-0.006811483,0.010067372,-0.015911624,-0.02558393,0.0038927626,0.0072814752,0.013030367,0.016906101,-0.012587621,-0.026401307,-0.015966116,-0.03133282,-0.04097788,-0.012567186,-0.02337701,0.013629777,0.011198078,0.005391289,-0.029316623,-0.029888788,-0.031251084,-0.037708372,-0.009181879,0.0011681693,0.012185743,0.009760855,0.011742997,0.01657915,-0.02581552,0.0053606373,-0.009467961,-0.0052754935,0.012744285,0.0036611722,0.015353083,-0.012369653,-0.005122235,-0.02649667,0.0068591633,-0.0023176072,-0.001507892,-0.0046488373,-0.04125034,-0.022954699,-0.019617071,-0.0046420256,0.009549699,0.011245758,0.0053402027,-0.021701384,0.016674511,0.0084326165,-0.021428926,-0.020693285,-0.007846829,-0.02066604,-0.004546665,-0.0027348103,-0.014208754,-0.0018118545,0.0033648727,-0.011014168,0.014494836,0.0016492304,-0.0074381395,0.03100587,0.015135115,0.011402423,0.0013750681,-0.025910882,-0.016102346,-0.010019692,-0.0014474401,-0.02567929,-0.0018408033,-0.016197708,0.013582097,-0.011422857,-0.00982897,-0.019072153,0.016892478,-0.035201743,-0.0003082196,0.0015206636,0.0043116687,-0.0021762687,-0.0066377902,-0.033267282,-0.015720902,-0.013241523,0.004601157,9.345834e-06,-0.0145629505,-0.008562034,-0.013949918,-0.0004137976,-0.009072895,0.015475689,-0.03302207,0.016865233,0.1835286,-0.008078419,-0.0006385765,0.025229733,0.006862569,0.02066604,0.027709113,0.0016866935,-0.0030958191,0.019712431,-0.009025215,0.016102346,-0.030379215,-0.005530924,0.0027875993,-0.0152168535,-0.013800065,-0.012696604,-0.027818097,-0.0030430302,0.024030913,-0.009393035,-0.008323632,-0.017750725,0.019208383,0.013146162,-0.016701756,0.007887698,0.019671563,0.011354743,-0.02126545,0.0039234143,-0.0061984495,0.01483541,0.008071607,-0.0029834295,0.02085676,-0.012553563,0.017805217,-0.032259185,0.003136688,0.0033580612,0.013003121,-0.039888043,0.00395066,0.008984346,-0.0045500705,-0.017192183,0.0031179565,0.0043184804,-0.012458202,0.007049885,0.02879895,0.0472172,0.004863399,0.02424888,-0.009658683,0.012717039,0.008609715,0.011926907,-0.03356699,0.027954327,-0.012608055,-0.006917061,0.0038178363,-0.016797118,-0.0053606373,0.012185743,0.0036168974,-0.013657023,-0.010809824,-0.023513239,-0.008446239,-0.0058306293,-0.022150943,-0.010482873,0.024643946,0.05364724,0.0060281623,0.023663092,-0.014167884,-0.01566641,-0.028008819,-0.033267282,-0.0022733326,-0.0002022159,0.041495554,0.007962624,-0.02879895,0.0016390131,-0.016742626,-0.009379412,-0.01956258,0.0033972273,0.0056944,0.0076561067,0.016892478,0.0065185893,-0.017028708,0.022995567,-0.021333564,0.061630297,0.0017675798,0.032313675,-0.025638422,-0.0009706363,0.0013461193,0.017764349,0.009229559,-0.0045160134,0.0055683875,-0.01969881,0.010080995,0.0007484117,-0.0015470581,0.008500731,-0.005946425,-0.030324722,-0.013445867,-0.007840017,0.0020757995,-0.006126929,-0.0009553105,0.0040766727,-0.001988953,-0.0065969215,-0.0098357815,-0.011307062,-0.017342037,-0.025502192,0.018404627,-0.023172665,-0.0017948258,-0.010271717,-0.019617071,-0.005943019,-0.013302826,-0.00011217661,0.005299334,0.015407574,0.0014082742,0.023417879,-0.009937954,0.0028625256,0.024834666,-0.01212444,0.018772447,-0.00053342426,-0.031496298,-0.03743591,-0.0046965177,-0.008895797,0.010019692,-0.0028335769,0.030842395,-0.01685161,-0.022832092,-0.006470909,0.015189608,-0.0062904046,-0.02934387,0.015189608,0.057270948,-0.00088208704,0.0071316226,-0.005755703,-0.17524584,-0.004519419,0.0012252155,-0.01721943,0.02122458,0.014154262,0.0069340896,0.016837986,-0.0060145394,0.0030072697,7.003056e-05,0.0028386856,-0.042994082,-0.0021149656,0.0016764762,0.012294726,-0.007615238,0.03435712,0.028471999,-0.002096234,0.018322889,0.011865604,0.0046454314,0.0010080995,-0.0007156314,0.009808536,-0.01919476,0.008718698,0.0032201286,0.004597751,0.00060537056,-0.0028097366,0.0022614123,-0.006130335,-0.0007262744,0.0053981002,-0.022096451,-0.031169346,-0.0348203,-0.010510119,0.016987838,0.04348451,0.0021626458,-0.013493548,0.020870384,0.025761029,0.047952842,-0.0061984495,0.0029272349,-0.0023414474,0.007976247,0.0025815521,-0.00028884946,-0.022341665,-0.0036407376,0.001535138,-0.0033427353,0.021892106,-0.03160528,-0.028580982,0.01061229,-0.014045278,-0.0045909397,0.010605479,-0.018908678,-0.0051699155,-0.02029822,0.036182597,-0.003913197,-0.0138136875,-0.006811483,-0.011742997,0.010986922,-0.01409977,0.01194053,-0.0076765413,-0.021987468,0.00817378,0.03550145,0.0007462831,0.012819211,0.011654448,0.008800436,0.00073095725,0.019739678,-0.014944394,-0.001844209,-0.002898286,0.0066207615,-0.009944765,0.020870384,-0.014903525,-0.0021285885,-0.020475319,0.022491517,0.004260583,-0.007022639,-0.010448815,0.01731479,-0.0071248114,0.009168256,0.027586507,-0.021088352,0.0002720336,0.013248335,0.03054269,0.010925619,0.016006986,0.052257698,0.007063508,-0.033812203,0.026237832,0.0064981547,0.009427093,0.0017539569,0.024548585,-0.007819583,-0.012383277,-0.007288287,-0.006668442,0.040351227,0.020952122,0.0077719023,0.0018765635,-0.0056841825,0.003439799,-0.098412305,-0.039288633,0.008051173,0.014631066,-0.020693285,0.0037190698,-0.015026132,0.0098834615,-0.012744285,0.036346074,-0.0006232507,-0.019072153,-0.035719417,-0.029098656,0.009100141,0.0030958191,-0.015067001,-0.0023635847,0.023853814,0.031060362,-0.011926907,-0.03689099,-0.003715664,-0.011525029,-0.007104377,0.0073291557,-0.017696233,-0.01814579,0.025052635,0.009542888,0.023022812,-0.017709857,0.018350136,-0.007867263,0.011981399,0.0024998144,-0.020638794,-0.054682586,0.056508064,-0.016660888,-0.0006819997,-0.000390596,0.02438511,-0.019480841,0.00466246,-0.010823446,-0.013861368,0.011518218,-0.02163327,-0.027245931,-0.024099028,-0.031632528,-0.036209844,-0.013704704,0.016388427,-0.014535705,0.018867807,-0.0093453545,-0.009863027,0.002765462,-0.0020451478,-0.0059906994,-0.0123151615,0.007492631,0.015870756,-0.017369282,-0.011136775,-0.021101974,0.010694029,-0.013248335,-0.018472742,0.0051052067,-0.027640998,0.012465014,-0.01905853,-0.012342407,-0.018636217,0.0073223445,0.013098482,-0.0068285116,0.008820871,-0.03007951,0.028281277,-0.0024572425,0.030706165,0.020829516,-0.022791222,0.0033512497,0.009318109,-0.034466103,0.01919476,0.006375548,0.0058919326,-0.016511034,0.013221089,-0.031850494,0.007921754,-0.0071384343,-0.019126644,0.010925619,-0.008786813,-0.008868551,-0.067896865,0.019113021,-0.011402423,0.014576574,0.010189978,0.011061848,0.0011000545,-0.00022882326,-0.001793123,0.00084079243,-0.013152974,0.0028489027,-0.01377963,-0.010087807,-0.015489313,-0.0059362072,0.019535333,0.00012622529,0.0107962005,0.0073087215,0.0015496124,0.002544089,-0.0027092674,0.013418621,-0.010128675,-0.0009663792,-0.015557427,0.009134199,-0.008916231,-0.0065151835,-0.00808523,-0.009433904,0.013874991,0.028553737,-0.015748149,-0.007417705,0.004624997,0.008875363,0.03141456,0.049396876,-0.010952865,-0.034275383,-0.0030532472,-0.021728631,-0.016442921,-0.015898002,-0.010489684,0.0017045736,0.0059804823,-0.0011366663,0.010673594,0.014113393,-0.005401506,-0.03844401,0.010755332,-0.015884379,0.007628861,0.011702128,0.012144874,-0.0010063966,0.021469794,0.0045636934,-0.0045126076,-0.009924331,-0.0107962005,0.011749809,-0.024357863,0.02122458,0.013357318,-0.019044906,-0.03866198,-0.010898373,-0.031850494,0.019957645,0.015884379,-0.017028708,-0.012008645,0.03264063,-0.009311297,0.018949546,0.015625542,0.0028267654,-0.012969064,0.038416766,0.012771531,0.0040528323,-0.02967082,0.004601157,-0.00840537,0.029834297,-0.024671191,0.008153345,-0.008923043,0.0008471782,-0.015693657,0.015407574,-0.006930684,-0.014917148,-0.004049427,0.016960593,0.015244099,0.0032184257,-0.00088208704,-0.022682238,-0.024289748,0.017478265,0.00087697845,-0.029616328,-0.00036122146,0.02879895,0.011143587,-0.010673594,0.024766553,-0.009243183,-0.013806876,0.009331732,-0.01313254,-0.031060362,-0.034329876,0.0068830037,-0.010360266,0.012921384,0.018690709,-0.007506254,0.029970525,0.04321205,0.0058851214,-0.026428554,-0.0014576573,-0.014031655,0.010455626,-0.0076492955,-0.020802269,-0.013152974,-0.013738762,-0.0005210785,-0.019371858,0.00027586505,-0.011422857,0.064845316,0.027068833,0.0006385765,-0.0074381395,-0.02163327,0.013588909,0.016551904,-0.010189978,0.011034602,-0.035610434,0.044465363,-0.013513982,-0.009072895,-0.030924134,-0.020584302,-0.0067910487,-0.016769871,0.019712431,-0.0033921185,0.016279444,-0.013922672,0.0017216024,0.03403017,0.009113764,-0.030815149,-0.022341665,0.0331583,-0.013949918,-0.010789389,-0.040487457,-0.024466848,0.008119288,-0.009175068,-0.0056603425,-0.000494684,0.0024010479,0.00093743036,-0.004175439,0.017396528,0.03898893,-0.0006181421,0.026292324,-0.037217945,-0.022396157,-0.014426721,0.00045126074,-0.024276126,-0.0044206525,-0.007247418] | K8: 2025-07-27T18:29:36.952Z
A9: 7 | B9: 302 | C9: computer_programmers_7 | D9: Technical Writing,Programming Knowledge,Version Control Systems,Attention to Detail,Documentation Tools,Communication Skills | E9: Software Development | F9: Documentation,Code Comments,Revision Tracking | G9: 1 | H9: Technical Writer,Developer | I9: 16 | J9: [-0.007652403,0.011088867,0.020917019,-0.009285909,0.022475967,0.025878541,-0.030799396,-0.0113871,0.0010938055,-0.022489524,0.035164453,0.008018416,0.009977269,0.0049716895,-0.009326578,-0.002436704,0.026691906,0.0052055316,-0.007306723,-0.03223634,-0.0068593724,0.0033212376,-0.011651444,-0.0045819525,-0.008431877,0.01207846,-0.0012412278,-0.042674515,-0.008079419,0.006296796,0.015101464,-0.013867862,0.020754347,-0.032073665,-0.017528001,-0.02105258,-0.013488292,-0.016579077,0.008933452,-0.010919416,0.014003423,0.039149936,0.0011556551,0.010336505,0.019452963,0.020659454,-0.00717794,-0.014193208,-0.005968061,0.024821168,-0.009712926,0.010878748,-0.02453649,-0.0038533136,0.0032212618,0.00983493,0.008547104,0.021567712,-0.012885047,-0.02004943,-0.013061276,0.0068356493,-0.004680234,-0.0034771326,-0.0038600916,0.002046967,-0.0119429,0.015209913,0.005835889,-0.0028806655,0.026935916,0.009211351,0.027193481,0.008011639,0.021296589,-0.0085267695,-0.0029009995,0.008350541,0.007611735,0.0052733123,0.0017690675,-0.0055986578,0.0015504757,0.0069102077,0.0063476306,0.010763521,0.021039024,0.00614429,0.00013714933,-0.015901273,-0.0133256195,0.0115836635,0.022611529,0.01611817,-0.0021316924,-0.003092479,0.0075575104,0.027410379,-0.01866671,-0.031070517,0.017785568,0.022462413,-0.0078693,-0.0074083935,-0.031775434,-0.0033585168,0.013474735,-0.0017089123,0.014559221,-0.012844378,-0.031558536,0.024712719,0.0027044364,-0.021296589,0.012729152,-0.0045650075,0.0021791386,-0.030257154,-0.0028315247,-0.03654717,0.018815828,0.005608825,0.015291249,-0.029877583,0.014179652,0.035625357,0.0015445449,-0.011014309,-0.0064425236,-0.0057511637,0.027925508,-0.00016341421,0.0124715865,0.013217171,-0.0037143638,0.0012124212,-0.010417841,0.019168286,-0.011000752,-0.010160276,0.010702519,0.023004655,-0.015833493,0.0049411883,0.011346432,-0.012756264,0.02833219,0.012525811,0.032100778,-0.012796932,0.008262426,-0.01788046,0.02871176,-0.013678077,-0.00914357,0.0032720969,0.0032636244,-0.00085572706,0.0026722408,-0.01190901,-0.008174311,0.012763042,0.0017572059,0.003758421,-0.00035415238,0.028603313,0.019642748,0.006771258,0.009028344,-0.011278653,-0.0043243873,0.0073202793,-0.04625332,0.010519512,-0.00037724007,0.01866671,-0.0034229083,-0.011848007,-0.009584143,-0.0016640079,0.0043853894,-0.0011997124,0.019208955,0.029877583,-0.036086265,0.0034906885,0.01698576,0.017216211,0.006296796,-0.024319593,0.043542106,0.025797205,-0.009984047,-0.020767903,-0.6641391,-0.028847322,-0.009028344,-0.010336505,0.013393399,0.011787005,0.031206079,0.015535259,-0.017283993,0.020767903,0.015779268,0.023519786,-0.01756867,-0.00748973,-0.016348623,-0.020686567,-0.011434547,-0.03275147,0.01649774,0.019412296,-0.021716828,0.01667397,-0.0048124054,-0.020266328,0.010472066,-0.027722169,0.0044735037,-0.0055579897,0.017487334,0.025173627,-0.020076543,0.023831574,0.015101464,-0.0119700115,0.056718607,0.0062595163,-0.0044735037,0.002040189,0.013725523,0.044030122,-0.017148431,0.0058494452,-0.008343763,0.020659454,0.0010065384,0.011095645,0.012491921,-0.0028501642,-0.026841024,-0.03299548,-0.0006820399,-0.017229768,-0.009828152,0.016307956,0.01273593,-0.007977748,0.0053987056,-0.012247912,0.0062222374,-0.0049276324,-0.0113871,0.0171891,-0.03161276,-0.003568636,-0.02806107,0.018734492,0.0032568465,0.0007472785,0.00085572706,-0.008879228,-0.020225659,-0.0015665736,0.006601807,-0.027817061,-0.0057003284,0.036601394,0.017772011,-0.02667835,0.00849288,0.012369916,-0.008397987,-0.021418594,-0.00096078665,-0.011237984,0.028874435,-0.0006295101,-0.0073677255,-0.033049703,0.016036833,-0.003355128,0.020700123,0.018165138,-0.012641038,-0.008377653,-0.009685813,0.023533342,0.002706131,-0.0050767493,0.0101128295,-0.00079980824,-0.016701082,-0.007354169,0.004127824,-0.0037041968,0.0018758215,0.0016072418,-0.022489524,0.0036838627,0.021960838,0.008784335,-6.7039015e-05,-0.0052699232,-0.0033585168,-0.011536217,0.0044531696,-0.024238257,0.015657263,0.008730111,-0.0042837188,-0.030013144,-0.008757222,0.021594822,0.016511297,-0.0101128295,-0.0040498767,0.023357112,0.0008641996,0.010472066,-0.007137272,-0.015779268,0.013589962,0.0028874434,-0.0030653668,0.00019984617,-0.02343845,-0.009123237,0.0131697245,-0.023248663,0.00253668,-0.03234479,-0.009509585,-0.004121046,-0.0027434102,-0.007096604,-0.0019147953,-0.032480348,-0.028901545,0.0007909121,0.0021096638,0.008472545,-0.0012641037,0.0023655347,-0.008201424,0.028765986,0.0032771805,-0.017690673,0.0003217449,-0.013989867,-0.005781665,-0.03958373,0.0020368,-0.0074287276,-0.015860604,-0.008418321,0.0026366562,-0.0075914003,-0.0058968915,0.027817061,-0.028765986,-0.031422976,0.0049886345,0.020632342,-0.0031009514,-0.0035042446,-0.01422032,0.015196357,-0.007964193,-0.009821374,-0.0004956439,-0.0036059152,-0.0007388059,0.010282281,-0.021215253,-0.018409146,0.026800355,0.0055105435,0.02212351,0.016646856,0.002223196,-0.00071974273,-0.019629193,-0.008262426,0.0028959159,0.0034872997,-0.0051174173,0.03792989,-0.0035313568,-0.0004414196,-0.017866904,0.04172559,0.021215253,0.00541904,-0.0022943653,-0.013752636,0.011929343,-0.026027659,0.008153978,-0.017677119,0.032073665,0.00793708,0.008357318,-0.011170204,0.0013191752,0.01788046,0.023113104,0.0017995687,-0.023831574,0.022625085,-0.028738873,-0.012986717,0.006564528,-0.02315377,0.025512528,-0.03212789,0.0218795,0.029145556,0.012993495,0.040288646,0.00717794,-0.01173278,-0.0097264815,-0.010512734,0.016213063,-0.017351773,0.019344516,0.017690673,0.0016080891,-0.04335232,0.044897713,0.025187183,-0.0020062986,0.002975558,0.0128986025,-0.04159003,0.022137066,0.015250581,0.05053704,-0.0031043405,-0.01491168,-0.01618595,-0.0059578936,0.010397508,-0.020686567,0.0031229802,0.019764753,0.015277693,0.03665562,-0.014437217,0.023235109,0.032805696,0.011183759,0.005059804,0.019005613,0.008858893,-0.017717786,-0.00049225485,-0.007672737,-0.018382033,0.0078015197,-0.0122411335,0.030419827,-0.0075778444,-0.00980104,0.0051377513,-0.005947727,0.008160756,-0.011353211,0.021405037,-0.002685797,0.023479117,-0.016104614,-0.008784335,0.008716554,0.01276982,0.013359509,0.010431398,-0.0140983155,0.0005532572,-0.007740517,0.03085362,-0.000892159,0.0151421325,0.009109681,0.011441325,0.022692865,0.0050360807,0.0040125973,-0.016375735,-0.014708338,-0.0014937097,-0.003538135,-0.0038024783,-0.0151421325,-0.023696015,0.023858687,-0.0038160344,-0.022421744,-0.018151581,-0.0035245789,-0.014721895,0.021621935,-0.0014394855,-0.006540805,-0.0122411335,0.0073880595,-0.020076543,-0.007327057,-0.015453923,0.01649774,0.018056689,-0.0045378953,0.0040498767,0.0042599957,0.016755305,0.07661892,0.009130015,-0.014301657,0.018273585,-0.014342325,-0.03145009,-0.048476513,-0.008194646,0.02288265,-0.012532589,0.014572778,0.002250308,0.005130973,-0.013230726,-0.001347982,0.006710256,0.0021825277,-0.017161988,-0.013752636,-0.026719019,0.002467205,-0.0132849505,0.018680267,-0.024861837,0.029986031,0.013610297,0.01908695,0.021974394,-0.0019300458,-0.024414485,0.0015818242,0.023601122,-0.0029518348,0.0070288237,-0.011434547,0.04009886,0.013596741,0.020130767,0.006727201,-0.021784607,0.008350541,0.014694782,0.018110912,-0.026556347,0.033239488,0.0012047959,-0.0038905928,0.025417635,-0.016511297,-0.018219361,0.008486101,0.019629193,-0.027152812,-0.004182048,0.008133643,0.01826003,0.005025914,0.009048678,-0.006147679,-0.038878817,-0.025132958,-0.034540873,-0.0064696353,-0.00093282724,0.0062798504,0.0009218129,-0.001724163,-0.014545666,-0.026651239,-0.003548302,0.0036872516,-0.026908804,-0.0133256195,-0.0015606428,0.014166095,-0.007157606,0.021188142,-0.00973326,-0.017744899,-0.00019698667,-0.045819525,-0.030528275,-0.0016851892,0.0023790908,0.0008620815,0.010261946,-0.033808846,0.013989867,-0.011244762,0.010817746,-0.013000273,0.0068187043,0.003285653,-0.020713678,-0.00017347536,-0.006876318,0.018585375,0.014816787,0.016335066,-0.007862522,-0.009258797,-0.028793098,-0.00414138,-0.032426126,0.016524851,-0.0020113823,-0.011665001,0.03250746,-0.016213063,0.016579077,0.03188388,-0.016104614,0.018720936,-0.00038295906,-0.00673059,0.03185677,0.023899356,-0.0070288237,0.038905926,-0.020998357,0.0019452964,-0.03245324,0.027193481,0.030040257,-0.0041684923,0.01756867,0.017148431,-0.011258318,-0.010777078,0.001670786,-0.0127833765,0.006364576,-0.017609337,-0.014477885,-0.011739559,-0.029986031,0.0068559838,-0.010051828,-0.009245241,-0.0031416197,-0.017487334,0.0094553605,0.015291249,0.014816787,0.013122278,-0.02343845,-0.008323428,-0.0014776118,-0.012566479,0.047581814,-0.0017690675,-0.00062908645,-0.02558031,-0.0027349375,0.0017097596,-0.043298095,-0.005622381,-0.021025468,0.022218402,0.026963027,-0.00059731444,-0.0025925988,0.02408914,-0.005947727,-0.005046248,0.021825276,0.0038533136,0.0015292944,-0.021798164,0.0021045802,0.027071476,-0.009943379,0.010980419,-0.008899561,0.033917293,0.0109261945,-0.0007345697,-0.0052699232,-0.0033314049,-0.018531151,-0.0010463593,-0.013989867,0.01263426,0.005219088,-0.02944379,0.01618595,0.028115295,0.018693823,0.00177754,0.03296837,0.012525811,0.01598261,-0.01042462,0.0062629054,0.041047785,-0.031775434,0.018693823,-0.035571136,-0.0016818002,0.017975353,0.017528001,0.0038702586,0.02109325,0.0018165137,-0.016036833,0.014789674,-0.014193208,-0.0052970354,0.0035042446,-0.0013496764,-0.014044091,-0.013352731,0.008458989,0.0072321645,0.006527249,0.0072253863,0.010960084,0.029769136,-0.006428967,-0.03741476,0.025105845,-0.028874435,0.03733342,0.009197795,0.019493632,0.040397096,0.025322743,0.0042159385,-0.010173832,0.011170204,-0.0066390866,0.022584416,0.042159386,-0.0053580375,-0.016091058,-0.0047107353,0.009502807,-0.0026824079,-0.019263178,-0.0018893776,-0.0066729765,-0.014830343,-0.016131725,0.013413734,-0.02585143,0.021865945,0.0055071544,0.008791113,-0.005090305,-0.0036465835,0.0014937097,0.01504724,-0.034432422,0.010960084,0.018544707,-0.008201424,0.02464494,-0.010228056,-0.023221552,0.017283993,-0.008675886,0.006581473,-0.01276982,-0.00013153626,0.035815142,0.015575927,-0.008052307,-0.028250854,0.018815828,0.032290563,0.0052089207,-0.03364617,0.002706131,-0.007977748,0.0060256743,-0.0026247946,-0.015399698,-0.02774928,-0.022259071,-0.023723127,-0.0003369955,0.029037107,0.0082963165,-0.002146943,-0.001860571,-0.01491168,-0.00025354093,-0.008004861,0.005805388,-0.0345951,-0.017094208,0.0066119744,0.0010726242,0.0018487093,0.012498699,0.003255152,0.0059612826,0.040288646,-0.01580638,-0.0031178966,0.0047852937,-0.009035123,-0.0072186086,0.0010446648,-0.016063945,-0.029226892,0.032805696,-0.035598245,-0.027315486,-0.011814117,-0.009333355,0.011712447,-0.017243324,-0.008669108,0.018720936,-0.0015021822,0.01694509,-0.019507188,0.0003463153,0.018761603,-0.016511297,-0.007957415,0.040641103,-0.01763645,0.003544913,0.019073393,0.0006278156,-0.021621935,-0.04169848,-0.022841983,-0.0005702023,0.02495673,-0.011170204,-0.011359989,0.020862795,-0.008201424,-0.019547855,0.020266328,0.009394358,-0.017473778,-0.0021401648,0.008553881,0.009414692,0.027017253,-0.015955497,6.730378e-05,-0.018761603,-0.025404079,-0.041644253,0.0036431944,-0.029226892,0.031558536,0.0048056277,-0.00828276,-0.02167616,-0.029118443,-0.0428643,-0.02495673,-0.017609337,-0.0024519546,0.016890867,0.023357112,-0.0043820003,0.003268708,0.0030840065,0.0072524985,-0.012810488,-0.005808777,0.011739559,0.009916267,0.012580035,0.0027671333,-0.015128577,-0.012573257,0.011298986,0.0027908564,-0.0015970748,0.008255648,-0.010865192,-0.021377927,-0.00372792,0.0065441937,-0.010187388,0.02516007,0.013230726,-0.016470628,-0.009692592,-0.0020435778,-0.01933096,-0.0045751743,0.0073609473,0.0028484697,-0.005215699,0.0069542653,-0.019439409,-0.016782418,0.0032110945,-0.009679035,0.0020486615,0.017351773,-0.02440093,0.016199507,0.018273585,0.0003528815,-0.014003423,-0.00027112145,-0.0031077296,0.011088867,-0.0036160822,-0.0075642886,-0.010824524,-0.0028569421,0.0024892339,-0.015996166,0.00033508916,-0.0009743427,-0.0065441937,-0.035435572,-0.009130015,0.019452963,0.011149869,-0.012708818,-0.014884568,0.008994454,-0.0022757256,-0.03275147,-0.011692112,-0.009672258,-0.007496508,0.017663563,-0.014166095,0.0076049566,0.00049945654,0.02078146,-0.022543749,0.004703957,0.20475091,-0.0066526425,0.015277693,0.028901545,0.0017250102,0.026095439,0.032805696,0.0038600916,0.00037258017,0.016524851,0.028006846,-0.01973764,-0.014545666,-0.008879228,-0.009089346,-0.009706148,-0.038743254,-0.020686567,-0.033564836,0.0009345217,0.032046556,0.0003759692,-0.0042532175,-0.02806107,0.028033957,0.027193481,-0.023221552,0.0060426192,0.034161303,0.016280843,-0.005988395,0.003948206,0.002050356,0.0015233636,-0.0013539128,-0.007916747,0.023289332,-0.0003374191,-0.0038194233,-0.016687525,0.010363617,-0.017907571,0.014572778,-0.055579897,0.006710256,0.05452252,0.0019317403,-0.007815076,-0.0050970833,0.0073406133,-0.005642715,0.004490449,0.028603313,0.015291249,0.0013200225,0.026759686,0.00050454005,0.0077540735,-0.0022774201,0.02046967,-0.014654114,-0.0023807853,-0.017555114,0.025404079,-0.004741236,0.011515884,0.01397631,-0.0049411883,0.0015369197,-0.037062302,-0.011183759,-0.024102697,0.008018416,0.009984047,-0.012810488,-0.032100778,0.004093934,0.03047405,0.016335066,0.03589648,-0.021269478,-0.026881691,-0.00015028178,-0.02598699,0.0022452245,-0.009963714,0.026325893,0.0025909042,0.000792183,-0.010621183,-0.012363138,-0.009285909,-0.023994248,0.0012234355,0.004490449,0.028549088,-0.024821168,-0.00824887,0.0024909284,0.007882856,-0.011163426,0.051241953,0.017175544,0.0039820964,-0.0023113103,0.015331917,-0.0076049566,0.015616596,0.0044362247,0.006513693,0.0012937577,-0.024184033,0.010682185,0.006334075,-0.009712926,0.0035008558,-0.0027756058,-0.028142406,0.011787005,0.0016563826,0.028901545,-0.024184033,0.012593592,0.017595781,-0.0026874912,0.0041888263,-0.03188388,0.0033449607,-0.004551451,-0.021445706,0.013501848,-0.020035874,-0.008120087,-0.01497946,-0.003758421,-0.021784607,0.014762563,0.0043447213,-0.027817061,0.015860604,0.023736682,0.00638491,-0.00067653274,-0.008357318,0.004110879,0.0032331233,0.0084115425,0.0014708339,-0.013522183,-0.013617075,-0.024550047,-0.027329043,0.0049954127,0.0041481582,0.016511297,-0.015060796,-0.023519786,-0.003944817,0.006554361,0.0014920152,-0.03172121,0.011204094,0.047852933,0.00066297664,-5.893714e-05,-0.0005536808,-0.1754698,0.009936601,-0.0023587565,-0.019181842,0.020144323,0.0034906885,0.006428967,0.017311104,0.004334554,0.012959605,0.009780706,-0.01276982,-0.016145281,-0.013230726,0.001591144,0.0006235793,-0.014721895,0.0113125425,-0.008303095,0.013196836,0.013935642,0.00090402056,-0.0028010234,-0.00026497885,0.011027865,0.015697932,-0.022394631,0.0012014069,0.021337258,0.0023282554,0.0026146274,0.0012852851,0.017243324,-0.005225866,0.013210393,-0.002529902,-0.010309393,-0.01694509,-0.024590716,0.000630781,0.01207846,0.029606462,0.025973434,-0.015264138,-0.0067983703,0.017839791,0.03364617,-0.0034246028,-0.00042574538,-0.022313295,0.01667397,-0.014694782,-0.0005329231,-0.01656552,0.01991387,-0.009604477,0.007089826,0.010472066,-0.015182801,-0.0066763656,0.007550732,-0.0247805,0.0009412998,0.0010904166,-0.012844378,-0.024021361,-0.011292208,0.0066797547,-0.011332876,0.002902694,-0.0068254825,-0.018341366,-0.01839559,-0.012261467,0.007632069,-0.008709776,-0.021608379,0.009645145,0.0035415238,-0.011936122,0.0041752704,-0.0013005356,0.016904423,-0.0145998895,-0.025566753,-0.011183759,-0.017826235,-0.011983568,0.022109954,-0.012173353,0.014206763,-0.02933534,-0.015575927,-0.004514172,0.021296589,-0.007699849,-0.0062357932,-0.003289042,0.010187388,0.0014581251,0.013678077,0.0013632325,0.00050454005,-0.0135560725,-0.0024485656,0.020442557,0.012559701,0.016280843,0.049859233,0.028413527,-0.027071476,0.022231959,0.0017995687,-0.00064137165,0.012437697,0.01732466,0.012559701,-0.009245241,-0.015345474,-0.00037067386,0.058236886,-0.001218352,-0.017839791,-0.0017106069,0.014694782,-0.016348623,-0.07358236,-0.019168286,0.013481514,0.025553197,-0.012295358,0.018300697,-0.008445433,0.0119429,-0.0053444817,0.01935807,0.014084759,-0.0070017115,-0.027193481,-0.029091332,0.0048632408,0.0064730244,-0.009435026,-0.004097323,-0.0036804737,0.03703519,-0.019954538,-0.022286182,-0.022042174,-0.0053512594,-0.031233191,0.026407229,-0.026881691,-0.0052936464,0.019222511,-0.0032212618,0.0030213096,-0.013271395,0.014586334,-0.02167616,0.00045794106,0.016240174,-0.030745173,-0.030663835,0.026569901,-0.013508626,-0.011448103,0.009604477,0.011800561,-0.04121046,0.004500616,-0.002004604,-0.010505956,0.015521702,-0.016579077,-0.01497946,-0.041454468,4.385204e-06,-0.054305624,-0.029281117,0.009529918,-0.0017605949,0.008303095,-0.005642715,-0.002629878,0.016389292,-0.020862795,0.0067170337,0.0019876591,0.037604544,0.02074079,-0.0098417085,0.0072253863,-0.02833219,0.016484184,-0.025132958,-0.0127833765,0.0058799465,-0.019073393,0.005649493,-0.029009994,0.016511297,-0.002806107,0.001111598,1.1848325e-05,0.0025248185,-0.011400657,-0.015494591,0.006123956,0.005405484,0.0068085375,0.024075584,-0.019886758,-0.015887717,-0.00086928316,-0.034540873,0.006896652,0.031314526,0.0118547855,-0.00092689646,0.0049039093,-0.008886006,0.010031493,-0.008621662,-0.020957688,0.0019114062,-0.017243324,-0.006012118,-0.083288506,0.0051648635,-0.004470115,-0.010865192,0.0074287276,-0.00044565587,0.0077676293,-0.010600848,-0.0015784352,0.0034415477,-0.023587566,-0.0006401008,-0.015996166,-0.026434341,-0.009570587,0.002240141,0.010051828,0.001584366,0.028467752,-0.0023773962,-0.008899561,-0.013190058,0.011298986,0.011271874,-0.019344516,0.015304806,0.0014776118,-0.011319321,-0.023831574,-0.00500558,0.024211146,-0.008174311,0.01732466,0.024102697,0.0099976035,0.011624332,-0.0057071066,0.025715869,0.0071508284,0.030772284,-0.011319321,-0.034540873,0.0016216452,-0.028765986,-0.0007565983,-0.01977831,-0.02667835,0.0019656306,0.02526852,-0.0013505237,0.00448706,0.0076252907,0.0055681565,-0.012539367,-0.014423661,-0.033402164,-0.0006108705,0.009245241,0.03882459,-0.008391209,0.013366288,0.00024443291,-0.010729631,-0.02446871,0.01297994,-0.0200901,-0.0004090121,0.011339654,0.0029789468,-0.015481034,-0.028250854,-0.026420785,0.00071084657,0.014003423,0.0064967475,-0.003755032,-0.016104614,0.039746404,-0.024943173,0.0247805,-0.0027044364,0.02636656,-0.030501163,0.008092975,0.018693823,-0.013867862,-0.01649774,-0.008743667,-0.00021965074,0.004571785,-0.013332397,0.015304806,-0.008486101,0.020212105,-0.013617075,0.022177733,0.020198548,0.0071643842,-0.007476174,0.009502807,-0.0132849505,0.001471681,0.002553625,0.002782384,-0.0455484,-0.00025227002,-0.036248937,-0.030663835,-0.018192248,0.0009836626,0.031694096,-0.005632548,0.02595988,-0.0015801297,-0.02491606,-0.010194167,-0.03272436,-0.0016682441,-0.03150431,0.016023278,-0.024428042,0.01587416,0.036248937,-0.03513734,0.024278926,0.013650965,0.0038092562,-0.03351061,0.004632788,0.0036804737,0.003765199,0.010451732,0.009706148,-0.0004121893,-0.0021554155,0.003744865,-0.030202929,0.0066560316,-0.00862844,0.078516774,0.017690673,-0.016592633,-0.0061205667,-0.0073406133,-0.0068627615,0.014789674,0.0048124054,0.0066255303,-0.015562371,0.016850198,-0.006540805,-0.0042566066,-0.004836129,-0.019818978,-0.001125154,0.006371354,0.023696015,0.008431877,0.0051275846,0.0029552237,0.0037855331,0.03942106,0.0063916883,-0.037008077,-0.012098795,0.035923593,0.006022285,0.001637743,-0.030040257,0.000282983,-0.00080319727,-0.019724086,0.0080251945,-0.005439374,-0.018517595,-0.020564562,-0.009923045,0.01466767,0.026773242,0.031043405,0.01297994,-0.026434341,-0.01971053,-0.03033849,-0.015155689,-0.0140983155,-0.0058833356,0.008560659] | K9: 2025-07-27T18:29:44.144Z
